Workbook
Name ComplejidadEstimación: Sheet1!$B$3:$B$5

Sheet Data maestra
A2: Estimación por complejidad | B2: días calendario
A3: Alta | B3: 28
A4: Media | B4: 14
A5: Baja | B5: 7

Sheet Criterios de priorización
A2: Columna | B2: Criterio nuevo | C2: Descripción general | D2: Peso | E2: Descripción del nivel | F2: Puntaje
A3: Proyecto SPO | B3: Proyectos de la SPO | C3: Proyecto que forma parte de la SPO | D3: 0.3 | E3: Si | F3: 5
E4: No | F4: 0
A5: Tipo de iniciativa | B5: Tipo de iniciativa | C5: Evalúa si es una iniciativa normativa, lega , seguridad Ti, etc | D5: 0.3 | E5: Regulatoria | F5: 5
E6: Seguridad TI | F6: 3
E7: ITSM | F7: 3
E8: Otros | F8: 1
A9: Beneficio cuantitativo (anual) | B9: Beneficio cuantitativo esperado | C9: Mide el valor que genera la atención de la necesidad del negocio (Falta indicar en cuanto tiempo) | D9: 0.15 | E9: Mayor a S/500,000.00 | F9: 5
E10: Entre S/100,000.00 y S/500,000.00 | F10: 3
E11: Menor a S/100,000.00 | F11: 2
E12: No cuantificado o S/0 | F12: 1
A13: Pilar estratégico | B13: Alineación estratégica | C13: Mide el impacto en los pilares estratégicos de la organización. | D13: 0.1 | E13: Crecimiento escalable | F13: 5
E14: Excelencia académica | F14: 5
E15: Experiencia | F15: 4
E16: Student Success y Empleabilidad | F16: 4
E17: Excelencia operativa | F17: 3
E18: Ninguno | F18: 0
A19: Usuarios beneficiados1 | B19: Usuarios beneficiados | C19: Mide impacto en los usuarios que serán beneficiados por la iniciativa | D19: 0.15 | E19: Alumnos | F19: 5
E20: Todos | F20: 5
E21: Docentes | F21: 4
E22: Administrativos | F22: 1
D23: =SUM(D3:D20) -> 1

Sheet Resumen
B1: POR ESTIMAR | E1: POR APROBAR ESTIMACION | H1: POR HABILITAR PPTO | K1: POR PLANIFICAR
B2: Líder de Dominio | C2: TOTAL Iniciativas | E2: IT BP | F2: TOTAL Iniciativas | H2: IT BP | I2: TOTAL Iniciativas | K2: Líder de Dominio | L2: TOTAL Iniciativas
B3: Aaron Melgar | C3: 4 | E3: Bruno Chiappe | F3: 2 | H3: Ángela Lucano | I3: 1 | K3: Alan Medina | L3: 1
B4: Ana Rojas | C4: 2 | E4: Carla Arias-Schreiber | F4: 5 | H4: Bruno Chiappe | I4: 1 | K4: Ana Rojas | L4: 1
B5: Ana Vega | C5: 9 | E5: Franco Vera | F5: 2 | H5: Carla Arias-Schreiber | I5: 2 | K5: Ana Vega | L5: 1
B6: Carmen Cruz | C6: 4 | E6: Gerson Vereau | F6: 1 | H6: Franco Vera | I6: 5 | K6: César Soplín | L6: 1
B7: César Soplín | C7: 17 | E7: José Paredes | F7: 3 | H7: Gerson Vereau | I7: 2 | K7: Elmer Zapata | L7: 1
B8: Cristina Andonaire | C8: 1 | E8: Total general | F8: 13 | H8: José Paredes | I8: 1 | K8: Hugo Paucar | L8: 1
B9: Cristy Vargas | C9: 1 | H9: Total general | I9: 12 | K9: Luis Calderón | L9: 1
B10: Elmer Zapata | C10: 9 | K10: Nicolas Morales | L10: 1
B11: Enrique Ruiz Huidobro | C11: 1 | K11: Nohelí Cabrera | L11: 1
B12: Hugo Vega | C12: 7 | K12: Total general | L12: 9
B13: Ivan Rengifo | C13: 2
B14: Janny Nicasio | C14: 1
B15: Johnnel Ayala | C15: 2
B16: Johnny Rodriguez | C16: 2
B17: Nicolas Morales | C17: 14
B18: Nohelí Cabrera | C18: 2
B19: Pendiente LD | C19: 3
B20: Rolando Lopez | C20: 1
B21: Ruddy Pereda | C21: 3
B22: Tania Tamariz | C22: 1
B23: Total general | C23: 86

Sheet BD
A1: Id | B1: Hora de inicio | C1: Hora de finalización | D1: Correo electrónico | E1: Nombre | F1: Título de la INICIATIVA | G1: Objetivo | H1: Institución | I1: VP del área solicitante | J1: Usuario solicitante del negocio | K1: Aprobación de la iniciativa por el VP o Director | L1: IT BP | M1: Fecha de entrega requerida | N1: Proyecto SPO | O1: Workstream del proyecto SPO | P1: ID SPO | Q1: Tipo de iniciativa | R1: Descripción del problema o desafío | S1: Situación deseada | T1: Procesos y áreas impactadas | U1: Usuarios beneficiados1 | V1: Pilar estratégico | W1: Forma parte de la estabilización de procesos SIS | X1: Beneficio cuantitativo (anual) | Y1: Beneficios cualitativos | Z1: Adjuntar ppt de la iniciativa | AA1: Puntaje sugerido
A2: =[1]Sheet1!A2 -> 15 | B2: =[1]Sheet1!B2 -> 46006.494 | C2: =[1]Sheet1!C2 -> 46008.703 | D2: =[1]Sheet1!D2 -> luis.almeyda@upc.pe | E2: =[1]Sheet1!E2 -> Luis Alberto Almeyda Porras | F2: =[1]Sheet1!F2 -> Mejoras en SPRING - Facturación por nuevo registro de Ventas SIRE | G2: =[1]Sheet1!G2 -> Necesitamos asegurar el envío correcto del 100% de información para el registro de Ventas a SUNAT en Boletas, Facturas, Notas de Crédito y Débito, dado que actualmente se tienen 2 casuísticas que generan incidencias en el reporte y por ende existen observaciones por parte de SUNAT. - Existen saltos en correlativos de las Notas de Crédito y Nota de Débito que generan inconsistencia en la información. - Se ha detectado que la fecha de emisión de las Notas de Crédito y Nota de Débito se generan con una fecha anterior al comprobante fiscal (Factura o Boleta). | H2: =[1]Sheet1!H2 -> UPC | ... AA2: =[1]Sheet1!AA2 -> 2.4
A3: =[1]Sheet1!A3 -> 16 | B3: =[1]Sheet1!B3 -> 46036.44 | C3: =[1]Sheet1!C3 -> 46036.443 | D3: =[1]Sheet1!D3 -> giancarlo.villacorta@upc.pe | E3: =[1]Sheet1!E3 -> Giancarlo Villacorta Quiñones | F3: =[1]Sheet1!F3 -> Mejoras en trámites de retiro de ciclo | G3: =[1]Sheet1!G3 -> Necesitamos que el tramite de retiro de ciclo valide la vigencia de la carta de permanencia durante el periodo actual para que solo considere en el periodo que corresponde, además que el alumno EPE pueda registrar aún si cuenta con notas o haya cursado el módulo A; Para evitar gestiones manuales por falta de recursos / evitar reclamos hacia la universidad o a través de indecopi; logrando que todas las solucitudes de alumnos se registren por el trámite | H3: =[1]Sheet1!H3 -> UPC | ... AA3: =[1]Sheet1!AA3 -> 0.3
A4: =[1]Sheet1!A4 -> 22 | B4: =[1]Sheet1!B4 -> 46042.586 | C4: =[1]Sheet1!C4 -> 46042.665 | D4: =[1]Sheet1!D4 -> alejandro.tello@laureate.pe | E4: =[1]Sheet1!E4 -> Alejandro Tello Llosa | F4: =[1]Sheet1!F4 -> Requerimiento de servicios de CRM para el desarrollo de la plataforma de Admisión Online | G4: =[1]Sheet1!G4 -> Necesitamos la creación de Servicios de integración con CRM para que realicemos las integraciones necesarias en la nueva plataforma de admisión Online logrando implementar una plataforma digital que permita reducir la deserción en las etapas previas a la matrícula, interviniendo en el momento de mayor intención del postulante. | H4: =[1]Sheet1!H4 -> UPN | ... Q4: =[1]Sheet1!Q4 -> Otro | S4: =[1]Sheet1!S4 -> 0 | T4: =[1]Sheet1!T4 -> Proceso de Admisión | U4: =[1]Sheet1!U4 -> 0 | V4: =[1]Sheet1!V4 -> Transformación Digital | W4: =[1]Sheet1!W4 -> No | X4: =[1]Sheet1!X4 -> 0 | Y4: =[1]Sheet1!Y4 -> Mejorar la experiencia del prospecto, reducir la operatividad del equipo de admisión, reducción los tiempos de matrícula en al menos 48 hrs | Z4: =[1]Sheet1!Z4 -> https://educorpperu-my.sharepoint.com/personal/diana_zapata_laureate_pe1/Documents/Aplicaciones/Microsoft%20Forms/REGISTRO%20DE%20INICIATIVAS/Pregunta/funnel-de-desercion-carreras-a-distancia-UPN_Alejandro%20Tello%20Llos.png | AA4: =[1]Sheet1!AA4 -> 1.5
A5: =[1]Sheet1!A5 -> 23 | B5: =[1]Sheet1!B5 -> 46042.744 | C5: =[1]Sheet1!C5 -> 46042.76 | D5: =[1]Sheet1!D5 -> luis.almeyda@upc.pe | E5: =[1]Sheet1!E5 -> Luis Alberto Almeyda Porras | F5: =[1]Sheet1!F5 -> Reporte para Seguimiento de Retiros de Ciclo formales | G5: =[1]Sheet1!G5 -> Se requiere según el control ejecutar una validación al 100% de los retiros formales del mes para alumnos de pregrado y EPE en los ciclos de verano y regulares, actualmente no se cuenta con un reporte que permita hacer esta validación, por lo que la revisión del equipo de facturación realiza es muestral (5% de los retiros mensuales). El promedio entre 2024 y 2025 de retiros formales ascendió a 3.7M USD. | H5: =[1]Sheet1!H5 -> UPC | ... AA5: =[1]Sheet1!AA5 -> 1.2
A6: =[1]Sheet1!A6 -> 24 | B6: =[1]Sheet1!B6 -> 46043.469 | C6: =[1]Sheet1!C6 -> 46043.537 | D6: =[1]Sheet1!D6 -> liz.medina@upc.pe | E6: =[1]Sheet1!E6 -> Carolina Medina Suarez | F6: =[1]Sheet1!F6 -> Mejora del Reporte de Matriculados de Licencias Coursera | G6: =[1]Sheet1!G6 -> Necesitamos optimizar el reporte de matriculados de licencias Coursera reduciendo el tiempo de carga de 25-30 minutos a máximo 5 minutos y habilitando la funcionalidad de descarga, para que el equipo pueda monitorear y gestionar las 28,000 licencias Coursera de forma oportuna durante el periodo de matrícula, logrando maximizar el uso de licencias, recuperar aproximadamente 450 licencias por ciclo de alumnos retirados (ahorro estimado de $22,500 USD), y permitir la toma de decisiones en tiempo casi real para la reasignación eficiente de recursos. | H6: =[1]Sheet1!H6 -> UPC | ... AA6: =[1]Sheet1!AA6 -> 0.3
A7: =[1]Sheet1!A7 -> 25 | B7: =[1]Sheet1!B7 -> 46048.588 | C7: =[1]Sheet1!C7 -> 46048.615 | D7: =[1]Sheet1!D7 -> makarena.ramos@laureate.pe | E7: =[1]Sheet1!E7 -> Makarena Ramos Aleman | F7: =[1]Sheet1!F7 -> Modificación de MDUU de elegibles en Banner. | G7: =[1]Sheet1!G7 -> [SPO] Se requiere mejora de MDUU de asignación de elegibles, que considere cambios aplicados en las marcas de Suspensión y Baja académica. Para asegurar la correcta asignación de los elegibles, excluyendo a los estudiantes que han sido suspendidos temporalmente. Logrando que los alumnos desaprobados por tercera vez tengan la posibilidad de retornar el siguiente ciclo. | H7: =[1]Sheet1!H7 -> UPN | ... AA7: =[1]Sheet1!AA7 -> 0.5
A8: =[1]Sheet1!A8 -> 26 | B8: =[1]Sheet1!B8 -> 46048.615 | C8: =[1]Sheet1!C8 -> 46048.624 | D8: =[1]Sheet1!D8 -> makarena.ramos@laureate.pe | E8: =[1]Sheet1!E8 -> Makarena Ramos Aleman | F8: =[1]Sheet1!F8 -> Actualización de Reportes PF012 y AC006 -Penalidad por 4to curso repetido | G8: =[1]Sheet1!G8 -> [SPO]Necesitamos la actualización de los reportes para que pueda incluir la Validación de carga de las penalidades(PF012), Cierre de Campaña - AC006. Logrando que incluya la casuistica de las penalidades por 4ta en los controles SOX. | H8: =[1]Sheet1!H8 -> UPN | ... AA8: =[1]Sheet1!AA8 -> 0.5
A9: =[1]Sheet1!A9 -> 27 | B9: =[1]Sheet1!B9 -> 46048.633 | C9: =[1]Sheet1!C9 -> 46048.649 | D9: =[1]Sheet1!D9 -> makarena.ramos@laureate.pe | E9: =[1]Sheet1!E9 -> Makarena Ramos Aleman | F9: =[1]Sheet1!F9 -> Mejora en la estimación de penalidades – 4ta repitencia. | G9: =[1]Sheet1!G9 -> [SPO]Mejora del proceso de estimación de penalidad para que genere los cargos con penalidad por cuarta repitencia. Logrando que los alumnos puedan matricularse nuevamente pagando la penalidad correspondiente. | H9: =[1]Sheet1!H9 -> UPN | ... AA9: =[1]Sheet1!AA9 -> 1.4
A10: =[1]Sheet1!A10 -> 28 | B10: =[1]Sheet1!B10 -> 46048.633 | C10: =[1]Sheet1!C10 -> 46048.654 | D10: =[1]Sheet1!D10 -> makarena.ramos@laureate.pe | E10: =[1]Sheet1!E10 -> Makarena Ramos Aleman | F10: =[1]Sheet1!F10 -> Marcación de reingresantes desaprobados por tercera vez (4TAV) | G10: =[1]Sheet1!G10 -> [SPO]Mejorar el proceso de marcación de 3ra repitencia durante el proceso de Reingresos para incluir a los alumnos con 4ta repitencia (reingresos). Esto está vinculado a la ejecución de la decisión de admisión 35.Logrando la automatización en el proceso de reingresos para los de 4ta. | H10: =[1]Sheet1!H10 -> UPN | ... AA10: =[1]Sheet1!AA10 -> 0.5
A11: =[1]Sheet1!A11 -> 29 | B11: =[1]Sheet1!B11 -> 46048.633 | C11: =[1]Sheet1!C11 -> 46048.662 | D11: =[1]Sheet1!D11 -> makarena.ramos@laureate.pe | E11: =[1]Sheet1!E11 -> Makarena Ramos Aleman | F11: =[1]Sheet1!F11 -> Proyección automática de cursos por 4ta vez | G11: =[1]Sheet1!G11 -> Necesitamos contar con un proceso que proyecte de forma automática únicamente a cursos por cuarta matrícula del alumno, para que luego este pueda hacer su matricula en línea de dicho curso: - Reingreso (uno a uno). Logrando que el alumno pueda realizar su matricula de manera satisfactoria en el tiempo establecido. | H11: =[1]Sheet1!H11 -> UPN | ... AA11: =[1]Sheet1!AA11 -> 1.4
A12: =[1]Sheet1!A12 -> 30 | B12: =[1]Sheet1!B12 -> 46048.651 | C12: =[1]Sheet1!C12 -> 46048.669 | D12: =[1]Sheet1!D12 -> gerson.vereau@upn.edu.pe | E12: =[1]Sheet1!E12 -> Gerson Vereau Rosas | F12: =[1]Sheet1!F12 -> Franja horaria no visible para horas adicionales | G12: =[1]Sheet1!G12 -> Establecer en Banner que las franjas horarias de madrugada (00:00 a.m. – 06:00 a.m.) no sean visibles en la plataforma del estudiante. Además, cuando un docente registre su marcación en una franja distinta a la mencionada (es decir, fuera de 00:00 a.m. – 06:00 a.m.), la franja de madrugada debe marcarse automáticamente y viajen para pago ambas franjas horarias | H12: =[1]Sheet1!H12 -> UPN | ... AA12: =[1]Sheet1!AA12 -> 0.3
A13: =[1]Sheet1!A13 -> 31 | B13: =[1]Sheet1!B13 -> 46048.646 | C13: =[1]Sheet1!C13 -> 46048.673 | D13: =[1]Sheet1!D13 -> jose.herbozo@upn.edu.pe | E13: =[1]Sheet1!E13 -> Jose Paredes Herbozo | F13: =[1]Sheet1!F13 -> Incorporar sección de "variable étnica" a la Ficha de Postulación y CRM | G13: =[1]Sheet1!G13 -> SUNEDU requiere que los alumnos de Pregrado, Posgrado (no cursos cortos, no diplomados) dejen registro de 2 preguntas: 1. El postulante por sus costumbres y antepasados se siente parte de: (alternativas pre cargadas) 2. El postulante habla alguna lengua indígena u originaria: (alternativas pre cargadas) Esto con el fin de poder registrar en la BD de SUNEDU la demografía de los estudiantes con fines propios del estado. El equipo Legal y Académico han requerido que UPN sea la universidad piloto para esta disposición de SUNEDU | H13: =[1]Sheet1!H13 -> UPN | ... AA13: =[1]Sheet1!AA13 -> 1.8
A14: =[1]Sheet1!A14 -> 32 | B14: =[1]Sheet1!B14 -> 46048.673 | C14: =[1]Sheet1!C14 -> 46048.69 | D14: =[1]Sheet1!D14 -> jose.herbozo@upn.edu.pe | E14: =[1]Sheet1!E14 -> Jose Paredes Herbozo | F14: =[1]Sheet1!F14 -> Desactivación del proceso automático de reembolsos en el retiro formal | G14: =[1]Sheet1!G14 -> Necesitamos desactivar el proceso automático de reembolsos del retiro formal, para que se deje de generar notas de crédito, notas de débito y envíos erróneos a cuentas por pagar y tesorería, logrando evitar reprocesos, pagos indebidos y carga operativa en las áreas afectadas. | H14: =[1]Sheet1!H14 -> UPN | ... AA14: =[1]Sheet1!AA14 -> 0.3
A15: =[1]Sheet1!A15 -> 33 | B15: =[1]Sheet1!B15 -> 46049.461 | C15: =[1]Sheet1!C15 -> 46049.472 | D15: =[1]Sheet1!D15 -> daniella.poppe@laureate.pe | E15: =[1]Sheet1!E15 -> Daniella Poppe Medina | F15: =[1]Sheet1!F15 -> Lead Scoring - Integración de modelo Lead Scoring a CRM | G15: =[1]Sheet1!G15 -> Necesitamos integrar el Lead Scoring al CRM para que el equipo comercial pueda priorizar de manera más efectiva los leads que recibe para la venta logrando un ratio de conversión mayor. | H15: =[1]Sheet1!H15 -> UPN | ... AA15: =[1]Sheet1!AA15 -> 1.8
A16: =[1]Sheet1!A16 -> 34 | B16: =[1]Sheet1!B16 -> 46049.599 | C16: =[1]Sheet1!C16 -> 46049.717 | D16: =[1]Sheet1!D16 -> eduardo.paul@cibertec.pe | E16: =[1]Sheet1!E16 -> Eduardo Paul Aguilar | F16: =[1]Sheet1!F16 -> Actualización en Gestión Docente sobre cambios realizados en Banner | G16: =[1]Sheet1!G16 -> Necesitamos incluir en el proceso de sincronización de datos de Banner hacia Gestión docente, aquellos cambios de sección que ocurre en Banner y que no son reflejados en Gestión docente para que se eviten registros duplicados en el sistema y registros faltantes logrando validación de datos por parte de docente, eliminación de ticket por este escenario. | H16: =[1]Sheet1!H16 -> CIB | ... AA16: =[1]Sheet1!AA16 -> 0.3
... A367: =[1]Sheet1!A367 -> 397 | B367: =[1]Sheet1!B367 -> 46287.75 | C367: =[1]Sheet1!C367 -> 46287.762 | D367: =[1]Sheet1!D367 -> anthony.lazaro@laureate.pe | E367: =[1]Sheet1!E367 -> Anthony Adrian Lazaro Espadin | F367: =[1]Sheet1!F367 -> Automatización de Autorización de acceso a Bases de DP | G367: =[1]Sheet1!G367 -> Necesitamos automatizar y centralizar la gestión de solicitudes de acceso a base de datos, para eliminar la gestión manual mediante correos y asegurar un flujo estandarizado de validación, aprobación y atención de requerimientos, logrando mayor trazabilidad, control de conformidades, reducción de tiempos de atención y una mejor experiencia para los usuarios. | H367: =[1]Sheet1!H367 -> CORP | ... AA367: =[1]Sheet1!AA367 -> 0.6
A368: =[1]Sheet1!A368 -> 0

Sheet BD New
A1: Id | B1: Hora de inicio | C1: Hora de finalización | D1: Correo electrónico | E1: Nombre | F1: Título de la INICIATIVA | G1: Objetivo | H1: Institución | I1: VP del área solicitante | J1: Usuario solicitante del negocio | K1: Aprobación de la iniciativa por el VP o Director | L1: IT BP | M1: Fecha de entrega requerida | N1: Proyecto SPO | O1: Workstream del proyecto SPO | P1: ID SPO | Q1: Tipo de iniciativa | R1: Descripción del problema o desafío | S1: Situación deseada | T1: Procesos y áreas impactadas | U1: Usuarios beneficiados1 | V1: Pilar estratégico | W1: Forma parte de la estabilización de procesos SIS | X1: Beneficio cuantitativo (anual) | Y1: Beneficios cualitativos | Z1: Adjuntar ppt de la iniciativa | AA1: Puntaje sugerido
A2: =IF([2]Sheet1!A3="","",[2]Sheet1!A3+399) -> 401 | B2: =[2]Sheet1!B3 -> 46289.379 | C2: =[2]Sheet1!C3 -> 46289.393 | D2: =[2]Sheet1!D3 -> bruno.chiappe@laureate.pe | E2: =[2]Sheet1!E3 -> Bruno Chiappe Vegas | F2: =[2]Sheet1!F3 -> Automatización de carga de llamadas de Genesys a CRM Cibertec | G2: =[2]Sheet1!G3 -> Necesitamos automatizar la carga de información de llamadas de Genesys hacia CRM Cibertec, para eliminar la ejecución manual y recurrente de cargas masivas que actualmente requiere intervención de especialistas y está sujeta a errores y retrasos, logrando disponer de la información oportunamente para el negocio, reducir la carga operativa del equipo TI y disminuir la necesidad de pases Express asociados a estas cargas. | H2: =[2]Sheet1!H3 -> CIB | I2: =[2]Sheet1!I3 -> Humberto Marotta - Tecnologías y transformación digital | ... AA2: =[2]Sheet1!AA3 -> 0.6
A3: =IF([2]Sheet1!A4="","",[2]Sheet1!A4+399) -> 402 | B3: =[2]Sheet1!B4 -> 46289.48 | C3: =[2]Sheet1!C4 -> 46289.501 | D3: =[2]Sheet1!D4 -> alejandra.beraun@laureate.pe | E3: =[2]Sheet1!E4 -> Alejandra Beraun Ching | F3: =[2]Sheet1!F4 -> Proyecto Cultura y Espacios | G3: =[2]Sheet1!G4 -> Implementar una nueva aplicacion de reservas que mejore la gestión de asignación de salas y que esté correctamente distribuida para el personal administrativo. Para lo cual se está rediseñando el piso 26, de manera que la aplicación converse con el nuevo espacio. | H3: =[2]Sheet1!H4 -> LAU | I3: =[2]Sheet1!I4 -> Álvaro Valdez - VP Operaciones | ... AA3: =[2]Sheet1!AA4 -> 0.7
A4: =IF([2]Sheet1!A5="","",[2]Sheet1!A5+399) -> 403 | B4: =[2]Sheet1!B5 -> 46289.51 | C4: =[2]Sheet1!C5 -> 46289.537 | D4: =[2]Sheet1!D5 -> suly.kong@upn.edu.pe | E4: =[2]Sheet1!E5 -> Suly Kong Paredes | F4: =[2]Sheet1!F5 -> La Defensoría tiene sobrecarga por atención unipersonal y desinformación de los usuarios, quienes acuden de forma presencial por trámites ajenos a sus funciones. La falta de un filtro digital previo genera atenciones prolongadas y dificulta organizar los expedientes con sustento desde el inicio. | G4: =[2]Sheet1!G5 -> Proporcionar a la comunidad universitaria (estudiantes, egresados, docentes y colaboradores) un canal digital estructurado, accesible y confidencial para canalizar petitorios, consultas y denuncias, estandarizando los requisitos desde el origen para optimizar los tiempos de respuesta y asegurar la correcta derivación institucional. | H4: =[2]Sheet1!H5 -> UPN | I4: =[2]Sheet1!I5 -> Martín Santana - Rectorado UPN | ... AA4: =[2]Sheet1!AA5 -> 2.7
A5: =IF([2]Sheet1!A6="","",[2]Sheet1!A6+399) -> 404 | B5: =[2]Sheet1!B6 -> 46290.496 | C5: =[2]Sheet1!C6 -> 46290.509 | D5: =[2]Sheet1!D6 -> brenda.maguina@laureate.pe | E5: =[2]Sheet1!E6 -> Brenda Michelle Maguiña Delgadillo | F5: =[2]Sheet1!F6 -> Implementación de Reloj Fisico-Personal Fiscalizado Presencial. | G5: =[2]Sheet1!G6 -> Necesitamos asegurar que el colaborador deberá realizar su marcación al llegar físicamente a las instalaciones de todas las instituciones inlcuyendo LCT. El registro quedará asociado al marcador y será integrado con el sistema HCM, con veracidad. | H5: =[2]Sheet1!H6 -> CORP | I5: =[2]Sheet1!I6 -> Tairi Ruillier- VP Personas y Cultura | ... AA5: =[2]Sheet1!AA6 -> 0.7
A6: =IF([2]Sheet1!A7="","",[2]Sheet1!A7+399) -> 405 | B6: =[2]Sheet1!B7 -> 46290.505 | C6: =[2]Sheet1!C7 -> 46290.536 | D6: =[2]Sheet1!D7 -> miguel.puccio@upn.edu.pe | E6: =[2]Sheet1!E7 -> Miguel Puccio Wendorff | F6: =[2]Sheet1!F7 -> Configuracion de apertura de beneficios de admisión | G6: =[2]Sheet1!G7 -> - Modificación del calculo sobre el beneficio mayor - Recalculo sobre más de una línea de beneficio - Visualización de los distintos beneficios que se ofrece a alumno en las boletas, detallando cada beneficio en una linea independiente - Creación de tabla intermedia para homologación de categorías | H6: =[2]Sheet1!H7 -> UPC | I6: =[2]Sheet1!I7 -> Alex Pendavis - VP Finanzas | ... AA6: =[2]Sheet1!AA7 -> 1.2
A7: =IF([2]Sheet1!A8="","",[2]Sheet1!A8+399) -> 406 | B7: =[2]Sheet1!B8 -> 46291.414 | C7: =[2]Sheet1!C8 -> 46291.449 | D7: =[2]Sheet1!D8 -> franco.vera@laureate.pe | E7: =[2]Sheet1!E8 -> Franco Manuel Vera Sanchez | F7: =[2]Sheet1!F8 -> LEAN+IA: CALIDAD | G7: =[2]Sheet1!G8 -> Estimar componentes fuera de desarrollo (licencias, almacenamiento, integraciones, etc) para repotenciar, agilizar, simplificar y estandarizar el flujo end-to-end de la gestión integral de aseguramiento de la calidad, apalancando en la Inteligencia Artificial y otras tecnologías como aliadas estratégicas, de tal forma que logremos liberar al equipo de las carga operativa y manual para que puedan enfocar su verdadero talento en actividades de alto valor, análisis estratégico y mejora continua, repotenciando su rol. | H7: =[2]Sheet1!H8 -> CORP | I7: =[2]Sheet1!I8 -> Joaquín Uribarri - VP Academia CIB | ... AA7: =[2]Sheet1!AA8 -> 0.6
A8: =IF([2]Sheet1!A9="","",[2]Sheet1!A9+399) -> 407 | B8: =[2]Sheet1!B9 -> 46292.883 | C8: =[2]Sheet1!C9 -> 46292.893 | D8: =[2]Sheet1!D9 -> percy.romero@laureate.pe | E8: =[2]Sheet1!E9 -> Percy Romero Vegas | F8: =[2]Sheet1!F9 -> APLICATIVO DE CONCILIACION MEDIOS DE PAGO - CIBERTEC | G8: =[2]Sheet1!G9 -> Implementar una herramienta de conciliación automática de medios de pago, que permita integrar y validar diariamente las transacciones provenientes de BCP, Interbank, Scotiabank, BBVA y Niubiz, u otro medio de pago comparándolas contra los registos del sistema Spring Comercial de CIB (tal como lo tiene UPC). | H8: =[2]Sheet1!H9 -> CIB | I8: =[2]Sheet1!I9 -> Alex Pendavis - VP Finanzas | ... AA8: =[2]Sheet1!AA9 -> 1.9
A9: =IF([2]Sheet1!A10="","",[2]Sheet1!A10+399) -> 408 | B9: =[2]Sheet1!B10 -> 46293.341 | C9: =[2]Sheet1!C10 -> 46293.352 | D9: =[2]Sheet1!D10 -> luis.calderon@laureate.pe | E9: =[2]Sheet1!E10 -> Luis Calderon Rodriguez | F9: =[2]Sheet1!F10 -> Upgrade y modernización de Jobs Batch UPN | G9: =[2]Sheet1!G10 -> Necesitamos actualizar y modernizar los jobs batch de UPN, para habilitar su migración y distribución en la nueva infraestructura, logrando reducir riesgos tecnológicos y mejorar la estabilidad y continuidad operativa de los procesos que soportan. | H9: =[2]Sheet1!H10 -> UPN | I9: =[2]Sheet1!I10 -> Humberto Marotta - Tecnologías y transformación digital | ... AA9: =[2]Sheet1!AA10 -> 1.5
A10: =IF([2]Sheet1!A11="","",[2]Sheet1!A11+399) -> 409 | B10: =[2]Sheet1!B11 -> 46294.377 | C10: =[2]Sheet1!C11 -> 46294.38 | D10: =[2]Sheet1!D11 -> angela.lucano@laureate.pe | E10: =[2]Sheet1!E11 -> Angela Lucano Carranza | F10: =[2]Sheet1!F11 -> Adecuación del Reporte de Retiro de Oficio UPC a la nueva normativa académica 2026 | G10: =[2]Sheet1!G11 -> Necesitamos adecuar el reporte de Retiro de Oficio vigente para alinearlo con la nueva normativa académica UPC, logrando una identificación automática, precisa y oportuna de estudiantes sujetos a retiro de oficio, asegurando el cumplimiento regulatorio y la continuidad del proceso académico dentro de los plazos establecidos para noviembre 2026. | H10: =[2]Sheet1!H11 -> UPC | I10: =[2]Sheet1!I11 -> Milagros Morgan - Rectorado UPC | ... AA10: =[2]Sheet1!AA11 -> 2.25
A11: =IF([2]Sheet1!A12="","",[2]Sheet1!A12+399) -> 410 | B11: =[2]Sheet1!B12 -> 46294.694 | C11: =[2]Sheet1!C12 -> 46294.705 | D11: =[2]Sheet1!D12 -> angela.lucano@laureate.pe | E11: =[2]Sheet1!E12 -> Angela Lucano Carranza | F11: =[2]Sheet1!F12 -> UPC: Adecuación de sistemas periféricos para soportar las nuevas mallas curriculares 2027 | G11: =[2]Sheet1!G12 -> Necesitamos adecuar los sistemas periféricos que consumen información académica de Banner para soportar correctamente el versionamiento de mallas curriculares, logrando que estudiantes, docentes y áreas administrativas visualicen información académica correcta y consistente en todos los sistemas. | H11: =[2]Sheet1!H12 -> UPC | I11: =[2]Sheet1!I12 -> Milagros Morgan - Rectorado UPC | ... AA11: =[2]Sheet1!AA12 -> 2.7
A12: =IF([2]Sheet1!A13="","",[2]Sheet1!A13+399) -> 411 | B12: =[2]Sheet1!B13 -> 46294.395 | C12: =[2]Sheet1!C13 -> 46295.15 | D12: =[2]Sheet1!D13 -> miriam.marca@laureate.pe | E12: =[2]Sheet1!E13 -> Miriam Marca Delgado | F12: =[2]Sheet1!F13 -> Aprovisionamiento Alumnos Nuevos y Administrativos | G12: =[2]Sheet1!G13 -> Necesitamos que el proceso de aprovisionamiento de cuentas de alumnos para CIBERTEC y UPC sea adoptado del modelo que tiene UPN | H12: =[2]Sheet1!H13 -> LAU | I12: =[2]Sheet1!I13 -> Humberto Marotta - Tecnologías y transformación digital | ... AA12: =[2]Sheet1!AA13 -> 2.1
A13: =IF([2]Sheet1!A14="","",[2]Sheet1!A14+399) -> 412 | B13: =[2]Sheet1!B14 -> 46295.79 | C13: =[2]Sheet1!C14 -> 46295.793 | D13: =[2]Sheet1!D14 -> jose.herbozo@laureate.pe | E13: =[2]Sheet1!E14 -> José Paredes Herbozo | F13: =[2]Sheet1!F14 -> Actualización del Reporte 01 GDO digital doc pendiente | G13: =[2]Sheet1!G14 -> Necesitamos actualizar el Reporte 01 GDO digital de documentos pendientes, retirando la selección de CRM 2011 del proyecto WebGestionDocumental, para eliminar la información desactualizada o inconsistente sobre los documentos pendientes, logrando un seguimiento confiable que favorezca el enrollment y la retención, proteja el revenue y el EBITDA, y reduzca las contingencias legales y normativas. | H13: =[2]Sheet1!H14 -> UPN | I13: =[2]Sheet1!I14 -> Ivan Olivares - VP Marketing y Comercial | ... AA13: =[2]Sheet1!AA14 -> 0.6
... A44: =IF([2]Sheet1!A45="","",[2]Sheet1!A45+399) | B44: =[2]Sheet1!B45 -> 0 | C44: =[2]Sheet1!C45 -> 0 | D44: =[2]Sheet1!D45 -> 0 | E44: =[2]Sheet1!E45 -> 0 | F44: =[2]Sheet1!F45 -> 0 | G44: =[2]Sheet1!G45 -> 0 | H44: =[2]Sheet1!H45 -> 0 | I44: =[2]Sheet1!I45 -> 0 | ... AA44: =[2]Sheet1!AA45 -> 0

Sheet BD 2
A1: Id | B1: Hora de inicio | C1: Hora de finalización | D1: Correo electrónico | E1: Nombre | F1: Título de la INICIATIVA | G1: Objetivo | H1: Institución | I1: VP del área solicitante | J1: Usuario solicitante del negocio | K1: Aprobación de la iniciativa por el VP o Director | L1: IT BP | M1: Fecha de entrega requerida | N1: Proyecto SPO | O1: Workstream del proyecto SPO | P1: ID SPO | Q1: Tipo de iniciativa | R1: Descripción del problema o desafío | S1: Situación deseada | T1: Procesos y áreas impactadas | U1: Usuarios beneficiados1 | V1: Pilar estratégico | W1: Forma parte de la estabilización de procesos SIS | X1: Beneficio cuantitativo (anual) | Y1: Beneficios cualitativos | Z1: Adjuntar ppt de la iniciativa | AA1: Puntaje sugerido
A2: 401 | B2: 46289.379 | C2: 46289.393 | D2: bruno.chiappe@laureate.pe | E2: Bruno Chiappe Vegas | F2: Automatización de carga de llamadas de Genesys a CRM Cibertec | G2: Necesitamos automatizar la carga de información de llamadas de Genesys hacia CRM Cibertec, para eliminar la ejecución manual y recurrente de cargas masivas que actualmente requiere intervención de especialistas y está sujeta a errores y retrasos, logrando disponer de la información oportunamente para el negocio, reducir la carga operativa del equipo TI y disminuir la necesidad de pases Express asociados a estas cargas. | H2: CIB | I2: Humberto Marotta - Tecnologías y transformación digital | J2: Katia Garvich | K2: https://educorpperu.sharepoint.com/sites/ITCS/Documentos%20compartidos/Aplicaciones/Microsoft%20Forms/REGISTRO%20DE%20INICIATIVAS%20-%20GESTI%C3%93N%20DE%20LA%20DEMANDA%20V3/Aprobaci%C3%B3n%20de%20la%20iniciativa%20por%20el%20VP%20del%20%C3%A1rea%20sol/RE_%20CIB%20Carga%20de%20datos%20de%20llamadas_Bruno%20Chiappe%20Vegas.pdf | L2: Bruno Chiappe | M2: 46326 | N2: No | O2: 0 | P2: 0 | Q2: Otro | R2: Actualmente, la información de llamadas proveniente de Genesys debe cargarse manualmente hacia CRM Cibertec al menos dos veces por semana. El procedimiento requiere intervención técnica directa sobre la base de datos y contempla múltiples actividades manuales, entre ellas ejecución de queries, importación de archivos, creación y eliminación de tablas temporales, validaciones, modificación de estructuras e índices y ejecución de procedimientos almacenados. Esto finalmente provoca la necesidad de gestionar pases Express para atender cargas masivas. | S2: Contar con un mecanismo automatizado que permita trasladar periódicamente la información de llamadas desde Genesys hacia CRM Cibertec, ejecutando las cargas y validaciones necesarias sin intervención manual recurrente y reduciendo significativamente los pases express. | T2: Proceso comercial / seguimiento de llamadas Áreas impactadas: - Command Center | U2: Administrativos | V2: Excelencia operativa | W2: No | X2: No cuantificado o S/0 | Y2: Reducción de errores asociados a cargas manuales. Mayor oportunidad y disponibilidad de la información para el negocio. Menor dependencia de especialistas para tareas operativas recurrentes. Liberación de capacidad del equipo TI para actividades de mayor valor. Reducción de pases Express asociados a cargas masivas. | Z2: https://educorpperu.sharepoint.com/sites/ITCS/_layouts/15/Doc.aspx?sourcedoc=%7BC67FA507-9566-45BD-8F12-A76BA4FD076A%7D&file=Manual%20de%20carga_Bruno%20Chiappe%20Vegas.docx&action=default&mobileredirect=true | AA2: =IFERROR(VLOOKUP(N2,'Criterios de priorización'!$E$3:$F$4,2,FALSE)*'Criterios de priorización'!$D$3,0)+IFERROR(VLOOKUP(Q2,'Criterios de priorización'!$E$5:$F$8,2,FALSE)*'Criterios de priorización'!$D$5,0)+IFERROR(VLOOKUP(X2,'Criterios de priorización'!$E$9:$F$12,2,FALSE)*'Criterios de priorización'!$D$9,0)+IFERROR(VLOOKUP(V2,'Criterios de priorización'!$E$13:$F$18,2,FALSE)*'Criterios de priorización'!$D$13,0)+IFERROR(VLOOKUP(U2,'Criterios de priorización'!$E$19:$F$22,2,FALSE)*'Criterios de priorización'!$D$19,0) -> 0.6
A3: 402 | B3: 46289.48 | C3: 46289.501 | D3: alejandra.beraun@laureate.pe | E3: Alejandra Beraun Ching | F3: Proyecto Cultura y Espacios | G3: Implementar una nueva aplicacion de reservas que mejore la gestión de asignación de salas y que esté correctamente distribuida para el personal administrativo. Para lo cual se está rediseñando el piso 26, de manera que la aplicación converse con el nuevo espacio. | H3: LAU | I3: Álvaro Valdez - VP Operaciones | J3: Alessandra Ravettino | K3: https://educorpperu.sharepoint.com/sites/ITCS/Documentos%20compartidos/Aplicaciones/Microsoft%20Forms/REGISTRO%20DE%20INICIATIVAS%20-%20GESTI%C3%93N%20DE%20LA%20DEMANDA%20V3/Aprobaci%C3%B3n%20de%20la%20iniciativa%20por%20el%20VP%20del%20%C3%A1rea%20sol/VB%20Alvaro%20Valdez%20-%20Archie_Alejandra%20Beraun%20Chi.pdf | L3: Franco Vera | M3: 46325 | N3: No | O3: 0 | P3: 0 | Q3: Otro | R3: Se contará con el proveedor actual de Communal hasta el 30/09 y se está buscando otra alternativa de app de reserva de espacios para el equipo central. | S3: Que la aplicación cumpla nuestras expectativas y nos permite distribuir adecuadamente todos los espacios de LCT en los que se encuentran nuestros colaboradores (salas de reuniones y estacionamiento), mejorando la experiencia del colaborador que asiste a sede | T3: Todos los equipos que asisten de manera presencial a LCT Proceso de reserva de espacios (salas y estacionamientos) | U3: Administrativos | V3: Experiencia | W3: No | X3: No cuantificado o S/0 | Y3: Mejora la experiencia del colaborador que asiste a sede (incluye VPs, visitas, entre otros) | Z3: https://educorpperu.sharepoint.com/sites/ITCS/_layouts/15/Doc.aspx?sourcedoc=%7B56FF1655-E73D-422C-A2B6-33849D7CB5A8%7D&file=Gesti%C3%B3n%20de%20iniciativas%20-%20Archie%201_Alejandra%20Beraun%20Chi.pptx&action=edit&mobileredirect=true | AA3: =IFERROR(VLOOKUP(N3,'Criterios de priorización'!$E$3:$F$4,2,FALSE)*'Criterios de priorización'!$D$3,0)+IFERROR(VLOOKUP(Q3,'Criterios de priorización'!$E$5:$F$8,2,FALSE)*'Criterios de priorización'!$D$5,0)+IFERROR(VLOOKUP(X3,'Criterios de priorización'!$E$9:$F$12,2,FALSE)*'Criterios de priorización'!$D$9,0)+IFERROR(VLOOKUP(V3,'Criterios de priorización'!$E$13:$F$18,2,FALSE)*'Criterios de priorización'!$D$13,0)+IFERROR(VLOOKUP(U3,'Criterios de priorización'!$E$19:$F$22,2,FALSE)*'Criterios de priorización'!$D$19,0) -> 0.7
A4: 403 | B4: 46289.51 | C4: 46289.537 | D4: suly.kong@upn.edu.pe | E4: Suly Kong Paredes | F4: La Defensoría tiene sobrecarga por atención unipersonal y desinformación de los usuarios, quienes acuden de forma presencial por trámites ajenos a sus funciones. La falta de un filtro digital previo genera atenciones prolongadas y dificulta organizar los expedientes con sustento desde el inicio. | G4: Proporcionar a la comunidad universitaria (estudiantes, egresados, docentes y colaboradores) un canal digital estructurado, accesible y confidencial para canalizar petitorios, consultas y denuncias, estandarizando los requisitos desde el origen para optimizar los tiempos de respuesta y asegurar la correcta derivación institucional. | H4: UPN | I4: Martín Santana - Rectorado UPN | J4: Suly Kong Paredes | K4: https://educorpperu.sharepoint.com/sites/ITCS/Documentos%20compartidos/Aplicaciones/Microsoft%20Forms/REGISTRO%20DE%20INICIATIVAS%20-%20GESTI%C3%93N%20DE%20LA%20DEMANDA%20V3/Aprobaci%C3%B3n%20de%20la%20iniciativa%20por%20el%20VP%20del%20%C3%A1rea%20sol/correo%20de%20aprobaci%C3%B3n%20Alex%20Rueda_Suly%20Kong%20Paredes.pdf | L4: Gerson Vereau | M4: 46307 | N4: No | O4: 0 | P4: 0 | Q4: Regulatoria | R4: 7.1 Sobrecarga operativa por atención unipersonal frente a alta demanda:_x000B_La Defensoría Universitaria cuenta con una sola persona a cargo para atender un volumen desbordante de casos de toda la comunidad universitaria, lo que genera cuellos de botella y dificulta el seguimiento oportuno de cada expediente 7.2 Tiempos excesivos en atención presencial poco estructurada:_x000B_Los estudiantes acuden de manera presencial y tardan demasiado tiempo en exponer sus situaciones de forma dispersa, sin tener claridad previa de lo que realmente necesitan ni de qué derecho solicitan tutelar, consumiendo valiosas horas de atención individual. 7.3 Alta recepción de casos que no son de competencia de la Defensoría:_x000B_La gran mayoría de usuarios desconoce las funciones de esta instancia y acude por temas que corresponden a Reclamos, secretarías académicas o comisiones disciplinarias/hostigamiento sexual. Esto convierte a la Defensoría en una mesa de orientación básica, perdiendo tiempo crítico en derivar casos en lugar de atender los expedientes que sí le competen. 7.4 Carencia de un filtro previo y expediente ordenado:_x000B_Al no existir un canal digital previo que filtre la admisibilidad y obligue al estudiante a definir su solicitud (consulta, petitorio o denuncia) con sustentos ordenados desde el inicio, se invierten extensas jornadas en recopilar información dispersa y orientar casos improcedentes. _x000B_ | S4: El nuevo formulario filtra casos fuera de competencia, guía al estudiante para tipificar su trámite y exige evidencias obligatorias para evitar reprocesos. Esto permite a la DU evaluar y priorizar cada expediente en una base centralizada, programando citas presenciales solo cuando realmente se amerite. | T4: Contacto UPN | U4: Todos | V4: Excelencia operativa | W4: No | X4: No cuantificado o S/0 | Y4: Beneficios para el usuario: Asistido (Autoayuda): Guía paso a paso con ejemplos claros, facilitando la distinción inmediata entre consulta, petitorio o denuncia. Ahorro de tiempo: Trámite 100% digital 24/7 desde cualquier campus o modalidad. Carga de pruebas ordenada: Permite adjuntar evidencias de forma secuencial o sustentar petitorios Atención inclusiva y prioritaria: Identificación reservada de situaciones de vulnerabilidad (salud, discapacidad o NEE) para activar ajustes razonables inmediatos. Claridad en la competencia: Delimita los casos que corresponden a la Defensoría frente a otras áreas (como Reclamos u Hostigamiento Sexual), evitando derivaciones erróneas. Trazabilidad y respaldo formal: Genera un cargo de recepción con fecha, hora para control inmediato del usuario y DU | Z4: https://educorpperu.sharepoint.com/sites/ITCS/_layouts/15/Doc.aspx?sourcedoc=%7BA37B411B-E6E0-4B17-AE31-CEC2497430BD%7D&file=PPT%20Implementaci%C3%B3n%20de%20formulario%20DU_Suly%20Kong%20Paredes.pptx&action=edit&mobileredirect=true; https://educorpperu.sharepoint.com/sites/ITCS/_layouts/15/Doc.aspx?sourcedoc=%7B764A2D38-08A7-4D87-B1C4-B9607E08DAD5%7D&file=Copia%20de%20Proyecto%20Formulario%20SIPOC_Suly%20Kong%20Paredes.xlsx&action=default&mobileredirect=true; https://educorpperu.sharepoint.com/sites/ITCS/_layouts/15/Doc.aspx?sourcedoc=%7B17EE13F9-F683-4F1D-9DAC-CC880ED08A74%7D&file=Formulario%20de%20Atenci%C3%B3n%20DU%202026%20vf_Suly%20Kong%20Paredes.docx&action=default&mobileredirect=true | AA4: =IFERROR(VLOOKUP(N4,'Criterios de priorización'!$E$3:$F$4,2,FALSE)*'Criterios de priorización'!$D$3,0)+IFERROR(VLOOKUP(Q4,'Criterios de priorización'!$E$5:$F$8,2,FALSE)*'Criterios de priorización'!$D$5,0)+IFERROR(VLOOKUP(X4,'Criterios de priorización'!$E$9:$F$12,2,FALSE)*'Criterios de priorización'!$D$9,0)+IFERROR(VLOOKUP(V4,'Criterios de priorización'!$E$13:$F$18,2,FALSE)*'Criterios de priorización'!$D$13,0)+IFERROR(VLOOKUP(U4,'Criterios de priorización'!$E$19:$F$22,2,FALSE)*'Criterios de priorización'!$D$19,0) -> 2.7
A5: 404 | B5: 46290.496 | C5: 46290.509 | D5: brenda.maguina@laureate.pe | E5: Brenda Michelle Maguiña Delgadillo | F5: Implementación de Reloj Fisico-Personal Fiscalizado Presencial. | G5: Necesitamos asegurar que el colaborador deberá realizar su marcación al llegar físicamente a las instalaciones de todas las instituciones inlcuyendo LCT. El registro quedará asociado al marcador y será integrado con el sistema HCM, con veracidad. | H5: CORP | I5: Tairi Ruillier- VP Personas y Cultura | J5: Peter Casas Aranguren | K5: https://educorpperu.sharepoint.com/sites/ITCS/Documentos%20compartidos/Aplicaciones/Microsoft%20Forms/REGISTRO%20DE%20INICIATIVAS%20-%20GESTI%C3%93N%20DE%20LA%20DEMANDA%20V3/Aprobaci%C3%B3n%20de%20la%20iniciativa%20por%20el%20VP%20del%20%C3%A1rea%20sol/VB%20Alfredo_Brenda%20Michelle%20Magu.pdf | L5: Franco Vera | M5: 46418 | N5: No | O5: 0 | P5: 0 | Q5: Otro | R5: Actualmente, un colaborador puede registrar su asistencia desde su dispositivo móvil antes de llegar físicamente a su centro de labores. El sistema puede mostrar una hora de ingreso correcta o incluso puntual, aunque la llegada real haya ocurrido después. Cuando existe una discrepancia, se requiere revisar las cámaras para comprobar la hora efectiva de llegada. | S5: La propuesta consiste en instalar marcadores físicos en puntos estratégicos del campus, principalmente en accesos y zonas de ingreso de colaboradores presenciales. El colaborador deberá realizar su marcación al llegar físicamente a las instalaciones. El registro quedará asociado al marcador y será integrado con el sistema HCM. | T5: Todas las areas que tengan personal fiscalizado- con modalidad presencial. | U5: Administrativos | V5: Experiencia | W5: No | X5: No cuantificado o S/0 | Y5: Veracidad de información al registrar su marcación de ingreso y salida al llegar físicamente a las instalaciones de su centro de labores. | Z5: https://educorpperu.sharepoint.com/sites/ITCS/_layouts/15/Doc.aspx?sourcedoc=%7BF44B3260-D237-425E-93E1-0F2ADAD667BC%7D&file=VF.%20Gesti%C3%B3n%20de%20iniciativas%20-%20Proceso%20y%20regist_Brenda%20Michelle%20Magu.pptx&action=edit&mobileredirect=true | AA5: =IFERROR(VLOOKUP(N5,'Criterios de priorización'!$E$3:$F$4,2,FALSE)*'Criterios de priorización'!$D$3,0)+IFERROR(VLOOKUP(Q5,'Criterios de priorización'!$E$5:$F$8,2,FALSE)*'Criterios de priorización'!$D$5,0)+IFERROR(VLOOKUP(X5,'Criterios de priorización'!$E$9:$F$12,2,FALSE)*'Criterios de priorización'!$D$9,0)+IFERROR(VLOOKUP(V5,'Criterios de priorización'!$E$13:$F$18,2,FALSE)*'Criterios de priorización'!$D$13,0)+IFERROR(VLOOKUP(U5,'Criterios de priorización'!$E$19:$F$22,2,FALSE)*'Criterios de priorización'!$D$19,0) -> 0.7
A6: 405 | B6: 46290.505 | C6: 46290.536 | D6: miguel.puccio@upn.edu.pe | E6: Miguel Puccio Wendorff | F6: Configuracion de apertura de beneficios de admisión | G6: - Modificación del calculo sobre el beneficio mayor - Recalculo sobre más de una línea de beneficio - Visualización de los distintos beneficios que se ofrece a alumno en las boletas, detallando cada beneficio en una linea independiente - Creación de tabla intermedia para homologación de categorías | H6: UPC | I6: Alex Pendavis - VP Finanzas | J6: Miguel Puccio Wendorff | K6: https://educorpperu.sharepoint.com/sites/ITCS/Documentos%20compartidos/Aplicaciones/Microsoft%20Forms/REGISTRO%20DE%20INICIATIVAS%20-%20GESTI%C3%93N%20DE%20LA%20DEMANDA%20V3/Aprobaci%C3%B3n%20de%20la%20iniciativa%20por%20el%20VP%20del%20%C3%A1rea%20sol/VB%20Miguel%20Bandach_Cambio%20de%20precios_Miguel%20Puccio%20Wendor.pdf | L6: Gerson Vereau | M6: 46349 | N6: No | O6: 0 | P6: 0 | Q6: Otro | R6: Problema de visualizacion de beneficios. Hoy se está sumando todos los beneficios en una sola línea generando confusión y nula trazabilidad. Existen hoy en día más de 41k combinaciones de descuentos (Ids). | S6: Mayor transparencia y trazabilidad de los beneficios otorgados. Reducción del número de Ids de beneficios para simplificar el proceso de venta. | T6: Admisión / Ventas / Facturación / Becas / Planeamiento / Experiencia / Retención / Contabilidad / Control Interno / Sistemas | U6: Todos | V6: Excelencia operativa | W6: No | X6: No cuantificado o S/0 | Y6: - Minimización de errores al facturar - Mayor trazabilidad de los beneficios - Mayor transparencia para el estudiante - Eficiencia operativa al no contar con lista de IDs de beneficios crecientes (>41k) | Z6: https://educorpperu.sharepoint.com/sites/ITCS/_layouts/15/Doc.aspx?sourcedoc=%7BD56CE3C0-AFCD-45CD-89AE-0194B74B5556%7D&file=Gesti%C3%B3n%20de%20iniciativas%20-%20Proceso%20y%20registro%203_Miguel%20Puccio%20Wendor.pptx&action=edit&mobileredirect=true | AA6: =IFERROR(VLOOKUP(N6,'Criterios de priorización'!$E$3:$F$4,2,FALSE)*'Criterios de priorización'!$D$3,0)+IFERROR(VLOOKUP(Q6,'Criterios de priorización'!$E$5:$F$8,2,FALSE)*'Criterios de priorización'!$D$5,0)+IFERROR(VLOOKUP(X6,'Criterios de priorización'!$E$9:$F$12,2,FALSE)*'Criterios de priorización'!$D$9,0)+IFERROR(VLOOKUP(V6,'Criterios de priorización'!$E$13:$F$18,2,FALSE)*'Criterios de priorización'!$D$13,0)+IFERROR(VLOOKUP(U6,'Criterios de priorización'!$E$19:$F$22,2,FALSE)*'Criterios de priorización'!$D$19,0) -> 1.2
A7: 406 | B7: 46291.414 | C7: 46291.449 | D7: franco.vera@laureate.pe | E7: Franco Manuel Vera Sanchez | F7: LEAN+IA: CALIDAD | G7: Estimar componentes fuera de desarrollo (licencias, almacenamiento, integraciones, etc) para repotenciar, agilizar, simplificar y estandarizar el flujo end-to-end de la gestión integral de aseguramiento de la calidad, apalancando en la Inteligencia Artificial y otras tecnologías como aliadas estratégicas, de tal forma que logremos liberar al equipo de las carga operativa y manual para que puedan enfocar su verdadero talento en actividades de alto valor, análisis estratégico y mejora continua, repotenciando su rol. | H7: CORP | I7: Joaquín Uribarri - VP Academia CIB | J7: Manuel Cortes Fontcuberta | K7: https://educorpperu.sharepoint.com/sites/ITCS/Documentos%20compartidos/Aplicaciones/Microsoft%20Forms/REGISTRO%20DE%20INICIATIVAS%20-%20GESTI%C3%93N%20DE%20LA%20DEMANDA%20V3/Aprobaci%C3%B3n%20de%20la%20iniciativa%20por%20el%20VP%20del%20%C3%A1rea%20sol/VB%20Manuel%20Cortes_Franco%20Manuel%20Vera%20S.pdf | L7: Franco Vera | M7: 46304 | N7: Sí | O7: Digital & IA | P7: 78088 | Q7: Otro | R7: Demasiada carga manual y operativa por parte de los equipos de aseguramiento de la calidad. | S7: Repotenciar, agilizar, simplificar y estandarizar el flujo end-to-end de la gestión integral de aseguramiento de la calidad, apalancando en la Inteligencia Artificial y otras tecnologías como aliadas estratégicas. | T7: Aseguramiento de la Calidad UPN-UPC y todas las áreas que comparten información. | U7: Administrativos | V7: Excelencia operativa | W7: No | X7: No cuantificado o S/0 | Y7: Automatizar procesos que pueden incurrir en errores manuales y entregas fuera del SLA, incluso para entidades auditoras externas. | Z7: https://educorpperu.sharepoint.com/sites/ITCS/_layouts/15/Doc.aspx?sourcedoc=%7B6448B771-797F-4396-B61E-9D4823DF0473%7D&file=Gesti%C3%B3n%20de%20iniciativas%20-%20LEAN%2BIA%20CALIDAD_Franco%20Manuel%20Vera%20S.pptx&action=edit&mobileredirect=true; https://educorpperu.sharepoint.com/sites/ITCS/Documentos%20compartidos/Aplicaciones/Microsoft%20Forms/REGISTRO%20DE%20INICIATIVAS%20-%20GESTI%C3%93N%20DE%20LA%20DEMANDA%20V3/Adjuntar%20ppt%20de%20la%20iniciativa/LEAN%20+%20IA%20Aseg.%20Calidad_TOBE_Franco%20Manuel%20Vera%20S.png | AA7: =IFERROR(VLOOKUP(N7,'Criterios de priorización'!$E$3:$F$4,2,FALSE)*'Criterios de priorización'!$D$3,0)+IFERROR(VLOOKUP(Q7,'Criterios de priorización'!$E$5:$F$8,2,FALSE)*'Criterios de priorización'!$D$5,0)+IFERROR(VLOOKUP(X7,'Criterios de priorización'!$E$9:$F$12,2,FALSE)*'Criterios de priorización'!$D$9,0)+IFERROR(VLOOKUP(V7,'Criterios de priorización'!$E$13:$F$18,2,FALSE)*'Criterios de priorización'!$D$13,0)+IFERROR(VLOOKUP(U7,'Criterios de priorización'!$E$19:$F$22,2,FALSE)*'Criterios de priorización'!$D$19,0) -> 0.6
A8: 407 | B8: 46292.883 | C8: 46292.893 | D8: percy.romero@laureate.pe | E8: Percy Romero Vegas | F8: APLICATIVO DE CONCILIACION MEDIOS DE PAGO - CIBERTEC | G8: Implementar una herramienta de conciliación automática de medios de pago, que permita integrar y validar diariamente las transacciones provenientes de BCP, Interbank, Scotiabank, BBVA y Niubiz, u otro medio de pago comparándolas contra los registos del sistema Spring Comercial de CIB (tal como lo tiene UPC). | H8: CIB | I8: Alex Pendavis - VP Finanzas | J8: Medios de Pago | K8: https://educorpperu.sharepoint.com/sites/ITCS/Documentos%20compartidos/Aplicaciones/Microsoft%20Forms/REGISTRO%20DE%20INICIATIVAS%20-%20GESTI%C3%93N%20DE%20LA%20DEMANDA%20V3/Aprobaci%C3%B3n%20de%20la%20iniciativa%20por%20el%20VP%20del%20%C3%A1rea%20sol/APROBACION%20DIRECTOR_Percy%20Romero%20Vegas.pdf | L8: Franco Vera | M8: 46321 | N8: No | O8: 0 | P8: 0 | Q8: Otro | R8: Situación Actual: 1.- CIB opera con 5 medios de pago: BCP, Interbank, Scotiabank, BBVA y Niubiz (intranet del alumno). 2.- No existe un proceso de conciliación diario automatizado. 3.- La validación de ingresos se realiza de forma reactiva, principalmente por reclamos de alumnos o consultas de áreas internas (Contabilidad. Comercial, Admisión, Cobranzas). | S8: Implementar una herramienta de conciliación automática de medios de pago, que permita integrar y validar diariamente las transacciones provenientes de BCP, Interbank, Scotiabank, BBVA y Niubiz, comparándolas contra los registros del sistema Spring Comercial de CIB (tal como lo tiene UPC). | T8: Medios de Pago, Cobranzas, Contabilidad, Admisión, Ventas, Coemrcial. | U8: Todos | V8: Experiencia | W8: No | X8: Mayor a S/500,000.00 | Y8: Reducción, Riesgo Financiero, Riesgo Operativo, Riesgo Reputacional. | Z8: https://educorpperu.sharepoint.com/sites/ITCS/_layouts/15/Doc.aspx?sourcedoc=%7BF226C316-9D65-443A-AF7A-C4AF217611D6%7D&file=1.-%20Solicitud%20de%20requerimientos%20-%20%20Aplicativo_Percy%20Romero%20Vegas.pptx&action=edit&mobileredirect=true | AA8: =IFERROR(VLOOKUP(N8,'Criterios de priorización'!$E$3:$F$4,2,FALSE)*'Criterios de priorización'!$D$3,0)+IFERROR(VLOOKUP(Q8,'Criterios de priorización'!$E$5:$F$8,2,FALSE)*'Criterios de priorización'!$D$5,0)+IFERROR(VLOOKUP(X8,'Criterios de priorización'!$E$9:$F$12,2,FALSE)*'Criterios de priorización'!$D$9,0)+IFERROR(VLOOKUP(V8,'Criterios de priorización'!$E$13:$F$18,2,FALSE)*'Criterios de priorización'!$D$13,0)+IFERROR(VLOOKUP(U8,'Criterios de priorización'!$E$19:$F$22,2,FALSE)*'Criterios de priorización'!$D$19,0) -> 1.9
A9: 408 | B9: 46293.341 | C9: 46293.352 | D9: luis.calderon@laureate.pe | E9: Luis Calderon Rodriguez | F9: Upgrade y modernización de Jobs Batch UPN | G9: Necesitamos actualizar y modernizar los jobs batch de UPN, para habilitar su migración y distribución en la nueva infraestructura, logrando reducir riesgos tecnológicos y mejorar la estabilidad y continuidad operativa de los procesos que soportan. | H9: UPN | I9: Humberto Marotta - Tecnologías y transformación digital | J9: Christian Quiroz | K9: https://educorpperu.sharepoint.com/sites/ITCS/_layouts/15/Doc.aspx?sourcedoc=%7B4CA4154C-D0E3-4B58-A3FB-440A7E50A586%7D&file=Correo%20de%20aprobaci%C3%B3n%20-%20Humberto_Luis%20Calderon%20Rodrig.docx&action=default&mobileredirect=true | L9: Gerson Vereau | M9: 46311 | N9: No | O9: 0 | P9: 0 | Q9: ITSM | R9: Los jobs batch de UPN presentan componentes y frameworks obsoletos que limitan su migración a la nueva infraestructura, manteniendo la concentración de procesamiento en servidores actuales y generando riesgos de saturación, indisponibilidad y continuidad operativa. De no implementarse la iniciativa, los jobs deberán continuar operando temporalmente en la infraestructura actual, manteniendo estos riesgos. | S9: Contar con los jobs batch actualizados y compatibles con la nueva infraestructura, permitiendo distribuir su ejecución entre los nuevos servidores, reducir la concentración de carga y mejorar su estabilidad, operación y mantenimiento. | T9: Áreas: TI – Aplicaciones e Infraestructura Procesos: Procesos de negocio de UPN soportados por los jobs batch involucrados en la iniciativa. | U9: Administrativos | V9: Excelencia operativa | W9: No | X9: No cuantificado o S/0 | Y9: Mayor estabilidad y continuidad operativa de los procesos batch, reducción del riesgo de saturación y puntos únicos de falla, actualización de componentes obsoletos y reducción de incidencias y tickets asociados a fallas de los jobs. | Z9: https://educorpperu.sharepoint.com/sites/ITCS/_layouts/15/Doc.aspx?sourcedoc=%7B19CFF8EC-55FE-40DF-90A8-70B504935AD4%7D&file=Gesti%C3%B3n%20de%20iniciativas%20-%20Jobs%20UPN_Luis%20Calderon%20Rodrig.pptx&action=edit&mobileredirect=true | AA9: =IFERROR(VLOOKUP(N9,'Criterios de priorización'!$E$3:$F$4,2,FALSE)*'Criterios de priorización'!$D$3,0)+IFERROR(VLOOKUP(Q9,'Criterios de priorización'!$E$5:$F$8,2,FALSE)*'Criterios de priorización'!$D$5,0)+IFERROR(VLOOKUP(X9,'Criterios de priorización'!$E$9:$F$12,2,FALSE)*'Criterios de priorización'!$D$9,0)+IFERROR(VLOOKUP(V9,'Criterios de priorización'!$E$13:$F$18,2,FALSE)*'Criterios de priorización'!$D$13,0)+IFERROR(VLOOKUP(U9,'Criterios de priorización'!$E$19:$F$22,2,FALSE)*'Criterios de priorización'!$D$19,0) -> 1.5
A10: 409 | B10: 46294.377 | C10: 46294.38 | D10: angela.lucano@laureate.pe | E10: Angela Lucano Carranza | F10: Adecuación del Reporte de Retiro de Oficio UPC a la nueva normativa académica 2026 | G10: Necesitamos adecuar el reporte de Retiro de Oficio vigente para alinearlo con la nueva normativa académica UPC, logrando una identificación automática, precisa y oportuna de estudiantes sujetos a retiro de oficio, asegurando el cumplimiento regulatorio y la continuidad del proceso académico dentro de los plazos establecidos para noviembre 2026. | H10: UPC | I10: Milagros Morgan - Rectorado UPC | J10: Miguel Chang | K10: https://educorpperu.sharepoint.com/sites/ITCS/Documentos%20compartidos/Aplicaciones/Microsoft%20Forms/REGISTRO%20DE%20INICIATIVAS%20-%20GESTI%C3%93N%20DE%20LA%20DEMANDA%20V3/Aprobaci%C3%B3n%20de%20la%20iniciativa%20por%20el%20VP%20del%20%C3%A1rea%20sol/Adecuaci%C3%B3n%20del%20Reporte%20de%20Retiro%20de%20Oficio%20UP_Angela%20Lucano%20Carran.pdf | L10: Ángela Lucano | M10: 46328 | N10: No | O10: 0 | P10: 0 | Q10: Regulatoria | R10: En marzo de 2026 se aprobó una nueva política de Retiro de Oficio que modifica los criterios utilizados para identificar estudiantes sujetos a esta medida académica. Actualmente, el reporte SOX-Compliance denominado "Reporte Preliminar de Retiro de Oficio - SOX_UPC_007" fue construido bajo la normativa anterior y no contempla las nuevas validaciones requeridas. | S10: Contar con un reporte automatizado y disponible que: Incorpore la modalidad de estudio del alumno (Presencial, Semipresencial o A Distancia). Evalúe asistencia menor al 10% para alumnos presenciales y semipresenciales. Evalúe falta de conexión al Aula Virtual para alumnos a distancia. Valide el no pago de la primera boleta. Mantenga las validaciones académicas vigentes de notas. Sea utilizado de manera oficial para la ejecución del proceso de Retiro de Oficio del ciclo académico correspondiente. Cumpla los lineamientos SOX y de Compliance. | T10: Gestión académica. Retiro de oficio. Control de matrícula. Seguimiento de asistencia. Seguimiento financiero de estudiantes. Auditoría y cumplimiento SOX. | U10: Administrativos | V10: Excelencia operativa | W10: No | X10: Menor a S/100,000.00 | Y10: Cumplimiento regulatorio, reducción de riesgo SOX y eficiencia operativa. | Z10: https://educorpperu.sharepoint.com/sites/ITCS/_layouts/15/Doc.aspx?sourcedoc=%7BF5F7A701-FCD7-4860-9BB9-53DF574BB443%7D&file=Gesti%C3%B3n%20de%20iniciativas%20-%20RETIRO%20DE%20OFICIO%20DOA_Angela%20Lucano%20Carran.pptx&action=edit&mobileredirect=true | AA10: =IFERROR(VLOOKUP(N10,'Criterios de priorización'!$E$3:$F$4,2,FALSE)*'Criterios de priorización'!$D$3,0)+IFERROR(VLOOKUP(Q10,'Criterios de priorización'!$E$5:$F$8,2,FALSE)*'Criterios de priorización'!$D$5,0)+IFERROR(VLOOKUP(X10,'Criterios de priorización'!$E$9:$F$12,2,FALSE)*'Criterios de priorización'!$D$9,0)+IFERROR(VLOOKUP(V10,'Criterios de priorización'!$E$13:$F$18,2,FALSE)*'Criterios de priorización'!$D$13,0)+IFERROR(VLOOKUP(U10,'Criterios de priorización'!$E$19:$F$22,2,FALSE)*'Criterios de priorización'!$D$19,0) -> 2.25
A11: 410 | B11: 46294.694 | C11: 46294.705 | D11: angela.lucano@laureate.pe | E11: Angela Lucano Carranza | F11: UPC: Adecuación de sistemas periféricos para soportar las nuevas mallas curriculares 2027 | G11: Necesitamos adecuar los sistemas periféricos que consumen información académica de Banner para soportar correctamente el versionamiento de mallas curriculares, logrando que estudiantes, docentes y áreas administrativas visualicen información académica correcta y consistente en todos los sistemas. | H11: UPC | I11: Milagros Morgan - Rectorado UPC | J11: Mónica Zavala | K11: https://educorpperu.sharepoint.com/sites/ITCS/_layouts/15/Doc.aspx?sourcedoc=%7BB1AF7D21-41BE-451D-90A7-D1C662B3DC9C%7D&file=Resumen%20reuni%C3%B3n%20-%20Proyecto%20mallas%202027_Angela%20Lucano%20Carran.docx&action=default&mobileredirect=true | L11: Ángela Lucano | M11: 46416 | N11: No | O11: 0 | P11: 0 | Q11: Regulatoria | R11: Actualmente, los cambios realizados en las mallas curriculares son gestionados por Banner; sin embargo, varios sistemas que consumen esta información no están preparados para reconocer las distintas versiones de cursos y mallas. Esto puede generar información incorrecta, registros duplicados o diferencias entre sistemas al momento de consultar datos académicos. | S11: Contar con sistemas alineados al modelo académico de Banner, capaces de identificar y mostrar la versión correcta de cursos y mallas según corresponda a cada estudiante, garantizando información consistente en todos los canales y procesos académicos. | T11: Consulta de cursos y mallas curriculares. Seguimiento del avance académico. Reportería académica y de gestión. Integraciones entre sistemas. Atención de trámites y consultas académicas. | U11: Todos | V11: Excelencia operativa | W11: No | X11: No cuantificado o S/0 | Y11: Reducción de incidencias por información académica incorrecta. Disminución del tiempo dedicado a validaciones y correcciones manuales. Eliminación de registros duplicados en consultas y reportes. Mayor confianza en la información mostrada a estudiantes y docentes. Capacidad de implementar futuras actualizaciones curriculares con menor esfuerzo. Consistencia de la información entre todos los sistemas institucionales. | Z11: https://educorpperu.sharepoint.com/sites/ITCS/_layouts/15/Doc.aspx?sourcedoc=%7BEF9FEB94-34ED-4AAA-BBD4-87AEA8C067DC%7D&file=Documento%20Funcional%20implementaci%C3%B3n%20de%20malla%202_Angela%20Lucano%20Carran.docx&action=default&mobileredirect=true | AA11: =IFERROR(VLOOKUP(N11,'Criterios de priorización'!$E$3:$F$4,2,FALSE)*'Criterios de priorización'!$D$3,0)+IFERROR(VLOOKUP(Q11,'Criterios de priorización'!$E$5:$F$8,2,FALSE)*'Criterios de priorización'!$D$5,0)+IFERROR(VLOOKUP(X11,'Criterios de priorización'!$E$9:$F$12,2,FALSE)*'Criterios de priorización'!$D$9,0)+IFERROR(VLOOKUP(V11,'Criterios de priorización'!$E$13:$F$18,2,FALSE)*'Criterios de priorización'!$D$13,0)+IFERROR(VLOOKUP(U11,'Criterios de priorización'!$E$19:$F$22,2,FALSE)*'Criterios de priorización'!$D$19,0) -> 2.7
A12: 411 | B12: 46294.395 | C12: 46295.15 | D12: miriam.marca@laureate.pe | E12: Miriam Marca Delgado | F12: Aprovisionamiento Alumnos Nuevos y Administrativos | G12: Necesitamos que el proceso de aprovisionamiento de cuentas de alumnos para CIBERTEC y UPC sea adoptado del modelo que tiene UPN | H12: LAU | I12: Humberto Marotta - Tecnologías y transformación digital | J12: Miriam Marca | K12: https://educorpperu.sharepoint.com/sites/ITCS/Documentos%20compartidos/Aplicaciones/Microsoft%20Forms/REGISTRO%20DE%20INICIATIVAS%20-%20GESTI%C3%93N%20DE%20LA%20DEMANDA%20V3/Aprobaci%C3%B3n%20de%20la%20iniciativa%20por%20el%20VP%20del%20%C3%A1rea%20sol/Re_%20INICIATIVA%20-%20APROVISIONAMIENTO%20DE%20CUENTAS_Miriam%20Marca%20Delgado.pdf | L12: Ángela Lucano | M12: 46366 | N12: No | O12: 0 | P12: 0 | Q12: ITSM | R12: Dependencia TOTAL de todos los alumnos ingresantes y docentes en UPC y Cibertec para el primer cambio de contraseña con el equipo de mesa de ayuda para registrar el número de celular y el correo personal. Estos 2 atributos son indispensables al momento de usar el SSPR (Restablecimiento de contraseña de autoservicio) en Microsoft Entra ID. Esto genera demoras en el acceso a los sistemas académicos y mayor carga operativa para la mesa de ayuda; desde la visión de negocio, impacta negativamente en la autonomía del usuario, la experiencia de estudiantes y docentes y la eficiencia institucional, afectando la continuidad de las actividades académicas y la escalabilidad de los procesos digitales de las instituciones. | S12: Esperamos que el aprovisionamiento de las cuentas de alumnos y docentes sea igual al que tiene UPN. Hoy los alumnos de UPN reciben una notificación de bienvenida personalizada en su correo personal registrado desde admisión. Se espera que tanto el alumno o docente incorporado, cuyos datos son registrados inicialmente por Admisión en el CRM y luego sincronizados hacia Banner y Microsoft Entra ID, como el alumno o docente regular, que puede autogestionar la actualización de su celular y correo personal, cuenten con un proceso unificado de autogestión de credenciales. | T12: Tecnología de la Información (TI): Reduce incidencias y solicitudes de soporte por contraseñas. Seguridad de la información: Fortalece la protección de cuentas y datos institucionales. Admisión y DOA (Servicios y Registros Académicos, Prospección, Docentes): Facilita el acceso a plataformas virtuales, matrícula y sistemas académicos. Atención al usuario: Disminuye tiempos de atención y mejora la experiencia de estudiantes y docentes. Cumplimiento normativo: Apoya el cumplimiento de políticas de seguridad y protección de datos. Recursos Humanos: Accesos para colaboradores y docentes | U12: Todos | V12: Excelencia operativa | W12: No | X12: No cuantificado o S/0 | Y12: Mejor experiencia para estudiantes, docentes y colaboradores. Mayor confianza en los servicios digitales institucionales. Menor interrupción de actividades académicas y administrativas. Mejora de la imagen institucional al ofrecer procesos más ágiles y seguros. Mayor alineamiento con buenas prácticas de ciberseguridad y gestión de riesgos. Menor carga operativa del equipo de soporte. Reducción de incidencias relacionadas con credenciales. Mejor percepción del servicio de TI por parte de los usuarios. | Z12: https://educorpperu.sharepoint.com/sites/ITCS/_layouts/15/Doc.aspx?sourcedoc=%7BE49D0BAA-5EE7-4C96-A0F7-38B47ED30878%7D&file=Proceso%20de%20Aprovisonamiento_Miriam%20Marca%20Delgado.pptx&action=edit&mobileredirect=true | AA12: =IFERROR(VLOOKUP(N12,'Criterios de priorización'!$E$3:$F$4,2,FALSE)*'Criterios de priorización'!$D$3,0)+IFERROR(VLOOKUP(Q12,'Criterios de priorización'!$E$5:$F$8,2,FALSE)*'Criterios de priorización'!$D$5,0)+IFERROR(VLOOKUP(X12,'Criterios de priorización'!$E$9:$F$12,2,FALSE)*'Criterios de priorización'!$D$9,0)+IFERROR(VLOOKUP(V12,'Criterios de priorización'!$E$13:$F$18,2,FALSE)*'Criterios de priorización'!$D$13,0)+IFERROR(VLOOKUP(U12,'Criterios de priorización'!$E$19:$F$22,2,FALSE)*'Criterios de priorización'!$D$19,0) -> 2.1
A13: 412 | B13: 46295.79 | C13: 46295.793 | D13: jose.herbozo@laureate.pe | E13: José Paredes Herbozo | F13: Actualización del Reporte 01 GDO digital doc pendiente | G13: Necesitamos actualizar el Reporte 01 GDO digital de documentos pendientes, retirando la selección de CRM 2011 del proyecto WebGestionDocumental, para eliminar la información desactualizada o inconsistente sobre los documentos pendientes, logrando un seguimiento confiable que favorezca el enrollment y la retención, proteja el revenue y el EBITDA, y reduzca las contingencias legales y normativas. | H13: UPN | I13: Ivan Olivares - VP Marketing y Comercial | J13: Ada Cadillo | K13: https://educorpperu.sharepoint.com/sites/ITCS/Documentos%20compartidos/Aplicaciones/Microsoft%20Forms/REGISTRO%20DE%20INICIATIVAS%20-%20GESTI%C3%93N%20DE%20LA%20DEMANDA%20V3/Aprobaci%C3%B3n%20de%20la%20iniciativa%20por%20el%20VP%20del%20%C3%A1rea%20sol/olk_UlOLAiv8Qh_Jos%C3%A9%20Paredes%20Herbozo.png | L13: Jose Paredes | M13: 46303 | N13: No | O13: 0 | P13: 0 | Q13: Otro | R13: El Reporte 01 GDO de documentos pendientes no refleja la información actualizada, porque aún depende de la selección de CRM 2011 en el proyecto WebGestionDocumental. Esto dificulta identificar qué alumnos tienen documentos pendientes, y afecta el seguimiento de enrollment y retención, el revenue, el EBITDA y la exposición a contingencias legales y normativas. Si no se implementa en la fecha requerida, el seguimiento se haría de forma manual, consolidando la información por cada área y validándola con los equipos responsables, con mayor esfuerzo y riesgo de errores. | S13: El Reporte 01 GDO digital de documentos pendientes opera sin la selección de CRM 2011, con información actualizada y confiable. Las áreas consultan el estado de los documentos pendientes de cada alumno desde un único reporte, sin consolidaciones manuales, y pueden actuar a tiempo sobre los casos que afectan la matrícula, la permanencia y el cumplimiento normativo. | T13: Proceso de gestión documental (GDO) de alumnos Procesos de enrollment y retención Áreas académicas y administrativas que dan seguimiento a documentos pendientes Áreas comerciales y de Customer Success Legal y cumplimiento normativo TI, como responsable del reporte y del proyecto WebGestionDocumental | U13: Administrativos | V13: Excelencia operativa | W13: No | X13: No cuantificado o S/0 | Y13: Información de documentos pendientes más confiable y actualizada. Menor dependencia de una herramienta obsoleta (CRM 2011) y de consolidaciones manuales. Mejor seguimiento de los alumnos con documentos pendientes, lo que favorece su matrícula y permanencia. Menor riesgo de incumplimientos legales y normativos por documentación incompleta. Decisiones más rápidas y mejor coordinación entre las áreas académicas, administrativas y comerciales. Proceso de gestión documental más ordenado y sostenible para TI. | Z13: https://educorpperu.sharepoint.com/sites/ITCS/_layouts/15/Doc.aspx?sourcedoc=%7BE50F3D73-BBD7-45DE-9818-1B05A5B0225C%7D&file=REPORTE%2001%20DOC%20PENDIENTE_Jos%C3%A9%20Paredes%20Herbozo.pptx&action=edit&mobileredirect=true | AA13: =IFERROR(VLOOKUP(N13,'Criterios de priorización'!$E$3:$F$4,2,FALSE)*'Criterios de priorización'!$D$3,0)+IFERROR(VLOOKUP(Q13,'Criterios de priorización'!$E$5:$F$8,2,FALSE)*'Criterios de priorización'!$D$5,0)+IFERROR(VLOOKUP(X13,'Criterios de priorización'!$E$9:$F$12,2,FALSE)*'Criterios de priorización'!$D$9,0)+IFERROR(VLOOKUP(V13,'Criterios de priorización'!$E$13:$F$18,2,FALSE)*'Criterios de priorización'!$D$13,0)+IFERROR(VLOOKUP(U13,'Criterios de priorización'!$E$19:$F$22,2,FALSE)*'Criterios de priorización'!$D$19,0) -> 0.6
A14: 423 | B14: 46063.076 | C14: 46063.076 | D14: angela.lucano@laureate.pe | E14: Angela D. Lucano Carranza | F14: LEAN + IA DOA UPC: Generar una solución de programación de evaluaciones que considere los atributos del examen y reglas del negocio establecidas. | G14: Necesitamos implementar una solución que permita la generación automática de la programación de evaluaciones para asegurar el cumplimiento de las reglas de negocio y requerimientos académicos, logrando una programación eficiente, trazable y una mejor experiencia para el alumno. | H14: UPC | I14: Milagros Morgan - Rectorado UPC | J14: Miguel Chang | K14: https://educorpperu.sharepoint.com/sites/ITCS/Documentos%20compartidos/Aplicaciones/Microsoft%20Forms/REGISTRO%20DE%20INICIATIVAS%20-%20GESTI%C3%93N%20DE%20LA%20DEMANDA%20V3/Aprobaci%C3%B3n%20de%20la%20iniciativa%20por%20el%20VP%20del%20%C3%A1rea%20sol/RE%20Iniciativas%20SPO%2078375%20LEAN%20+%20IA%20DOA%20UPC_Angela%20Lucano%20Carran.pdf | L14: Ángela Lucano | M14: 46387 | N14: Sí | O14: Digital & IA | P14: 78375 | Q14: Otro | R14: El proceso de programación de evaluaciones considera un alto consumo de tiempo operativo y horas extras debido a que se recopila información dispersa en múltiples reportes y formatos, se realiza un registro manual del rol de exámenes en Banner, se tiene riesgo de omisiones y errores en supervisores, modalidades y otros atributos ya que hay dependencia de validaciones por correo con las áreas académicas. | S14: Contar con una solución que: Genere automáticamente la programación de evaluaciones. Incorpore validaciones automáticas y reglas de negocio. Permita trazabilidad integral del proceso. Reduzca tiempos de programación y publicación del rol de exámenes. Minimice cambios posteriores a la publicación. Entregue al alumno un rol equilibrado y oportuno. | T14: Programación de evaluaciones. Validación del rol de exámenes. Publicación del rol de exámenes. Gestión de requerimientos académicos. Registro y actualización en Banner. | U14: Todos | V14: Excelencia operativa | W14: No | X14: No cuantificado o S/0 | Y14: 8,800 horas liberadas al año. Eliminación de 2,475 horas extras. Equivalente a 7 FTE liberados. Reducción del SLA de ejecución de 5 semanas a 2 semanas y de reprocesos. Mayor trazabilidad de la información. Mejor experiencia del alumno al contar oportunamente con su rol de evaluaciones. Revalorización del tiempo del personal hacia actividades analíticas y de gestión. Eliminación de tareas manuales de digitación y transcripción. | Z14: https://educorpperu.sharepoint.com/sites/ITCS/_layouts/15/Doc.aspx?sourcedoc=%7B243CC215-52A4-414C-95F1-EC45BB07FE26%7D&file=Resultados%20Taller%20Cocreaci%C3%B3n%20DOA%20UPC_Angela%20Lucano%20Carran.pptx&action=edit&mobileredirect=true | AA14: =IFERROR(VLOOKUP(N14,'Criterios de priorización'!$E$3:$F$4,2,FALSE)*'Criterios de priorización'!$D$3,0)+IFERROR(VLOOKUP(Q14,'Criterios de priorización'!$E$5:$F$8,2,FALSE)*'Criterios de priorización'!$D$5,0)+IFERROR(VLOOKUP(X14,'Criterios de priorización'!$E$9:$F$12,2,FALSE)*'Criterios de priorización'!$D$9,0)+IFERROR(VLOOKUP(V14,'Criterios de priorización'!$E$13:$F$18,2,FALSE)*'Criterios de priorización'!$D$13,0)+IFERROR(VLOOKUP(U14,'Criterios de priorización'!$E$19:$F$22,2,FALSE)*'Criterios de priorización'!$D$19,0) -> 1.2
A15: 424 | B15: 46063.079 | C15: 46063.079 | D15: angela.lucano@laureate.pe | E15: Angela D. Lucano Carranza | F15: LEAN + IA DOA UPC: Auditoría Interna y Mejora Continua | G15: Necesitamos implementar una solución que ejecute controles y validaciones dentro del mismo proceso para identificar oportunamente desviaciones y errores, logrando una matrícula correcta, cumplimiento normativo y mejora continua basada en hallazgos de auditoría. | H15: UPC | I15: Milagros Morgan - Rectorado UPC | J15: Miguel Chang | K15: https://educorpperu.sharepoint.com/sites/ITCS/Documentos%20compartidos/Aplicaciones/Microsoft%20Forms/REGISTRO%20DE%20INICIATIVAS%20-%20GESTI%C3%93N%20DE%20LA%20DEMANDA%20V3/Aprobaci%C3%B3n%20de%20la%20iniciativa%20por%20el%20VP%20del%20%C3%A1rea%20sol/RE%20Iniciativas%20SPO%2078375%20LEAN%20+%20IA%20DOA%20UPC_Angela%20Lucano%20Carran%201.pdf | L15: Ángela Lucano | M15: 46328 | N15: Sí | O15: Digital & IA | P15: 78375 | Q15: Otro | R15: Dentro del proceso de auditoría interna y mejora continua se realizan cruces manuales de información, validaciones duplicadas, intercambio manual de archivos entre áreas, tiempos prolongados de revisión y respuesta, observaciones acumuladas pendientes, riesgo de errores detectados tardíamente y recursos enfocados en actividades operativas en lugar de análisis y mejora. | S15: Contar con una plataforma que: Realice validaciones dentro del flujo operativo. Genere alertas automáticas. Prevenga errores mediante bloqueos en línea. Mantenga un catálogo de reglas de negocio. Genere reportes automáticos de hallazgos. Permita seguimiento, trazabilidad y mejora continua. | T15: Programación de horarios. Matrícula. Baja académica. Gestión multicampus. Auditoría interna. Gestión de reglas y controles. Mejora continua. | U15: Todos | V15: Excelencia operativa | W15: No | X15: No cuantificado o S/0 | Y15: Beneficio operativo identificado: 12,480 horas liberadas por automatización. Equivalente aproximado de 6 FTE. Reducción del tiempo de detección y corrección de errores (lead time) y de reprocesos. Mayor trazabilidad de la información. Eliminación de validaciones duplicadas. Eliminación del intercambio manual de archivos. Disminución de observaciones pendientes. Alertas automáticas para respuesta temprana. Reorientación del equipo hacia análisis, mejora continua y gobierno de reglas. | Z15: https://educorpperu.sharepoint.com/sites/ITCS/_layouts/15/Doc.aspx?sourcedoc=%7BC09C6447-05EF-4FBE-B63E-EBAA97D7F72E%7D&file=Resultados%20Taller%20Cocreaci%C3%B3n%20DOA%20UPC_Angela%20Lucano%20Carran%201.pptx&action=edit&mobileredirect=true | AA15: =IFERROR(VLOOKUP(N15,'Criterios de priorización'!$E$3:$F$4,2,FALSE)*'Criterios de priorización'!$D$3,0)+IFERROR(VLOOKUP(Q15,'Criterios de priorización'!$E$5:$F$8,2,FALSE)*'Criterios de priorización'!$D$5,0)+IFERROR(VLOOKUP(X15,'Criterios de priorización'!$E$9:$F$12,2,FALSE)*'Criterios de priorización'!$D$9,0)+IFERROR(VLOOKUP(V15,'Criterios de priorización'!$E$13:$F$18,2,FALSE)*'Criterios de priorización'!$D$13,0)+IFERROR(VLOOKUP(U15,'Criterios de priorización'!$E$19:$F$22,2,FALSE)*'Criterios de priorización'!$D$19,0) -> 1.2
A16: 425 | B16: 46063.546 | C16: 46063.546 | D16: carlos.diez@upn.edu.pe | E16: Carlos Antonio Diez Arenas | F16: Proyección automática de cursos equivalentes en la matrícula | G16: Lograr que el estudiante visualice en su proyección el curso equivalente aprobado cuando el curso exigido por su plan de estudios no cuenta con oferta programada, de modo que pueda matricularse sin requerir habilitación manual. El resultado se verifica cuando, para un estudiante con equivalencia en su plan de estudio, el curso de la equivalencia aparece en su proyección y puede registrarlo. Los casos de equivalencia de uno a varios y de varios a uno dependen de la iniciativa de representación de equivalencias en el sistema. | H16: UPN | I16: Martín Santana - Rectorado UPN | J16: Carlos Diez Arenas - Director de Secretaria Académica | K16: https://educorpperu.sharepoint.com/sites/ITCS/Documentos%20compartidos/Aplicaciones/Microsoft%20Forms/REGISTRO%20DE%20INICIATIVAS%20-%20GESTI%C3%93N%20DE%20LA%20DEMANDA%20V3/Aprobaci%C3%B3n%20de%20la%20iniciativa%20por%20el%20VP%20del%20%C3%A1rea%20sol/Solicitud%20de%20aprobaci%C3%B3n%20-%20Iniciativa%20de%20proye_Carlos%20Diez%20Arenas.pdf | L16: Carla Arias-Schreiber | M16: 46377 | N16: No | O16: 0 | P16: 0 | Q16: Otro | R16: La proyección de cursos en Banner se ejecuta sobre el plan de estudios del programa. Cuando un estudiante tiene cursos reconocidos por equivalencia, el sistema registra el cumplimiento en el avance curricular, pero no proyecta el curso equivalente que el estudiante debe llevar efectivamente. El resultado es que al estudiante no se le muestra en autoservicio el curso que le corresponde, pese a que su situación académica está correctamente registrada. Esta falla alcanza hoy incluso a las equivalencias uno a uno, que son el caso más simple. Los casos de una a varias y de varias a una no están cubiertos por ninguna solución actual y dependen de la iniciativa de registro de equivalencias uno a n y n a uno. La falla es silenciosa. La proyección no devuelve error ni deja traza de los estudiantes a los que no se les proyectó curso alguno, de modo que la institución no cuenta con un listado de los casos afectados y solo los detecta cuando el estudiante reclama o cuando el área los descubre revisando caso por caso. Esto impide dimensionar el problema, priorizar la atención y verificar que fue resuelto antes del cierre de matrícula. La consecuencia operativa es que cada caso debe resolverse de forma manual, mediante sobrepasos por curso y por NRC o mediante matrícula manual, con intervención de Procesos de Matrícula. Esto consume capacidad del equipo en el periodo de mayor carga, alarga el tiempo de atención del estudiante y, cuando la detección es tardía, expone al estudiante a matricularse en un curso que no le corresponde o a quedar sin matrícula al vencer el plazo. La población expuesta son los estudiantes con cursos reconocidos por equivalencia, que en la matrícula 2026-2 ascendieron a 4,200 convalidantes, además de los estudiantes migrados entre planes curriculares por efecto de la actualización de mallas. El desafío es que la proyección reconozca la equivalencia registrada y proyecte el curso que el estudiante debe llevar, dejando además traza de los casos en los que no logre proyectar, para que puedan ser gestionados antes del cierre de matrícula. | S16: La proyección de cursos reconoce las equivalencias registradas y proyecta al estudiante el curso que debe llevar efectivamente, no el curso del plan que ya tiene reconocido. El comportamiento debe ser el mismo para los tres escenarios de equivalencia: uno a uno, uno a varios y varios a uno. Los dos últimos escenarios dependen del registro de equivalencias uno a n y n a uno, de modo que mientras esa iniciativa no esté implementada no podrán ser probados, aunque la solución debe quedar construida para soportarlos. Cuando la proyección no logre resolver un caso, debe dejar registro identificable del estudiante y del curso no proyectado, de manera que los casos pendientes puedan ser gestionados antes del cierre de matrícula en lugar de ser descubiertos por reclamo del estudiante. El estado deseado es que el estudiante con cursos reconocidos por equivalencia vea en autoservicio la oferta que le corresponde y pueda matricularse por la vía regular, sin requerir sobrepasos por curso ni por NRC, ni matrícula manual, ni intervención del equipo de Procesos de Matrícula. El resultado se verifica por la reducción de sobrepasos y matrículas manuales asociados a equivalencias, por la reducción de consultas y reclamos por este motivo, y por la existencia de un listado de casos no proyectados que hoy no existe. | T16: El proceso directamente impactado es la Gestión de Matrícula, en sus subprocesos de proyección de cursos, matrícula por autoservicio, matrícula manual y proactiva, y atención de incidencias de matrícula. La propiedad del proceso de proyección corresponde a la Dirección de Secretaría Académica y la ejecución está a cargo del equipo de Procesos de Matrícula, por lo que ambos resultan impactados. Dentro de la Dirección de Operaciones Académicas, el área de Directores Académicos de Sede es la que hoy absorbe la carga manual de sobrepasos y la Dirección de Secretaria Académica absorbe la carga de matrícula manual derivada de esta falla, y el área de Registros Académicos participa en el registro de las equivalencias en el sistema y en la consistencia de la historia académica del estudiante. El proceso de Gestión Curricular también resulta impactado, en tanto el Vicerrectorado Académico aprueba los planes de estudio y sus tablas de equivalencias mediante resolución, y la Gerencia de Enseñanza Aprendizaje realiza su carga en el sistema. La calidad y la oportunidad de ese insumo condicionan el resultado de la proyección. El proceso de Programación Horaria, a cargo de la Dirección de Operaciones Académicas, resulta impactado porque la proyección solo puede resolverse si existe oferta programada para el curso equivalente en la sede y modalidad del estudiante. La atención al estudiante resulta impactada en Contacto UPN, que es el canal por el que ingresan las consultas y reclamos generados por esta falla, y el estudiante es el afectado final, al no poder completar su matrícula por la vía regular dentro del plazo. La implementación corresponde al equipo de Banner de Tecnología de la Información, que define si la solución se resuelve por configuración o por desarrollo. | U16: Alumnos | V16: Excelencia operativa | W16: No | X16: No cuantificado o S/0 | Y16: El estudiante con cursos reconocidos por equivalencia se matricula por la vía regular, en el mismo plazo y con la misma autonomía que cualquier otro estudiante. Hoy su matrícula depende de una gestión manual que él no ve ni controla, y que solo se activa cuando reclama. Esto elimina una diferencia de trato entre poblaciones que no responde a ninguna decisión institucional, sino a una limitación del sistema. El proceso gana visibilidad sobre sus propias fallas. Hoy la institución no sabe a qué estudiantes no se les proyectó curso, de modo que no puede priorizar, no puede verificar que resolvió todos los casos y no puede dimensionar el problema de un periodo a otro. El registro de casos no proyectados convierte un problema invisible en un problema gestionable, y permite cerrarlo antes del fin de la matrícula en lugar de descubrirlo por reclamo. Se reduce el riesgo de error en la historia académica del estudiante. La corrección manual mediante sobrepasos por curso y por NRC se ejecuta en el periodo de mayor carga operativa y bajo presión de plazo, que es la condición en la que el error es más probable. Cada corrección manual es una oportunidad de inconsistencia entre lo que la resolución de equivalencias aprobó, lo que el sistema reconoce y lo que el estudiante efectivamente lleva. Mejora la trazabilidad del proceso frente a auditoría y aseguramiento de la calidad. La institución puede evidenciar que lo ejecutado corresponde a lo aprobado por resolución, sin depender de registros manuales construidos fuera del sistema. Disminuye la dependencia del conocimiento tácito de pocas personas. La solución actual descansa en que un grupo reducido del equipo sepa qué sobrepaso aplicar en cada caso, lo que concentra riesgo operativo en la ventana más crítica del año y dificulta la incorporación de personal nuevo. | Z16: https://educorpperu.sharepoint.com/sites/ITCS/_layouts/15/Doc.aspx?sourcedoc=%7B038FC900-F2FC-48EF-A957-A8CA3A932251%7D&file=Gesti%C3%B3n%20de%20iniciativa%20Better%20together%20-%20No%20ap_Carlos%20Diez%20Arenas.pptx&action=edit&mobileredirect=true | AA16: =IFERROR(VLOOKUP(N16,'Criterios de priorización'!$E$3:$F$4,2,FALSE)*'Criterios de priorización'!$D$3,0)+IFERROR(VLOOKUP(Q16,'Criterios de priorización'!$E$5:$F$8,2,FALSE)*'Criterios de priorización'!$D$5,0)+IFERROR(VLOOKUP(X16,'Criterios de priorización'!$E$9:$F$12,2,FALSE)*'Criterios de priorización'!$D$9,0)+IFERROR(VLOOKUP(V16,'Criterios de priorización'!$E$13:$F$18,2,FALSE)*'Criterios de priorización'!$D$13,0)+IFERROR(VLOOKUP(U16,'Criterios de priorización'!$E$19:$F$22,2,FALSE)*'Criterios de priorización'!$D$19,0) -> 1.2
A17: 426 | B17: 46183.643 | C17: 46183.643 | D17: bruno.chiappe@laureate.pe | E17: Bruno Chiappe Vegas | F17: NOVA - Implementación proyecto HubSpot Web | G17: Consolidar una plataforma web unificada reutilizando el stack de UNITEC, orientada a optimizar la generación de tráfico orgánico, mejorar la trazabilidad de leads y habilitar capacidades de gestión 360 y lead scoring. | H17: LAU | I17: Ivan Olivares - VP Marketing y Comercial | J17: Humberto Cáceres | K17: https://educorpperu.sharepoint.com/sites/ITCS/Documentos%20compartidos/Aplicaciones/Microsoft%20Forms/REGISTRO%20DE%20INICIATIVAS%20-%20GESTI%C3%93N%20DE%20LA%20DEMANDA%20V3/Aprobaci%C3%B3n%20de%20la%20iniciativa%20por%20el%20VP%20del%20%C3%A1rea%20sol/Hubspot%20Web%20-%20aprob_Bruno%20Chiappe%20Vegas.pdf | L17: Bruno Chiappe | M17: 46356 | N17: No | O17: 0 | P17: 0 | Q17: Otro | R17: Actualmente, los activos web de las instituciones se encuentran distribuidos en distintas plataformas, arquitecturas y dominios, lo que genera fragmentación tecnológica, dificulta la estandarización de la experiencia digital y limita la trazabilidad integral de los leads. Asimismo, existen oportunidades de mejora en rendimiento web, arquitectura SEO, medición y continuidad tecnológica. | S17: Contar con un ecosistema web consolidado sobre HubSpot, reutilizando un stack tecnológico común y componentes estandarizados para UPC, UPN y Cibertec, que permita: - Centralizar la gestión de los activos web. - Mejorar la arquitectura de URLs y el posicionamiento orgánico. - Optimizar la velocidad y experiencia de navegación. - Implementar formularios, tracking y medición de manera integrada. - Obtener mayor trazabilidad del journey y comportamiento de los leads. - Habilitar progresivamente capacidades de gestión 360 y lead scoring. - Reducir riesgos de continuidad tecnológica y dependencia de plataformas legacy. | T17: Marketing digital Admisión Comercial Comunicaciones | U17: Administrativos | V17: Excelencia operativa | W17: No | X17: No cuantificado o S/0 | Y17: Mayor integración y estandarización del ecosistema digital; mejor experiencia de usuario y performance web; fortalecimiento del SEO mediante una arquitectura de URLs más ordenada; mayor trazabilidad del prospecto y de las fuentes de captación; capacidad futura de gestionar una visión 360 del lead y aplicar lead scoring; y una plataforma escalable y reutilizable entre las distintas instituciones de Laureate Perú. | Z17: https://educorpperu.sharepoint.com/sites/ITCS/_layouts/15/Doc.aspx?sourcedoc=%7BD1E78A1D-FE2F-4EA0-B872-0E3962B6BF19%7D&file=ALCANCE_Avance_Frentes_Digitales_HubSpot_Ago2_Bruno%20Chiappe%20Vegas.pptx&action=edit&mobileredirect=true | AA17: =IFERROR(VLOOKUP(N17,'Criterios de priorización'!$E$3:$F$4,2,FALSE)*'Criterios de priorización'!$D$3,0)+IFERROR(VLOOKUP(Q17,'Criterios de priorización'!$E$5:$F$8,2,FALSE)*'Criterios de priorización'!$D$5,0)+IFERROR(VLOOKUP(X17,'Criterios de priorización'!$E$9:$F$12,2,FALSE)*'Criterios de priorización'!$D$9,0)+IFERROR(VLOOKUP(V17,'Criterios de priorización'!$E$13:$F$18,2,FALSE)*'Criterios de priorización'!$D$13,0)+IFERROR(VLOOKUP(U17,'Criterios de priorización'!$E$19:$F$22,2,FALSE)*'Criterios de priorización'!$D$19,0) -> 0.6
A18: 427 | B18: 46183.713 | C18: 46183.713 | D18: jose.herbozo@laureate.pe | E18: José Luis Paredes Herbozo | F18: Activación de Contactabilidad outbound en Genesys en EPG UPN y automatización del trigger mediante creación de reglas en EPG UPC | G18: Necesitamos activar WhatsApp en Genesys como canal complementario a la llamada y automatizar su trigger mediante reglas basadas en CRM, para elevar la baja contactabilidad de prospectos que no atienden al discador y eliminar la carga manual de tablas de códigos, logrando mayor ratio de contactabilidad, derivación automática al equipo comercial correcto y más oportunidades de conversión. | H18: LAU | I18: Ivan Olivares - VP Marketing y Comercial | J18: Romina Honda | K18: https://educorpperu.sharepoint.com/sites/ITCS/Documentos%20compartidos/Aplicaciones/Microsoft%20Forms/REGISTRO%20DE%20INICIATIVAS%20-%20GESTI%C3%93N%20DE%20LA%20DEMANDA%20V3/Aprobaci%C3%B3n%20de%20la%20iniciativa%20por%20el%20VP%20del%20%C3%A1rea%20sol/olk_ONxfPu8HWf_Jos%C3%A9%20Paredes%20Herbozo.png | L18: José Paredes | M18: 46356 | N18: No | O18: 0 | P18: 0 | Q18: Otro | R18: Cuando el discador no logra contactar a un prospecto, no existe un segundo intento automático por otro canal, lo que limita el ratio de contactabilidad y las oportunidades de conversión en Posgrado UPN y EPG UPC. Además, el trigger del WhatsApp automático depende de la lectura de una tabla de códigos que se carga manualmente, lo que genera carga operativa y riesgo de demoras o errores. Recientemente se identificó que Genesys permite crear reglas con el CRM como fuente de datos principal, y aún no están configuradas. Si no se implementa en la fecha requerida, se continuaría con la gestión telefónica como único canal y con la carga manual de la tabla de códigos. | S18: Ante una llamada no atendida por el discador, Genesys envía automáticamente un mensaje de WhatsApp al prospecto. El trigger se activa mediante reglas configuradas por campaña/cola de cada categoría, con el CRM como fuente de datos, sin cargas manuales. El BOT identifica la categoría del prospecto y lo deriva al equipo comercial correspondiente. Si no se identifica la categoría por el código de persona, el prospecto pasa a una campaña/cola de desbordamiento. La actividad de WhatsApp se crea cuando el prospecto responde el mensaje outbound. | T18: Proceso de contactabilidad outbound (UPN Posgrado y EPG UPC) Equipos comerciales por categoría de Posgrado Customer Success / Contact Center (gestión en Genesys) TI (configuración de Genesys, reglas e integración con CRM) | U18: Administrativos | V18: Excelencia operativa | W18: No | X18: Entre S/100,000.00 y S/500,000.00 | Y18: Mayor contactabilidad de prospectos mediante un canal complementario a la llamada. Más oportunidades de conversión en Posgrado UPN y EPG UPC. Derivación automática y oportuna al equipo comercial especializado según la categoría del prospecto. Eliminación de la carga manual de tablas de códigos, con menor riesgo de errores y demoras. Mejor aprovechamiento de las capacidades de Genesys, con reglas basadas en el CRM como fuente de datos. Mayor eficiencia operativa del equipo comercial y del contact center. | Z18: https://educorpperu.sharepoint.com/sites/ITCS/_layouts/15/Doc.aspx?sourcedoc=%7B8A257094-6E29-4E4D-83BB-F7C2536C3D7D%7D&file=Solicitud%20de%20Activaci%C3%B3n%20-%20WhatsApp%20en%20Genesys_Jos%C3%A9%20Paredes%20Herbozo.pptx&action=edit&mobileredirect=true | AA18: =IFERROR(VLOOKUP(N18,'Criterios de priorización'!$E$3:$F$4,2,FALSE)*'Criterios de priorización'!$D$3,0)+IFERROR(VLOOKUP(Q18,'Criterios de priorización'!$E$5:$F$8,2,FALSE)*'Criterios de priorización'!$D$5,0)+IFERROR(VLOOKUP(X18,'Criterios de priorización'!$E$9:$F$12,2,FALSE)*'Criterios de priorización'!$D$9,0)+IFERROR(VLOOKUP(V18,'Criterios de priorización'!$E$13:$F$18,2,FALSE)*'Criterios de priorización'!$D$13,0)+IFERROR(VLOOKUP(U18,'Criterios de priorización'!$E$19:$F$22,2,FALSE)*'Criterios de priorización'!$D$19,0) -> 0.9
A19: 428 | B19: 46183.766 | C19: 46183.766 | D19: oscar.porras@upn.edu.pe | E19: Oscar Daniel Porras Cardenas | F19: Mejoras a implementar en la plataforma del SGCI | G19: Necesitamos implementar actualizaciones en la plataforma del SGCI, para optimizar el uso de la plataforma, logrando un mejor uso y desempeño de la misma | H19: UPN | I19: Martín Santana - Rectorado UPN | J19: GACI | K19: https://educorpperu.sharepoint.com/sites/ITCS/Documentos%20compartidos/Aplicaciones/Microsoft%20Forms/REGISTRO%20DE%20INICIATIVAS%20-%20GESTI%C3%93N%20DE%20LA%20DEMANDA%20V3/Aprobaci%C3%B3n%20de%20la%20iniciativa%20por%20el%20VP%20del%20%C3%A1rea%20sol/Aprobaci%C3%B3n_Oscar%20Porras%20Cardena.pdf | L19: Gerson Vereau | M19: 46367 | N19: No | O19: 0 | P19: 0 | Q19: Otro | R19: Se deben incorporar mejoras en la plataforma del SGCI, la justificación de las mismas se detalla según el caso: 1. Reasignación de funciones por rol y creación de nuevo rol "responsable de evidencias", A fin de agilizar la gestión de los requerimientos de la calidad, se debe actualizar las funciones habilitadas a los roles existentes: visualización de estados, visualización de historial, correos de alerta, funciones de ingreso de información y aprobación, entre otros. Asimismo, se incluye la creación de un nuevo rol "responsable de evidencias" como apoyo al LO. 2. Correos recordatorios tipo resumen: el correo para LO y LP debe incluir un resumen de requerimientos observados y pendientes de entrega. Actualmente la plataforma envía un correo por cada requerimiento a cargo, lo que hace que al tener varios requerimientos en distintas fechas, sea abrumador para el líder recibir tantos correos. Por ello se hace necesario que un solo correo resuma los estatus pendientes y observados asignados a cada rol 3. Incluir en el reporte: ciclo de mejora (P-V) y fecha en que el estado cambia a revisar por LT. El reporte descargable debe incluir entre sus columnas el ciclo de mejora (P - V) así como la fecha en que la información es enviada al Líder temático. Estos valores permitirán hacer un mejor filtro de la información para su seguimiento 4. Los links de la plataforma deben descargarse con el nombre con el que se han guardado. Las evidencias cargadas en la plataforma deben descargarse con el nombre original del archivo. 5. Cambiar el rol de líder temático por revisor Actualmente el rol asignado es el de líder temático 1, 2 y 3, estos deben cambiarse a solo revisor 6. Mejorar el encuadre de la información en PDF del requerimiento La información visible en PDF en la bandeja asociada al rol, se visualiza pegada a la izquierda lo que dificulta su lectura | S19: Se espera una plataforma que sea más dinámica a fin de que la revisión de las exigencias de la calidad sean revisadas de manera más ágil y se pueda alertar cualquier desviación identificada, de manera más oportuna. La plataforma debe servir como una herramienta que simplifique el proceso de revisión de requerimientos de la calidad | T19: La plataforma es gestionada por la Gerencia de Aseguramiento de la Calidad Institucional, quien es responsable de la revisión de evidencias que todos los Líderes de proceso (UPN y Laureate) ingresan como parte del Plan de Autoevaluación de la Calidad | U19: Todos | V19: Excelencia académica | W19: No | X19: Menor a S/100,000.00 | Y19: Mejorar la experiencia de los usuarios de la plataforma, agilizando la presentación y revisión de requerimientos de la calidad | Z19: https://educorpperu.sharepoint.com/sites/ITCS/_layouts/15/Doc.aspx?sourcedoc=%7B901CEC81-F6A4-476F-865D-F83F31CF51C5%7D&file=mejoras%20plataforma%20SGCI_Oscar%20Porras%20Cardena.pptx&action=edit&mobileredirect=true | AA19: =IFERROR(VLOOKUP(N19,'Criterios de priorización'!$E$3:$F$4,2,FALSE)*'Criterios de priorización'!$D$3,0)+IFERROR(VLOOKUP(Q19,'Criterios de priorización'!$E$5:$F$8,2,FALSE)*'Criterios de priorización'!$D$5,0)+IFERROR(VLOOKUP(X19,'Criterios de priorización'!$E$9:$F$12,2,FALSE)*'Criterios de priorización'!$D$9,0)+IFERROR(VLOOKUP(V19,'Criterios de priorización'!$E$13:$F$18,2,FALSE)*'Criterios de priorización'!$D$13,0)+IFERROR(VLOOKUP(U19,'Criterios de priorización'!$E$19:$F$22,2,FALSE)*'Criterios de priorización'!$D$19,0) -> 1.55
A20: 429 | B20: 46183.791 | C20: 46183.791 | D20: luz.flores@upn.edu.pe | E20: Luz Marina Flores Rodriguez | F20: Mejora del descompactador para una distribución correcta de cursos y créditos en matrícula | G20: Necesitamos que el descompactador BLSP asigne horarios dentro de las opciones disponibles, distribuyendo de manera equilibrada los cursos entre el Módulo 1 y el Módulo 2. Esto permitirá minimizar los ajustes posteriores en los horarios de los estudiantes nuevos y garantizar una experiencia de matrícula satisfactoria desde su primer periodo académico. | H20: UPN | I20: Martín Santana - Rectorado UPN | J20: Luz Marina Flores R | K20: https://educorpperu.sharepoint.com/sites/ITCS/Documentos%20compartidos/Aplicaciones/Microsoft%20Forms/REGISTRO%20DE%20INICIATIVAS%20-%20GESTI%C3%93N%20DE%20LA%20DEMANDA%20V3/Aprobaci%C3%B3n%20de%20la%20iniciativa%20por%20el%20VP%20del%20%C3%A1rea%20sol/Continuaci%C3%B3n%20de%20mejoras%20al%20descompactador%20VB_Luz%20Flores%20Rodriguez.pdf | L20: Carla Arias-Schreiber | M20: 46325 | N20: No | O20: 0 | P20: 0 | Q20: Regulatoria | R20: Actualmente, se están asignando horarios de manera desequilibrada entre el Módulo 1 y el Módulo 2 para los estudiantes de nuevo ingreso. Como consecuencia, algunos estudiantes concentran la mayor parte de sus cursos en el Módulo 1, quedando con una carga académica mínima o inexistente en el Módulo 2. Esta situación genera una experiencia poco adecuada al inicio de su vida universitaria y afecta la percepción de la calidad de los servicios académicos brindados. De no implementarse una solución oportuna, será necesario continuar con la revisión y corrección manual de los horarios asignados, lo que demanda un esfuerzo operativo significativo y jornadas extensas de trabajo. | S20: Automatizar la asignación balanceada de cursos entre el Módulo 1 y el Módulo 2 para los estudiantes nuevos, garantizando una distribución adecuada de la carga académica y minimizando las intervenciones manuales. Con ello, se busca mejorar la experiencia del estudiante, reducir los tiempos de revisión operativa y evitar jornadas extraordinarias asociadas a la corrección de horarios. | T20: Proceso de programación de horarios, proceso de registro de horarios y atención al estudiante | U20: Alumnos | V20: Excelencia operativa | W20: No | X20: No cuantificado o S/0 | Y20: 1)Mejora de la experiencia del estudiante de nuevo ingreso, al recibir un horario con una distribución académica equilibrada desde el inicio de su formación universitaria. 2)Mayor percepción de calidad del servicio, al reducir la necesidad de realizar ajustes posteriores en los horarios asignados. 3)Incremento de la satisfacción estudiantil, al contar con una programación académica coherente y adecuada a la estructura modular. 4)Reducción de reprocesos operativos, evitando las revisiones y correcciones manuales de horarios generados de manera desequilibrada. 5)Optimización del trabajo del equipo académico y administrativo, permitiendo destinar esfuerzos a actividades de mayor valor agregado en lugar de tareas correctivas. 6) Mayor confianza en los procesos automatizados de matrícula y programación académica, al garantizar resultados más consistentes y alineados con las necesidades de los estudiantes. 7)Fortalecimiento de la imagen institucional, al ofrecer una experiencia de incorporación más ordenada y eficiente para los estudiantes que inician su carrera. 8)Disminución del riesgo de errores operativos, asociados a las modificaciones manuales de horarios y cargas académicas. | Z20: https://educorpperu.sharepoint.com/sites/ITCS/_layouts/15/Doc.aspx?sourcedoc=%7BE17684D9-A4C2-4CD3-9ED0-BEECD7B6AFBA%7D&file=PPT-%20SOLICITUD%20DES%20COMPACTACI%C3%93N%20CACHIMBOS%2025-_Luz%20Flores%20Rodriguez.pptx&action=edit&mobileredirect=true | AA20: =IFERROR(VLOOKUP(N20,'Criterios de priorización'!$E$3:$F$4,2,FALSE)*'Criterios de priorización'!$D$3,0)+IFERROR(VLOOKUP(Q20,'Criterios de priorización'!$E$5:$F$8,2,FALSE)*'Criterios de priorización'!$D$5,0)+IFERROR(VLOOKUP(X20,'Criterios de priorización'!$E$9:$F$12,2,FALSE)*'Criterios de priorización'!$D$9,0)+IFERROR(VLOOKUP(V20,'Criterios de priorización'!$E$13:$F$18,2,FALSE)*'Criterios de priorización'!$D$13,0)+IFERROR(VLOOKUP(U20,'Criterios de priorización'!$E$19:$F$22,2,FALSE)*'Criterios de priorización'!$D$19,0) -> 2.7
A21: 430 | B21: 46183.792 | C21: 46183.792 | D21: jhonatan.sanchez@upn.edu.pe | E21: Jhonatan Fernando Sanchez Zambrano | F21: Cambio de horarios integral UPN | G21: La iniciativa busca fortalecer las condiciones de seguridad de estudiantes, docentes y personal administrativo que permanecen en las sedes hasta el término de las actividades académicas (22:40 h), horario en el que se incrementa su exposición a situaciones de inseguridad. | H21: UPN | I21: Martín Santana - Rectorado UPN | J21: Jhonatan Fernando Sanchez Zambrano | K21: https://educorpperu.sharepoint.com/sites/ITCS/Documentos%20compartidos/Aplicaciones/Microsoft%20Forms/REGISTRO%20DE%20INICIATIVAS%20-%20GESTI%C3%93N%20DE%20LA%20DEMANDA%20V3/Aprobaci%C3%B3n%20de%20la%20iniciativa%20por%20el%20VP%20del%20%C3%A1rea%20sol/VB_Jhonatan%20Sanchez%20Zam.pdf | L21: Carla Arias-Schreiber | M21: 46311 | N21: No | O21: 0 | P21: 0 | Q21: Otro | R21: La iniciativa busca fortalecer las condiciones de seguridad de estudiantes, docentes y personal administrativo que permanecen en las sedes hasta el término de las actividades académicas (22:40 h), horario en el que se incrementa su exposición a situaciones de inseguridad. En ese sentido se busca actualizar todas las franjas horarias adelantándolas 30 minutos | S21: Franjas horarias desde las 7.00 AM hasta las 10.10 PM | T21: Nomina Programación Academia | U21: Alumnos | V21: Experiencia | W21: No | X21: No cuantificado o S/0 | Y21: La iniciativa busca fortalecer las condiciones de seguridad de estudiantes, docentes y personal administrativo que permanecen en las sedes hasta el término de las actividades académicas (22:40 h), horario en el que se incrementa su exposición a situaciones de inseguridad. | Z21: https://educorpperu.sharepoint.com/sites/ITCS/_layouts/15/Doc.aspx?sourcedoc=%7B85B31776-5B25-4211-912A-A82899A28E2F%7D&file=Gesti%C3%B3n%20de%20iniciativas%20-%20Horarios%207AM_Jhonatan%20Sanchez%20Zam.pptx&action=edit&mobileredirect=true | AA21: =IFERROR(VLOOKUP(N21,'Criterios de priorización'!$E$3:$F$4,2,FALSE)*'Criterios de priorización'!$D$3,0)+IFERROR(VLOOKUP(Q21,'Criterios de priorización'!$E$5:$F$8,2,FALSE)*'Criterios de priorización'!$D$5,0)+IFERROR(VLOOKUP(X21,'Criterios de priorización'!$E$9:$F$12,2,FALSE)*'Criterios de priorización'!$D$9,0)+IFERROR(VLOOKUP(V21,'Criterios de priorización'!$E$13:$F$18,2,FALSE)*'Criterios de priorización'!$D$13,0)+IFERROR(VLOOKUP(U21,'Criterios de priorización'!$E$19:$F$22,2,FALSE)*'Criterios de priorización'!$D$19,0) -> 1.3
A22: 431 | B22: 46213.44 | C22: 46213.44 | D22: yenny.pajuelo@cibertec.pe | E22: Yenny Ysabel Pajuelo Ramirez | F22: Actualización UDCID - autenticación del estudiante | G22: Garantizar el acceso continuo e ininterrumpido del 100% de los estudiantes a la plataforma Banner para los procesos de prematricula y matrícula, mediante la automatización de la actualización del campo UDCI. | H22: CIB | I22: Danilo Tauil - GM TecVoc | J22: Yenny Pajuelo | K22: https://educorpperu.sharepoint.com/sites/ITCS/Documentos%20compartidos/Aplicaciones/Microsoft%20Forms/REGISTRO%20DE%20INICIATIVAS%20-%20GESTI%C3%93N%20DE%20LA%20DEMANDA%20V3/Aprobaci%C3%B3n%20de%20la%20iniciativa%20por%20el%20VP%20del%20%C3%A1rea%20sol/V%C2%B0B%C2%B0%20Proyecto%20UDCID-%20autenticaci%C3%B3n%20de%20estudia_Yenny%20Pajuelo%20Ramire.png | L22: Carla Arias-Schreiber | M22: 46335 | N22: No | O22: 0 | P22: 0 | Q22: ITSM | R22: La falta de automatización en la actualización del UDCID y los fallos recurrentes en la plataforma Banner impiden garantizar un proceso fluido de prematricula y matrícula para la totalidad de los estudiantes, afectando la experiencia del usuario e incrementando la carga operativa manual. | S22: La totalidad de la población estudiantil accede a la plataforma Banner de manera simultánea, rápida y sin interrupciones durante los periodos de prematricula y matrícula. A su vez, los datos del campo UDCID se procesen y actualicen automáticamente en el sistema sin requerir intervención manual (generación de ticket) | T22: Experiencia del estudiante, Retención, Proceso de Matrícula, Sedes | U22: Alumnos | V22: Excelencia operativa | W22: No | X22: Entre S/100,000.00 y S/500,000.00 | Y22: Reducción de tiempo / Aumento en NPS / Retención del estudiante | Z22: https://educorpperu.sharepoint.com/sites/ITCS/_layouts/15/Doc.aspx?sourcedoc=%7B73561A56-BCFD-4FBB-B994-8E3A0097CBD7%7D&file=Formato%20Solicitud%20de%20Requerimientos%20(UDCID)%20S_Yenny%20Pajuelo%20Ramire.pptx&action=edit&mobileredirect=true | AA22: =IFERROR(VLOOKUP(N22,'Criterios de priorización'!$E$3:$F$4,2,FALSE)*'Criterios de priorización'!$D$3,0)+IFERROR(VLOOKUP(Q22,'Criterios de priorización'!$E$5:$F$8,2,FALSE)*'Criterios de priorización'!$D$5,0)+IFERROR(VLOOKUP(X22,'Criterios de priorización'!$E$9:$F$12,2,FALSE)*'Criterios de priorización'!$D$9,0)+IFERROR(VLOOKUP(V22,'Criterios de priorización'!$E$13:$F$18,2,FALSE)*'Criterios de priorización'!$D$13,0)+IFERROR(VLOOKUP(U22,'Criterios de priorización'!$E$19:$F$22,2,FALSE)*'Criterios de priorización'!$D$19,0) -> 2.4
A23: 432 | B23: 46366.774 | C23: 46366.774 | D23: bruno.chiappe@laureate.pe | E23: Bruno Chiappe Vegas | F23: Implementación del Canal WhatsApp Omnicanal con Asistente Virtual Comercial SofIA | G23: Necesitamos implementar y estandarizar un canal institucional de WhatsApp omnicanal, incorporando al asistente virtual SofIA como asesor educativo comercial y habilitando la atención integrada con los asesores de ventas, para eliminar la fragmentación de las conversaciones, la pérdida de información entre canales y responsables, las limitaciones de atención fuera del horario comercial y la falta de trazabilidad del proceso de captación y seguimiento, logrando una experiencia comercial continua y personalizada, mayor eficiencia operativa, mejor gestión de oportunidades comerciales, incremento de la conversión de prospectos a inscritos y medición integral de los resultados comerciales para UPN, UPC y Cibertec. | H23: LAU | I23: Ivan Olivares - VP Marketing y Comercial | J23: Jaime Medina Salcedo | K23: https://educorpperu.sharepoint.com/sites/ITCS/Documentos%20compartidos/Aplicaciones/Microsoft%20Forms/REGISTRO%20DE%20INICIATIVAS%20-%20GESTI%C3%93N%20DE%20LA%20DEMANDA%20V3/Aprobaci%C3%B3n%20de%20la%20iniciativa%20por%20el%20VP%20del%20%C3%A1rea%20sol/Whatsapp%20Channel%20SofIA%20-%20aprob_Bruno%20Chiappe%20Vegas.pdf | L23: Bruno Chiappe | M23: 46356 | N23: No | O23: 0 | P23: 0 | Q23: Otro | R23: Actualmente, la gestión comercial por WhatsApp presenta fragmentación en la atención, pérdida de contexto entre responsables, limitaciones de atención fuera de horario y falta de coordinación en campañas y seguimientos. Asimismo, existe una limitada trazabilidad de las interacciones y su impacto en las conversiones, dificultando la continuidad comercial, la eficiencia operativa y el aprovechamiento de oportunidades de inscripción. | S23: Contar con un canal institucional de WhatsApp omnicanal para UPN, UPC y Cibertec, que centralice la atención comercial e incorpore a SofIA como asesora virtual para orientar, perfilar, realizar venta consultiva y acompañar al prospecto hacia la inscripción. La solución deberá garantizar continuidad con los asesores de ventas, atención fuera de horario, campañas segmentadas, seguimiento de oportunidades y trazabilidad integral de las gestiones y resultados comerciales. | T23: Procesos: Captación de prospectos, atención comercial, admisión Áreas: Ventas, Marketing Digital, Command Center, Admisión | U23: Alumnos | V23: Experiencia | W23: No | X23: No cuantificado o S/0 | Y23: Mejora de la experiencia del prospecto mediante una atención personalizada, continua y disponible fuera de horario. Mayor eficiencia comercial gracias a la automatización con SofIA, la coordinación con asesores de ventas y el seguimiento oportuno de oportunidades. Asimismo, permite estandarizar la atención entre instituciones, optimizar campañas y fortalecer la trazabilidad, supervisión y toma de decisiones comerciales. | Z23: https://educorpperu.sharepoint.com/sites/ITCS/_layouts/15/Doc.aspx?sourcedoc=%7BC499C532-F918-4659-850F-F2012613C5FD%7D&file=AR_02_Canal_WhatsApp_Channel_y_Asistente_Virt_Bruno%20Chiappe%20Vegas.docx&action=default&mobileredirect=true | AA23: =IFERROR(VLOOKUP(N23,'Criterios de priorización'!$E$3:$F$4,2,FALSE)*'Criterios de priorización'!$D$3,0)+IFERROR(VLOOKUP(Q23,'Criterios de priorización'!$E$5:$F$8,2,FALSE)*'Criterios de priorización'!$D$5,0)+IFERROR(VLOOKUP(X23,'Criterios de priorización'!$E$9:$F$12,2,FALSE)*'Criterios de priorización'!$D$9,0)+IFERROR(VLOOKUP(V23,'Criterios de priorización'!$E$13:$F$18,2,FALSE)*'Criterios de priorización'!$D$13,0)+IFERROR(VLOOKUP(U23,'Criterios de priorización'!$E$19:$F$22,2,FALSE)*'Criterios de priorización'!$D$19,0) -> 1.3
A24: 433 | B24: 13/10/2026 10:16:09 | C24: 13/10/2026 10:16:09 | D24: luis.sanchez@upn.edu.pe | E24: Luis Enrique Sanchez Cruz | F24: Configuración de puntaje único para el Examen de Suficiencia - Inglés | G24: Necesitamos Modificar la configuración actual del Examen de Suficiencia de Inglés en Banner/SOATEST para que el resultado se registre mediante una única nota final (Overall Score), siguiendo el modelo actualmente utilizado para Portugués y Quechua. El cálculo y ponderación de las habilidades evaluadas se realizará internamente desde el Centro de Idiomas, registrándose en Banner únicamente el resultado final para Fortalecer la estandarización y el control académico del Examen de Suficiencia de Inglés, permitiendo incorporar las habilidades comunicativas requeridas —Reading, Listening, Speaking y Writing— sin que la configuración tecnológica limite el diseño de la evaluación. Adicionalmente, se homogeneizará el registro de resultados respecto de los exámenes de Portugués y Quechua y se brindará al estudiante un resultado integral mediante un Overall Score; logrando que se estandarice las 4 habilidades de las competencias lingüisticas. De no contar con el cambio, Banner/SOATEST continuará permitiendo únicamente el registro de Listening y Reading, lo que impediría registrar adecuadamente el resultado de una evaluación que incorpore Speaking y Writing y limitaría la implementación completa de un modelo de eavluación estandarizado. | H24: UPN | I24: Martín Santana - Rectorado UPN | J24: Luis Enrique Sánchez Cruz | K24: https://educorpperu.sharepoint.com/sites/ITCS/Documentos%20compartidos/Aplicaciones/Microsoft%20Forms/REGISTRO%20DE%20INICIATIVAS%20-%20GESTI%C3%93N%20DE%20LA%20DEMANDA%20V3/Aprobaci%C3%B3n%20de%20la%20iniciativa%20por%20el%20VP%20del%20%C3%A1rea%20sol/Visto%20Buemo%20jefatura_Luis%20Sanchez%20Cruz.png | L24: Carla Arias-Schreiber | M24: 46353 | N24: No | O24: 0 | P24: 0 | Q24: Otro | R24: Actualmente, el Examen de Suficiencia de Inglés se encuentra configurado en Banner/SOATEST para registrar resultados independientes únicamente para las habilidades de Listening y Reading. Esta configuración no permite incorporar adecuadamente Speaking y Writing, habilidades que forman parte de la nueva estructura de evaluación del examen. Mantener la configuración actual limita la implementación integral del nuevo modelo de evaluación, ya que el sistema condiciona la estructura del examen a campos individuales predefinidos. De no implementarse el cambio requerido, el Centro de Idiomas tendría que continuar gestionando internamente los resultados de las cuatro habilidades y adaptar posteriormente la información para su registro en Banner/SOATEST, generando una limitación operativa y de estandarización respecto de Portugués y Quechua. | S24: Contar con una configuración de Banner/SOATEST que permita registrar para el Examen de Suficiencia de Inglés una única nota final u Overall Score, siguiendo el modelo actualmente utilizado para los exámenes de Portugués y Quechua. El Centro de Idiomas realizará internamente la evaluación, cálculo y ponderación de Listening, Reading, Speaking y Writing, y posteriormente registrará en Banner/SOATEST únicamente el resultado final. Esto permitirá mantener una estructura de evaluación flexible, incorporar las habilidades requeridas sin depender de campos individuales del sistema y homogeneizar el registro de resultados entre los diferentes idiomas. Asimismo, el cambio deberá mantener el flujo actual mediante el cual el estudiante, luego del registro de su resultado, puede continuar con la obtención de su constancia o certificado de aprobación. | T24: Centro de Idiomas, responsable de la evaluación, cálculo y ponderación de las habilidades y del registro del Overall Scor; estudiantes que rindan el Examen de Suficiencia de Inglés, como usuarios finales del proceso | U24: Alumnos | V24: Experiencia | W24: Sí | X24: No cuantificado o S/0 | Y24: ortalecer la estandarización y el control académico del Examen de Suficiencia de Inglés, permitiendo incorporar las cuatro habilidades comunicativas requeridas —Listening, Reading, Speaking y Writing— sin que la configuración tecnológica limite el diseño de la evaluación. Asimismo, se homogeneizará el registro de resultados con los exámenes de Portugués y Quechua mediante una única nota final (Overall Score), facilitando una gestión más flexible, consistente y alineada con el modelo de evaluación definido por el Centro de Idiomas. | Z24: https://educorpperu.sharepoint.com/sites/ITCS/_layouts/15/Doc.aspx?sourcedoc=%7B46A395B4-649A-4708-ACF2-16D51C62F338%7D&file=Gesti%C3%B3n%20de%20iniciativas%20-%20Centro%20de%20Idiomas%20-_Luis%20Sanchez%20Cruz.pptx&action=edit&mobileredirect=true | AA24: =IFERROR(VLOOKUP(N24,'Criterios de priorización'!$E$3:$F$4,2,FALSE)*'Criterios de priorización'!$D$3,0)+IFERROR(VLOOKUP(Q24,'Criterios de priorización'!$E$5:$F$8,2,FALSE)*'Criterios de priorización'!$D$5,0)+IFERROR(VLOOKUP(X24,'Criterios de priorización'!$E$9:$F$12,2,FALSE)*'Criterios de priorización'!$D$9,0)+IFERROR(VLOOKUP(V24,'Criterios de priorización'!$E$13:$F$18,2,FALSE)*'Criterios de priorización'!$D$13,0)+IFERROR(VLOOKUP(U24,'Criterios de priorización'!$E$19:$F$22,2,FALSE)*'Criterios de priorización'!$D$19,0) -> 1.3
A25: 434 | B25: 13/10/2026 14:28:58 | C25: 13/10/2026 14:28:58 | D25: jose.herbozo@laureate.pe | E25: José Luis Paredes Herbozo | F25: Habilitar ambientes para aplicativo de iniciativas | G25: Habilitar ambientes para aplicativo de iniciativas (Dev, Certificación y Producción) LINK DE DIAGRAMA DE ARQUITECTURA: https://laureate.leanix.net/LaureatePeru/diagrams/freedraw/acc2c56f-aa28-41b8-9996-af486c76374d?returnUrl=%2Fdiagrams%2Foverview%2Fall-diagrams | H25: LAU | I25: Humberto Marotta - Tecnologías y transformación digital | J25: José Luis Paredes Herbozo | K25: https://educorpperu.sharepoint.com/sites/ITCS/Documentos%20compartidos/Aplicaciones/Microsoft%20Forms/REGISTRO%20DE%20INICIATIVAS%20-%20GESTI%C3%93N%20DE%20LA%20DEMANDA%20V3/Aprobaci%C3%B3n%20de%20la%20iniciativa%20por%20el%20VP%20del%20%C3%A1rea%20sol/olk_dqg60VfeV6_Jos%C3%A9%20Paredes%20Herbozo.png | L25: José Paredes | M25: 46341 | N25: No | O25: 0 | P25: 0 | Q25: Otro | R25: Hoy las iniciativas de software llegan a la cola de TI como solicitudes ambiguas, sin estructura ni criterios de calidad corporativa. Esto genera reprocesos, observaciones repetidas, demoras en el registro y aprobaciones sin evidencia formal. El impacto en el negocio es que TI atiende demandas mal definidas y se pierde trazabilidad en la priorización. Gestión temporal si no se implementa a tiempo: el expediente no lo define. Lo razonable es mantener el proceso actual de solicitudes manuales con revisión del IT BP, pero es un supuesto mío, confírmalo. | S25: El solicitante describe su necesidad con el asistente TEO, que propone un título con verbo en infinitivo, un objetivo SMART y normaliza fechas. La iniciativa se guarda como expediente y pasa por un workflow formal: Borrador → Pendiente → Observada → Aprobada / En Demanda / Rechazada. El Business Partner TI evalúa la viabilidad y el VP aprueba con consentimiento registrado (texto firmado, fecha, hora e IP), con notificación automática por correo M365. Cada VP ve solo sus iniciativas y el servicio sigue operando aunque fallen los proveedores de IA, gracias al failover en cascada. | T25: Proceso de captura, priorización y aprobación de iniciativas de software. Solicitantes: jefes, directores de escuela y VPs de negocio de UPC, UPN y Cibertec. Business Partners y evaluadores de TI. Vicepresidencias y decanos aprobadores. PMO TI y Arquitectura de Soluciones (administración del metamodelo, roles y bitácoras). | U25: Administrativos | V25: Excelencia operativa | W25: No | X25: No cuantificado o S/0 | Y25: Solicitudes mejor estructuradas desde el origen: título con verbo en infinitivo, objetivo SMART y fechas normalizadas, lo que reduce observaciones y reprocesos. Trazabilidad completa del ciclo de vida de cada iniciativa, con historial inmutable de estados y observaciones. Mayor validez probatoria de las aprobaciones: el VP acepta un consentimiento con texto firmado, fecha, hora e IP. Confidencialidad entre vicepresidencias, ya que cada VP ve solo sus iniciativas. Mejor priorización y toma de decisiones del VP y del Comité, con información homogénea y de calidad. Menor carga operativa para los Business Partners de TI, que reciben demandas más claras. Comunicación automática y oportuna al solicitante y al VP mediante correo M365. Continuidad del servicio, ya que el solicitante no pierde su trabajo aunque fallen los proveedores de IA. Flexibilidad de gobierno: TI ajusta campos, formularios y roles sin despliegues de código. Estandarización del proceso en UPC, UPN y Cibertec. | Z25: https://educorpperu.sharepoint.com/sites/ITCS/Documentos%20compartidos/Aplicaciones/Microsoft%20Forms/REGISTRO%20DE%20INICIATIVAS%20-%20GESTI%C3%93N%20DE%20LA%20DEMANDA%20V3/Adjuntar%20ppt%20de%20la%20iniciativa/Expediente_Tecnico_IACS_v2_Jos%C3%A9%20Paredes%20Herbozo.pdf | AA25: =IFERROR(VLOOKUP(N25,'Criterios de priorización'!$E$3:$F$4,2,FALSE)*'Criterios de priorización'!$D$3,0)+IFERROR(VLOOKUP(Q25,'Criterios de priorización'!$E$5:$F$8,2,FALSE)*'Criterios de priorización'!$D$5,0)+IFERROR(VLOOKUP(X25,'Criterios de priorización'!$E$9:$F$12,2,FALSE)*'Criterios de priorización'!$D$9,0)+IFERROR(VLOOKUP(V25,'Criterios de priorización'!$E$13:$F$18,2,FALSE)*'Criterios de priorización'!$D$13,0)+IFERROR(VLOOKUP(U25,'Criterios de priorización'!$E$19:$F$22,2,FALSE)*'Criterios de priorización'!$D$19,0) -> 0.6
A26: 435 | B26: 14/10/2026 11:25:20 | C26: 14/10/2026 11:25:20 | D26: angela.lucano@laureate.pe | E26: Angela D. Lucano Carranza | F26: [UPC] Proyección y seguimiento del cumplimiento de menciones para optimizar la planificación académica y la experiencia de matrícula | G26: Necesitamos implementar una solución en Banner que permita identificar oportunamente a los estudiantes que se encuentran en proceso de cumplimiento o que ya han completado las mallas de sus menciones, así como visualizar el estado de avance de cada mención, para que las áreas académicas puedan proyectar adecuadamente la demanda y planificar la oferta horaria requerida, logrando mejorar la experiencia de matrícula del estudiante (principalmente porque son alumnos próximos a egresar), optimizar la planificación académica y reducir los esfuerzos operativos asociados al análisis manual de información. | H26: UPC | I26: Milagros Morgan - Rectorado UPC | J26: Roxana Pairazaman y Monica Zavala | K26: https://educorpperu.sharepoint.com/sites/ITCS/Documentos%20compartidos/Aplicaciones/Microsoft%20Forms/REGISTRO%20DE%20INICIATIVAS%20-%20GESTI%C3%93N%20DE%20LA%20DEMANDA%20V3/Aprobaci%C3%B3n%20de%20la%20iniciativa%20por%20el%20VP%20del%20%C3%A1rea%20sol/RE_%20Revisi%C3%B3n%20del%20cumplimiento%20de%20las%20mencione_Angela%20Lucano%20Carran.pdf | L26: Ángela Lucano | M26: 46402 | N26: No | O26: 0 | P26: 0 | Q26: Otro | R26: Actualmente, el sistema Banner no permite identificar de forma automática y centralizada a los estudiantes que cumplen o están próximos a cumplir las mallas de menciones. Como consecuencia, la proyección de demanda y la programación de cursos de mención requieren revisiones manuales sobre más de 798 mil registros, generando ineficiencias operativas, retrasos en la planificación académica y dificultades para estimar adecuadamente la oferta horaria. Esta situación impacta directamente en la experiencia del estudiante durante la matrícula, ya que la programación de cursos de mención puede realizarse de manera tardía o insuficiente, incrementando consultas y reclamos, afectando el avance académico y deteriorando la percepción de calidad del servicio educativo. | S26: Contar en Banner con una funcionalidad que permita identificar automáticamente las menciones disponibles para cada estudiante, visualizar los cursos que las conforman y su estado de cumplimiento, así como acceder a reportes o consultas que faciliten la proyección de demanda y la planificación académica. De esta manera, las áreas académicas podrán programar oportunamente la oferta de cursos de mención y los estudiantes dispondrán de información confiable para tomar decisiones durante su matrícula. | T26: Dirección de Operaciones Académicas, Direcciones académicas | U26: Todos | V26: Excelencia operativa | W26: No | X26: No cuantificado o S/0 | Y26: Beneficios cuantitativos: - Reducción del esfuerzo de análisis manual sobre 798,064 registros utilizados para la proyección de cursos de mención. - Disminución de los tiempos de respuesta para la estimación de demanda y programación de cursos de mención. - Reducción de los tickets y solicitudes relacionados con la oferta horaria, considerando que en el último período se registraron 3,018 solicitudes. - Mejora en la precisión de la planificación para 277 menciones (199 en Pregrado Regular y 78 en EPE) asociadas a 816 cursos de mención. Beneficios cualitativos: - Mejora de la experiencia del estudiante durante el proceso de matrícula. - Mayor visibilidad y control sobre el cumplimiento de menciones académicas. - Incremento de la confianza del estudiante en la información académica disponible. - Mejor planificación de la oferta horaria de cursos de mención. - Reducción de riesgos de retraso en el avance académico de alumnos próximos a egresar. - Disminución de actividades manuales de análisis realizadas por las áreas académicas. - Fortalecimiento de la percepción de calidad y oportunidad del servicio educativo. - Mayor capacidad para anticipar necesidades académicas y tomar decisiones basadas en información confiable. | Z26: https://educorpperu.sharepoint.com/sites/ITCS/_layouts/15/Doc.aspx?sourcedoc=%7B210E852D-8A56-4965-90B1-EC98A0ED9FDD%7D&file=Gesti%C3%B3n%20de%20iniciativas%20-%20Registro_GC_v3_Angela%20Lucano%20Carran.pptx&action=edit&mobileredirect=true | AA26: =IFERROR(VLOOKUP(N26,'Criterios de priorización'!$E$3:$F$4,2,FALSE)*'Criterios de priorización'!$D$3,0)+IFERROR(VLOOKUP(Q26,'Criterios de priorización'!$E$5:$F$8,2,FALSE)*'Criterios de priorización'!$D$5,0)+IFERROR(VLOOKUP(X26,'Criterios de priorización'!$E$9:$F$12,2,FALSE)*'Criterios de priorización'!$D$9,0)+IFERROR(VLOOKUP(V26,'Criterios de priorización'!$E$13:$F$18,2,FALSE)*'Criterios de priorización'!$D$13,0)+IFERROR(VLOOKUP(U26,'Criterios de priorización'!$E$19:$F$22,2,FALSE)*'Criterios de priorización'!$D$19,0) -> 1.2
A27: 436 | B27: 16/10/2026 10:32:01 | C27: 16/10/2026 10:32:01 | D27: franco.vera@laureate.pe | E27: Franco Manuel Vera Sanchez | F27: Sistematización del Proceso de Reclutamiento y Selección e Incorporación de Docentes mediante solución ATS/DOA UPC | G27: Solución para agilizar los procesos de Reclutamiento y Selección como: Generar y enviar recordatorios y estatus, Realizar convocatorias internas + link de postulación, Capturar y almacenar las postulaciones, entre otros pasos del flujo. Y el proceso de Incorporación. | H27: UPC | I27: Milagros Morgan - Rectorado UPC | J27: Miguel Chang | K27: https://educorpperu.sharepoint.com/sites/ITCS/Documentos%20compartidos/Aplicaciones/Microsoft%20Forms/REGISTRO%20DE%20INICIATIVAS%20-%20GESTI%C3%93N%20DE%20LA%20DEMANDA%20V3/Aprobaci%C3%B3n%20de%20la%20iniciativa%20por%20el%20VP%20del%20%C3%A1rea%20sol/Iniciativas%20SPO%20LEAN%20+%20IA%20DOA%20UPC_Franco%20Manuel%20Vera%20S.pdf | L27: Franco Vera | M27: 46387 | N27: Sí | O27: Digital & IA | P27: 78375 | Q27: Otro | R27: Proceso de selección y reclutamiento manual y poco eficiente. | S27: Automatizando de actividades para generar el informe de relevamiento, el primer filtro, el pre screening, la evaluación psicotécnica, hasta la incorporación.. | T27: Proceso es de Reclutamiento y Selección parar la DOA UPC. | U27: Administrativos | V27: Excelencia operativa | W27: No | X27: Mayor a S/500,000.00 | Y27: Horas liberadas •Incremento de satisfacción de líderes de área. | Z27: https://educorpperu.sharepoint.com/sites/ITCS/_layouts/15/Doc.aspx?sourcedoc=%7BEE07FA39-E724-438B-A3D0-FD0FD4B46FCB%7D&file=Resultados%20Taller%20Cocreaci%C3%B3n%20DOA%20UPC_Franco%20Manuel%20Vera%20S.pptx&action=edit&mobileredirect=true | AA27: =IFERROR(VLOOKUP(N27,'Criterios de priorización'!$E$3:$F$4,2,FALSE)*'Criterios de priorización'!$D$3,0)+IFERROR(VLOOKUP(Q27,'Criterios de priorización'!$E$5:$F$8,2,FALSE)*'Criterios de priorización'!$D$5,0)+IFERROR(VLOOKUP(X27,'Criterios de priorización'!$E$9:$F$12,2,FALSE)*'Criterios de priorización'!$D$9,0)+IFERROR(VLOOKUP(V27,'Criterios de priorización'!$E$13:$F$18,2,FALSE)*'Criterios de priorización'!$D$13,0)+IFERROR(VLOOKUP(U27,'Criterios de priorización'!$E$19:$F$22,2,FALSE)*'Criterios de priorización'!$D$19,0) -> 1.2
A28: 437 | B28: 19/10/2026 13:28:31 | C28: 19/10/2026 13:28:31 | D28: claudia.medina@upn.edu.pe | E28: Claudia Milagros Medina Mancilla | F28: Creación de reporte "Estudiantes por cuarta aptos para registro de matrícula" | G28: Se necesita el reporte para identificar a los estudiantes con reingreso y nuevo reingreso que cuenten con el atributo de 4TAV y hayan realizado el pago del concepto de prematrícula, con la finalidad de proceder con el registro únicamente de los cursos por cuarta que deben llevar, logrando eliminar los reprocesos, reclamos y riesgo de incumplimiento del Reglamento de Estudios y la Ley Universitaria | H28: UPN | I28: Martín Santana - Rectorado UPN | J28: Claudia Medina | K28: https://educorpperu.sharepoint.com/sites/ITCS/Documentos%20compartidos/Aplicaciones/Microsoft%20Forms/REGISTRO%20DE%20INICIATIVAS%20-%20GESTI%C3%93N%20DE%20LA%20DEMANDA%20V3/Aprobaci%C3%B3n%20de%20la%20iniciativa%20por%20el%20VP%20del%20%C3%A1rea%20sol/VB_Claudia%20Medina%20Manci.pdf | L28: Marco Pezo | M28: 46336 | N28: No | O28: 0 | P28: 0 | Q28: Otro | R28: Actualmente, los estudiantes que reingresan con una matrícula condicionada para llevar el curso por cuarta hasta la campaña 2026-2 se autogestionaban el registro de cursos; sin embargo, debido a los errores y reprocesos que se han ejecutado, se ha tomado la decisión que será la Universidad quien registre los cursos por cuarta correspondientes para evitar las incidencias; por lo que se requiere el reporte para identificar a los estudiantes aptos para dicho registro. | S28: Contar con la lista de estudiantes con atributo por 4ta aptos para registro de cursos y proceder con su matrícula de forma administrativa. | T28: Admisión, Procesos de Matrícula, Registros Académicos. | U28: Alumnos | V28: Experiencia | W28: No | X28: No cuantificado o S/0 | Y28: Para los semestres 2026-1 y 2026-2, el 50% de estudiantes por cuarta, tuvieron una matrícula con error, es decir, se registraron en cursos que no les correspondía, por lo que se ha establecido, que estos estudiantes no realizarán su matrícula por autoservicio, sino se le realizará una matrícula administrativa, lo que garantiza un correcto registro y elimina reprocesos, disminuyendo los reclamos y quejas. | Z28: https://educorpperu.sharepoint.com/sites/ITCS/_layouts/15/Doc.aspx?sourcedoc=%7BED596A94-805A-4A79-A2D3-4400676244E6%7D&file=Gesti%C3%B3n%20de%20iniciativas%20-%20Registro%20-%20Reporte%204_Claudia%20Medina%20Manci.pptx&action=edit&mobileredirect=true | AA28: =IFERROR(VLOOKUP(N28,'Criterios de priorización'!$E$3:$F$4,2,FALSE)*'Criterios de priorización'!$D$3,0)+IFERROR(VLOOKUP(Q28,'Criterios de priorización'!$E$5:$F$8,2,FALSE)*'Criterios de priorización'!$D$5,0)+IFERROR(VLOOKUP(X28,'Criterios de priorización'!$E$9:$F$12,2,FALSE)*'Criterios de priorización'!$D$9,0)+IFERROR(VLOOKUP(V28,'Criterios de priorización'!$E$13:$F$18,2,FALSE)*'Criterios de priorización'!$D$13,0)+IFERROR(VLOOKUP(U28,'Criterios de priorización'!$E$19:$F$22,2,FALSE)*'Criterios de priorización'!$D$19,0) -> 1.3
A29: 438 | B29: 19/10/2026 18:10:51 | C29: 19/10/2026 18:10:51 | D29: jorge.tacza@laureate.pe | E29: Jorge Enrique Tacza Duran | F29: Reportes de retiros formales | G29: Se solicita la creación de un reporte de retiros formales con el cual se pueda analizar los retiros y validar que los documentos de los alumnos fueron anulados mediante notas de crédito. El reporte permitirá ejecutar una validación al 100% de los retiros, actualmente al no tener el reporte, el equipo de facturación realiza pruebas muestrales. | H29: UPC | I29: Alex Pendavis - VP Finanzas | J29: Karol Espinoza | K29: https://educorpperu.sharepoint.com/sites/ITCS/Documentos%20compartidos/Aplicaciones/Microsoft%20Forms/REGISTRO%20DE%20INICIATIVAS%20-%20GESTI%C3%93N%20DE%20LA%20DEMANDA%20V3/Aprobaci%C3%B3n%20de%20la%20iniciativa%20por%20el%20VP%20del%20%C3%A1rea%20sol/RE_%20Nuevos%20reportes%202027%20-%20FBCC_%20Jorge%20Enriqu_Jorge%20Enrique%20Tacza.pdf | L29: Gerson Vereau | M29: 46388 | N29: No | O29: 0 | P29: 0 | Q29: Otro | R29: No se cuenta con un reporte del proceso formal de retiros que permita evaluar la trazabilidad de la operación. Este reporte permitirá reducir errores y carga operativa. | S29: Evitar reprocesos y errores manuales. Así como reportes automatizados | T29: Facturación, control interno, retenciones y otros | U29: Administrativos | V29: Excelencia operativa | W29: No | X29: No cuantificado o S/0 | Y29: Mejora el proceso de trámite de retiros | Z29: https://educorpperu.sharepoint.com/sites/ITCS/_layouts/15/Doc.aspx?sourcedoc=%7BF1607338-6160-4FD3-B28E-7406FA9E1DB3%7D&file=Gesti%C3%B3n%20de%20iniciativas%20-%20Retiros%20formales_Jorge%20Enrique%20Tacza.pptx&action=edit&mobileredirect=true | AA29: =IFERROR(VLOOKUP(N29,'Criterios de priorización'!$E$3:$F$4,2,FALSE)*'Criterios de priorización'!$D$3,0)+IFERROR(VLOOKUP(Q29,'Criterios de priorización'!$E$5:$F$8,2,FALSE)*'Criterios de priorización'!$D$5,0)+IFERROR(VLOOKUP(X29,'Criterios de priorización'!$E$9:$F$12,2,FALSE)*'Criterios de priorización'!$D$9,0)+IFERROR(VLOOKUP(V29,'Criterios de priorización'!$E$13:$F$18,2,FALSE)*'Criterios de priorización'!$D$13,0)+IFERROR(VLOOKUP(U29,'Criterios de priorización'!$E$19:$F$22,2,FALSE)*'Criterios de priorización'!$D$19,0) -> 0.6
A30: 439 | B30: 20/10/2026 11:17:15 | C30: 20/10/2026 11:17:15 | D30: franco.vera@laureate.pe | E30: Franco Manuel Vera Sanchez | F30: Mejoramiento de ETL para funnel de Retención | G30: Se requiere la migración de Integration Services a AWS. Para no contar con servidores On Premise, logrando cumplir con los estándares de seguridad y arquitectura vigentes. | H30: UPN | I30: Álvaro Valdez - VP Operaciones | J30: Mirella Concha | K30: https://educorpperu.sharepoint.com/sites/ITCS/Documentos%20compartidos/Aplicaciones/Microsoft%20Forms/REGISTRO%20DE%20INICIATIVAS%20-%20GESTI%C3%93N%20DE%20LA%20DEMANDA%20V3/Aprobaci%C3%B3n%20de%20la%20iniciativa%20por%20el%20VP%20del%20%C3%A1rea%20sol/VB%20Alvaro%20Valdez_ETL_Franco%20Manuel%20Vera%20S.pdf | L30: Gerson Vereau | M30: 46423 | N30: No | O30: 0 | P30: 0 | Q30: Seguridad TI | R30: Servidores sobre cargados y On Premise | S30: Mejoramiento de ETL con migración a AWS | T30: Retenciones y todos los procesos involucrados. | U30: Administrativos | V30: Excelencia operativa | W30: No | X30: Mayor a S/500,000.00 | Y30: Aprovechamiento, orden y eficiencia previo a cada inicio de periodos. | Z30: https://educorpperu.sharepoint.com/sites/ITCS/_layouts/15/Doc.aspx?sourcedoc=%7BB40EF229-B8EF-4A9E-8430-CBBEBD95D190%7D&file=Gesti%C3%B3n%20de%20iniciativas%20-%20Proceso%20y%20registro_Franco%20Manuel%20Vera%20S.pptx&action=edit&mobileredirect=true | AA30: =IFERROR(VLOOKUP(N30,'Criterios de priorización'!$E$3:$F$4,2,FALSE)*'Criterios de priorización'!$D$3,0)+IFERROR(VLOOKUP(Q30,'Criterios de priorización'!$E$5:$F$8,2,FALSE)*'Criterios de priorización'!$D$5,0)+IFERROR(VLOOKUP(X30,'Criterios de priorización'!$E$9:$F$12,2,FALSE)*'Criterios de priorización'!$D$9,0)+IFERROR(VLOOKUP(V30,'Criterios de priorización'!$E$13:$F$18,2,FALSE)*'Criterios de priorización'!$D$13,0)+IFERROR(VLOOKUP(U30,'Criterios de priorización'!$E$19:$F$22,2,FALSE)*'Criterios de priorización'!$D$19,0) -> 2.1
A31: 440 | B31: 21/10/2026 17:44:34 | C31: 21/10/2026 17:44:34 | D31: franco.vera@laureate.pe | E31: Franco Manuel Vera Sanchez | F31: Sede Piura UPN | G31: Revisión integral del frente TI - Aplicaciones Comerciales | H31: UPN | I31: Álvaro Valdez - VP Operaciones | J31: Sharon Chou | K31: https://educorpperu.sharepoint.com/sites/ITCS/Documentos%20compartidos/Aplicaciones/Microsoft%20Forms/REGISTRO%20DE%20INICIATIVAS%20-%20GESTI%C3%93N%20DE%20LA%20DEMANDA%20V3/Aprobaci%C3%B3n%20de%20la%20iniciativa%20por%20el%20VP%20del%20%C3%A1rea%20sol/VB%20UPN%20Ica%20y%20Piura_Katia_Franco%20Manuel%20Vera%20S.pdf | L31: Franco Vera | M31: 46447 | N31: No | O31: 0 | P31: 0 | Q31: Otro | R31: Completar el Gantt de actividades desde el frente de TI - Aplicaciones Comerciales | S31: Completar el Gantt de actividades desde el frente de TI - Aplicaciones Comerciales | T31: VP TTD | U31: Todos | V31: Crecimiento escalable | W31: No | X31: No cuantificado o S/0 | Y31: Nueva sede UPN Piura | Z31: https://educorpperu.sharepoint.com/sites/ITCS/Documentos%20compartidos/Aplicaciones/Microsoft%20Forms/REGISTRO%20DE%20INICIATIVAS%20-%20GESTI%C3%93N%20DE%20LA%20DEMANDA%20V3/Adjuntar%20ppt%20de%20la%20iniciativa/LRP%20Budget%20and%20CIPS%20-%20Laureate%20Board_Katia_Franco%20Manuel%20Vera%20S.pdf | AA31: =IFERROR(VLOOKUP(N31,'Criterios de priorización'!$E$3:$F$4,2,FALSE)*'Criterios de priorización'!$D$3,0)+IFERROR(VLOOKUP(Q31,'Criterios de priorización'!$E$5:$F$8,2,FALSE)*'Criterios de priorización'!$D$5,0)+IFERROR(VLOOKUP(X31,'Criterios de priorización'!$E$9:$F$12,2,FALSE)*'Criterios de priorización'!$D$9,0)+IFERROR(VLOOKUP(V31,'Criterios de priorización'!$E$13:$F$18,2,FALSE)*'Criterios de priorización'!$D$13,0)+IFERROR(VLOOKUP(U31,'Criterios de priorización'!$E$19:$F$22,2,FALSE)*'Criterios de priorización'!$D$19,0) -> 1.4
A32: 441 | B32: 21/10/2026 17:48:13 | C32: 21/10/2026 17:48:13 | D32: franco.vera@laureate.pe | E32: Franco Manuel Vera Sanchez | F32: Sede Ica UPN | G32: Revisión integral del frente Aplicaciones Comerciales | H32: UPN | I32: Álvaro Valdez - VP Operaciones | J32: Sharon Chou | K32: https://educorpperu.sharepoint.com/sites/ITCS/Documentos%20compartidos/Aplicaciones/Microsoft%20Forms/REGISTRO%20DE%20INICIATIVAS%20-%20GESTI%C3%93N%20DE%20LA%20DEMANDA%20V3/Aprobaci%C3%B3n%20de%20la%20iniciativa%20por%20el%20VP%20del%20%C3%A1rea%20sol/VB%20UPN%20Ica%20y%20Piura_Katia_Franco%20Manuel%20Vera%20S%201.pdf | L32: Franco Vera | M32: 46447 | N32: No | O32: 0 | P32: 0 | Q32: Otro | R32: Completar el Gantt de actividades desde el frente de TI - Aplicaciones Comerciales | S32: Completar el Gantt de actividades desde el frente de TI - Aplicaciones Comerciales | T32: VP TTD | U32: Todos | V32: Crecimiento escalable | W32: No | X32: No cuantificado o S/0 | Y32: Nueva sede UPN Ica | Z32: https://educorpperu.sharepoint.com/sites/ITCS/Documentos%20compartidos/Aplicaciones/Microsoft%20Forms/REGISTRO%20DE%20INICIATIVAS%20-%20GESTI%C3%93N%20DE%20LA%20DEMANDA%20V3/Adjuntar%20ppt%20de%20la%20iniciativa/LRP%20Budget%20and%20CIPS%20-%20Laureate%20Board_Katia_Franco%20Manuel%20Vera%20S%201.pdf | AA32: =IFERROR(VLOOKUP(N32,'Criterios de priorización'!$E$3:$F$4,2,FALSE)*'Criterios de priorización'!$D$3,0)+IFERROR(VLOOKUP(Q32,'Criterios de priorización'!$E$5:$F$8,2,FALSE)*'Criterios de priorización'!$D$5,0)+IFERROR(VLOOKUP(X32,'Criterios de priorización'!$E$9:$F$12,2,FALSE)*'Criterios de priorización'!$D$9,0)+IFERROR(VLOOKUP(V32,'Criterios de priorización'!$E$13:$F$18,2,FALSE)*'Criterios de priorización'!$D$13,0)+IFERROR(VLOOKUP(U32,'Criterios de priorización'!$E$19:$F$22,2,FALSE)*'Criterios de priorización'!$D$19,0) -> 1.4
A33: 442 | B33: 22/10/2026 01:15:00 | C33: 22/10/2026 01:15:00 | D33: carlos.martinez@laureate.pe | E33: Carlos Cesar Martinez Moreno | F33: Implementación de monitoreo y reintento automático del ETL Banner–Blackboard UPC | G33: Necesitamos implementar un mecanismo automático de monitoreo, detención y reintento del proceso ETL Banner–Blackboard, para evitar que una ejecución bloqueada impida la generación de la información necesaria para la clonación de cursos EPE, logrando mejorar la continuidad del proceso y reducir el riesgo de afectación a docentes y alumnos. | H33: UPC | I33: Humberto Marotta - Tecnologías y transformación digital | J33: Carlos César Martínez Moreno | K33: https://educorpperu.sharepoint.com/sites/ITCS/_layouts/15/Doc.aspx?sourcedoc=%7B98A511D4-D85B-4BDA-A20B-88AA9203C508%7D&file=20-08-2026-INC1361083-UPC-[TICKET%20PADRE%20INC13_Carlos%20Cesar%20Martine.docx&action=default&mobileredirect=true | L33: Marco Pezo | M33: 46336 | N33: No | O33: 0 | P33: 0 | Q33: ITSM | R33: Actualmente, el proceso ETL encargado de extraer información de EPE desde Banner hacia Blackboard presenta una falla que provoca que no se generen todos los archivos necesarios para su posterior carga al aula virtual. Esto impide iniciar oportunamente el proceso de clonación de cursos EPE y genera riesgo de afectación al acceso de docentes y alumnos a sus aulas próximas a iniciar clases. El análisis posterior identificó que existe un bloqueo de una tabla a nivel de Integration Service y que se requiere un desarrollo que permita controlar las sesiones y el tiempo de las transacciones. | S33: Contar con un proceso ETL Banner–Blackboard supervisado automáticamente, capaz de detectar ejecuciones bloqueadas, detener la sesión afectada y realizar un reintento automático del proceso. Asimismo, se busca disponer de alertas automáticas al equipo de TI cuando se produzca una interrupción/reintento o cuando el segundo intento no concluya correctamente. | T33: Procesos: Integración Banner–Blackboard. ETL de extracción de información asociada a EPE. Generación de información para la clonación de cursos EPE. Disponibilidad/acceso a aulas virtuales Blackboard. Área identificada: Academia UPC. Usuarios impactados: docentes y alumnos de EPE asociados a los cursos involucrados | U33: Todos | V33: Excelencia operativa | W33: No | X33: No cuantificado o S/0 | Y33: continuidad del ETL + recuperación automática + alertamiento TI + reducción del riesgo de afectación académica. | Z33: https://educorpperu.sharepoint.com/sites/ITCS/_layouts/15/Doc.aspx?sourcedoc=%7B08F36969-37C7-403A-BDDC-7F42DD9E399E%7D&file=20-08-2026-INC1361083-UPC-[TICKET%20PADRE%20INC13_Carlos%20Cesar%20Martine.docx&action=default&mobileredirect=true | AA33: =IFERROR(VLOOKUP(N33,'Criterios de priorización'!$E$3:$F$4,2,FALSE)*'Criterios de priorización'!$D$3,0)+IFERROR(VLOOKUP(Q33,'Criterios de priorización'!$E$5:$F$8,2,FALSE)*'Criterios de priorización'!$D$5,0)+IFERROR(VLOOKUP(X33,'Criterios de priorización'!$E$9:$F$12,2,FALSE)*'Criterios de priorización'!$D$9,0)+IFERROR(VLOOKUP(V33,'Criterios de priorización'!$E$13:$F$18,2,FALSE)*'Criterios de priorización'!$D$13,0)+IFERROR(VLOOKUP(U33,'Criterios de priorización'!$E$19:$F$22,2,FALSE)*'Criterios de priorización'!$D$19,0) -> 2.1
A34: 443 | B34: 22/10/2026 11:20:19 | C34: 22/10/2026 11:20:19 | D34: jhonatan.sanchez@upn.edu.pe | E34: Jhonatan Fernando Sanchez Zambrano | F34: Descompactador de cursos virtuales (cursos virtuales modulares) | G34: Necesitamos que los NRC destino en los que el descompactador matricula a los estudiantes, esté alienado al modulo que seleccionó como NRC Bolsón. | H34: UPN | I34: Álvaro Valdez - VP Operaciones | J34: Jhonatan Fernando Sanchez Zambrano | K34: https://educorpperu.sharepoint.com/sites/ITCS/Documentos%20compartidos/Aplicaciones/Microsoft%20Forms/REGISTRO%20DE%20INICIATIVAS%20-%20GESTI%C3%93N%20DE%20LA%20DEMANDA%20V3/Aprobaci%C3%B3n%20de%20la%20iniciativa%20por%20el%20VP%20del%20%C3%A1rea%20sol/VB%20DOA_Jhonatan%20Sanchez%20Zam.pdf | L34: Carla Arias-Schreiber | M34: 46371 | N34: No | O34: 0 | P34: 0 | Q34: Otro | R34: Los estudiantes al seleccionar NRC bolsones (modulares), el descompactador no está registrándolos en un NRC del mismo módulo | S34: Que el descompactador envié a los NRC destino considerando el modulo del NRC bolzón | T34: - | U34: Alumnos | V34: Excelencia académica | W34: No | X34: No cuantificado o S/0 | Y34: Disminuir reclamos y mejorar la satisfacción de los estudiantes. | Z34: https://educorpperu.sharepoint.com/sites/ITCS/_layouts/15/Doc.aspx?sourcedoc=%7BA07FF862-A472-417A-8A3F-41AE30172B39%7D&file=SOLICITUD%20DESCOMPACTADOR%20BLSN%2009-09-2026_Jhonatan%20Sanchez%20Zam.pptx&action=edit&mobileredirect=true | AA34: =IFERROR(VLOOKUP(N34,'Criterios de priorización'!$E$3:$F$4,2,FALSE)*'Criterios de priorización'!$D$3,0)+IFERROR(VLOOKUP(Q34,'Criterios de priorización'!$E$5:$F$8,2,FALSE)*'Criterios de priorización'!$D$5,0)+IFERROR(VLOOKUP(X34,'Criterios de priorización'!$E$9:$F$12,2,FALSE)*'Criterios de priorización'!$D$9,0)+IFERROR(VLOOKUP(V34,'Criterios de priorización'!$E$13:$F$18,2,FALSE)*'Criterios de priorización'!$D$13,0)+IFERROR(VLOOKUP(U34,'Criterios de priorización'!$E$19:$F$22,2,FALSE)*'Criterios de priorización'!$D$19,0) -> 1.4
A35: 444 | B35: 22/10/2026 16:08:57 | C35: 22/10/2026 16:08:57 | D35: jose.herbozo@laureate.pe | E35: José Luis Paredes Herbozo | F35: Incorporación de fechas de gestión y trazabilidad del prospecto en el Plano 365. | G35: Necesitamos incorporar cinco campos de fechas al Plano 365 (primera llamada con resultado Contacto, Efectivo e Interesado, creación original del prospecto y primera aparición del lead en la campaña), para eliminar la falta de visibilidad sobre cuándo ingresa un lead y cuándo alcanza cada hito de gestión, logrando que la Vicepresidencia Comercial haga seguimiento de la campaña en curso con fechas verificables contra los registros de origen. | H35: UPN | I35: Ivan Olivares - VP Marketing y Comercial | J35: Juan Mina | K35: https://educorpperu.sharepoint.com/sites/ITCS/Documentos%20compartidos/Aplicaciones/Microsoft%20Forms/REGISTRO%20DE%20INICIATIVAS%20-%20GESTI%C3%93N%20DE%20LA%20DEMANDA%20V3/Aprobaci%C3%B3n%20de%20la%20iniciativa%20por%20el%20VP%20del%20%C3%A1rea%20sol/olk_YB2PXEGMeR_Jos%C3%A9%20Paredes%20Herbozo.png | L35: José Paredes | M35: 46338 | N35: No | O35: 0 | P35: 0 | Q35: Otro | R35: El Plano 365 no incluye las fechas de la primera llamada con resultado Contacto, Efectivo e Interesado dentro de la campaña en curso, ni la fecha original de creación del prospecto ni la de su primera aparición en el plano. Por eso la Vicepresidencia Comercial no puede medir cuándo ingresa un lead ni cuánto tarda en alcanzar cada hito de gestión, y su seguimiento queda limitado. Si no se implementa en la fecha requerida, la información debería obtenerse de forma manual y temporal, cruzando los registros de llamadas y de creación de prospectos del CRM con el plano. Ese cruce sería más lento y con mayor riesgo de inconsistencias. Además, la primera aparición en el plano no podría reconstruirse sin un histórico del plano o un registro persistente de ingreso. | S35: El Plano 365 se genera con cinco campos adicionales por lead y campaña: Fecha de primera llamada con resultado Contacto. Fecha de primera llamada con resultado Efectivo. Fecha de primera llamada con resultado Interesado. Fecha original de creación del prospecto. Fecha de primera aparición del lead en el plano. | T35: Procesos: generación del Plano 365. Plataformas: CRM y proceso de generación del Plano 365. Áreas y usuarios: Vicepresidencia Comercial (solicitante y beneficiaria), equipo responsable del Plano 365 (incorpora y valida los campos) y BI (valida definiciones y consistencia de resultados). | U35: Administrativos | V35: Excelencia operativa | W35: No | X35: No cuantificado o S/0 | Y35: Mejor seguimiento comercial: la Vicepresidencia Comercial podrá ver cuándo cada lead alcanza por primera vez los resultados Contacto, Efectivo e Interesado dentro de la campaña en curso. Mejores decisiones: al conocer los tiempos entre ingreso, gestión y resultado, se pueden identificar demoras y ajustar la estrategia de la campaña. Trazabilidad del prospecto: se conservan la fecha original de creación y la primera aparición en el plano, aunque el prospecto participe en campañas posteriores o el plano se actualice. Confiabilidad de la información: las fechas provienen de los registros de origen y se validan con una muestra, lo que reduce inconsistencias. Menos trabajo manual: se evita cruzar a mano los registros de llamadas y de creación de prospectos con el plano. Definiciones alineadas: BI y el equipo del Plano 365 confirman los criterios (campaña vigente, códigos de resultado, llave del lead), lo que da una lectura única de los hitos de gestión. | Z35: https://educorpperu.sharepoint.com/sites/ITCS/_layouts/15/Doc.aspx?sourcedoc=%7B29E1D272-23B7-407A-A05C-CDA30DF1F136%7D&file=Solicitud_campos_adicionales_Plano_365_Jos%C3%A9%20Paredes%20Herbozo.docx&action=default&mobileredirect=true | AA35: =IFERROR(VLOOKUP(N35,'Criterios de priorización'!$E$3:$F$4,2,FALSE)*'Criterios de priorización'!$D$3,0)+IFERROR(VLOOKUP(Q35,'Criterios de priorización'!$E$5:$F$8,2,FALSE)*'Criterios de priorización'!$D$5,0)+IFERROR(VLOOKUP(X35,'Criterios de priorización'!$E$9:$F$12,2,FALSE)*'Criterios de priorización'!$D$9,0)+IFERROR(VLOOKUP(V35,'Criterios de priorización'!$E$13:$F$18,2,FALSE)*'Criterios de priorización'!$D$13,0)+IFERROR(VLOOKUP(U35,'Criterios de priorización'!$E$19:$F$22,2,FALSE)*'Criterios de priorización'!$D$19,0) -> 0.6

Sheet Registro incompleto
A1: Id | B1: Hora de inicio | C1: Hora de finalización | D1: Correo electrónico | E1: Nombre | F1: Título de la INICIATIVA | G1: Objetivo | H1: Institución | I1: VP del área solicitante | J1: Usuario solicitante del negocio | K1: Aprobación de la iniciativa por el VP o Director | L1: IT BP | M1: Fecha de entrega requerida | N1: Proyecto SPO | O1: Workstream del proyecto SPO | P1: ID SPO | Q1: Tipo de iniciativa | R1: Descripción del problema o desafío | S1: Situación deseada | T1: Procesos y áreas impactadas | U1: Usuarios beneficiados1 | V1: Pilar estratégico | W1: Forma parte de la estabilización de procesos SIS | X1: Beneficio cuantitativo (anual) | Y1: Beneficios cualitativos | Z1: Adjuntar ppt de la iniciativa | AA1: Puntaje Sugerido | AB1: Líder de Dominio | AC1: Asignado por | AD1: Fecha de asignación del LD | AE1: Complejidad | AF1: Fecha inicio (estimación) | AG1: Fecha fin (estimación) | AH1: Tiempo estimado (meses) | AI1: Costo dolares | AJ1: Costo Soles | AK1: Asunciones | AL1: Recursos internos o externos | AM1: Indicar si es Proyecto o Requerimiento No BAU | AN1: Estatus Estimación | AO1: Comentarios | AP1: Completar información
A2: 144 | B2: 46153.674 | C2: 46153.701 | D2: carla.arias@laureate.pe | E2: Carla Arias Schreiber Ulloa | F2: Matrícula de new convalidantes | G2: Implementar una nueva funcionalidades que permita registrar de manera automática los cursos de estudiantes nuevos con convalidación, a fin de asegurar el 100% de atención sin retrasos hacia los estudiantes por fallas y necesidad de registro manual. A partir de la malla gutemberg el RPA presenta fallas y Nicolás Morales sugirió evaluar otra solución que cubra la totalidad de reglas de negocio. | H2: UPN | I2: Martín Santana - Rectorado UPN | J2: Luz Marina Flores | K2: https://educorpperu-my.sharepoint.com/personal/diana_zapata_laureate_pe1/Documents/Aplicaciones/Microsoft%20Forms/REGISTRO%20DE%20INICIATIVAS%20-%20GESTI%C3%93N%20DE%20LA%20DEMANDA%20(2%201/Pregunta/Director%20S.A._Carla%20Arias%20Schreibe.png | L2: Carla Arias-Schreiber | M2: 46185 | N2: No | O2: 0 | Q2: Otro | R2: En el 26-1 el RPA de registro de cursos de horarios para estudiantes convalidantes presenta problemas, por lo que el 73.4% de horarios tuvieron que ser ingresados de forma manual e individual (+ 5K). Lo cual impactó el avance de la meta de ventas, el tiempo de atención a estudiantes e implicó que 3 colaboradores tuviesen que dedicar 70% de su tiempo, de lunes a domingo, durante 1 mes; 2 colaboradores de otra área de la dirección. | S2: Por recomendación de Nicolás Morales, contar con una nueva funcionalidad que pueda cubrir el registro de horarios automático o masivo+programado. El RPA no puede sostener este proceso, ya que con las nuevas reglas académicas, duplicaría su tiempo de procesamiento y bajaría su capacidad de cantidad de registros. | T2: Admisión y matrícula de nuevos estudiantes, con convalidación | U2: Alumnos | V2: Excelencia operativa | W2: NO | X2: No cuantificado o S/0 | Y2: Entrega oportuna de horarios. Durante matrícula extempóranea se espera que a más tardar al día siguiente ya tengan cursos matriculados. Por los problemas, el SLA ha sido de hasta 1 semana, impactando el inicio de clases de manera significativa. | Z2: https://educorpperu-my.sharepoint.com/personal/diana_zapata_laureate_pe1/Documents/Aplicaciones/Microsoft%20Forms/REGISTRO%20DE%20INICIATIVAS%20-%20GESTI%C3%93N%20DE%20LA%20DEMANDA%20(2%201/Adjuntar%20sustentos%20que%20ayuden%20al%20entendimiento%20de/Impactos%20M%C3%B3nica%20Garcia_Carla%20Arias%20Schreibe.png | AA2: 1.05 | AB2: Ana Vega | AC2: AM | AD2: 46183 | AE2: Media | AO2: Incompleto | AP2: - 22/06: Se devuelve el requerimiento ya que no se tiene las reglas completas - DOA quiere validar si las nuevas reglas en el RPA actual funcionan Ok, porque son las que se quieren trasladar a esta nueva funcionalidad. Deadline 03/07. - Aún no podemos evidenciar la correcta funcionalidad de las nuevas reglas, necesarias para la inclusión de este requerimiento.
A3: 341 | B3: 46239.488 | C3: 46239.507 | D3: suly.kong@upn.edu.pe | E3: Suly Kong Paredes | F3: Implementación de una Plataforma Integral de Gestión Documental para Procedimientos Disciplinarios | G3: Necesitamos implementar una plataforma digital e interactiva en línea para la gestión documental y el seguimiento automatizado de procedimientos disciplinarios (hostigamiento sexual, disciplina estudiantil, docentes y egresados) que incluya un canal de acceso seguro para los usuarios, para que se elimine la dispersión de información, la falta de trazabilidad, el registro manual y la necesidad de atención presencial para consultas de expedientes, logrando centralizar el 100% de los casos en una base de datos segura, brindar acceso a la información en tiempo real, optimizar la interoperabilidad institucional y reducir significativamente los tiempos de atención, control y respuesta bajo los estándares de transparencia de la era digital | H3: UPN | I3: Martín Santana - Rectorado UPN | J3: Suly Kong | K3: https://educorpperu-my.sharepoint.com/personal/diana_zapata_laureate_pe1/Documents/Aplicaciones/Microsoft%20Forms/REGISTRO%20DE%20INICIATIVAS%20-%20GESTI%C3%93N%20DE%20LA%20DEMANDA%20(2%201/Pregunta/aprobaci%C3%B3n%20de%20Alex%20Rueda%20-%20proyectos_Suly%20Kong%20Paredes.pdf | L3: Gerson Vereau | M3: 46266 | N3: No | O3: 0 | P3: 0 | Q3: Regulatoria | R3: Actualmente, la gestión de los procedimientos disciplinarios (hostigamiento sexual, disciplina estudiantil, docentes y egresados) se realizan con una alta dependencia de procesos manuales, basados en el flujo de correos electrónicos. Esta situación genera riesgos operacionales para el área, tales como la limitada trazabilidad y vulnerabilidad de la información crítica y confidencial contenida en los expedientes, la pérdida de continuidad en el seguimiento digital, como los documentos que se reciben en el correo electrónico, Al depender de correos electrónicos, la información de un mismo caso podría quedar disgregada en varios mensajes, corriendo el riesgo de omitir revisar archivos adjuntos. perdiendo la secuencia del proceso. Esta situación puede generar la nulidad del procedimiento y la parte que debe ser sancionada, por estos defectos, no reciba la penalidad que le corresponde. Asimismo, existe una brecha de comunicación que afecta directamente a las partes interesadas: por un lado, los estudiantes alegan desconocimiento del estado de sus procedimientos o de las actuaciones realizadas argumentando la falta de revisión del correo institucional. Por otro lado, debido a que los Directores Académicos de Sede carecen de una visibilidad integral y en tiempo real sobre los procesos y las sanciones vigentes de sus alumnos, las autoridades locales se ven imposibilitadas de aplicar medidas preventivas o correctivas oportunas. Esta falta de control y monitoreo centralizado limita la capacidad de fiscalización normativa, compromete el resguardo seguro de la información confidencial y restringe la interactividad necesaria con la comunidad universitaria. | S3: Con esta iniciativa, se espera implementar una plataforma digital centralizada que automatice y unifique la gestión de todos los procedimientos disciplinarios (hostigamiento sexual, disciplina estudiantil, docentes y egresados). Asimismo, lograr una trazabilidad completa (end-to-end) de los expedientes electrónicos, garantizando el resguardo seguro y confidencial de la información y eliminando el riesgo de omitir en la evaluación archivos virtuales. Asimismo, se busca transformar la gobernanza institucional y la experiencia del usuario: los Directores Académicos de Sede contarán con visibilidad integral y en tiempo real sobre las sanciones vigentes para aplicar medidas preventivas o correctivas oportunas, mientras que la comunidad estudiantil dispondrá de un canal interactivo y transparente para consultar el estado de sus procesos y con ello no alegará desconocimiento de dicho. Finalmente, la plataforma garantiza la notificación oportuna del estado disciplinario del estudiante antes del proceso de matrícula. Esto elimina la generación de cargos por gastos administrativos derivados de anulaciones o devoluciones, optimizando los tiempos del equipo administrativo y reduciendo la fricción financiera con el usuario. | T3: Ética & Compliance, GTH | U3: Todos | V3: Excelencia operativa | W3: No | X3: No cuantificado o S/0 | Y3: Beneficios esperados (Logrando) Registro centralizado y digital del 100% de los expedientes disciplinarios. Trazabilidad completa de cada procedimiento desde su inicio hasta su cierre. Consulta en tiempo real del estado del expediente por parte de estudiantes y autoridades competentes. Carga y gestión ordenada de documentos y evidencias en cada acto procedimental. Reducción de tiempos administrativos y eliminación del manejo manual de expedientes. Mayor transparencia, control y cumplimiento del debido proceso. Disponibilidad permanente de información para auditorías, reportes y toma de decisiones. Implementación de un canal de gestión documental preventivo Este proyecto posiciona a la universidad a la vanguardia tecnológica y de automatización. Al migrar de formatos impresos a una plataforma en línea, moderna y segura, se transforma la experiencia del estudiante, consolidando la reputación de la institución como un referente de innovación digital y eficiencia administrativa en el sector educativo | Z3: https://educorpperu.sharepoint.com/:f:/s/Repositorio_EquipoCentral/dit/portafoliosyp/IgC0D-K9qsfhR6H90QVDuilZAZXDIfAuTcI8HH1HIRowO4Y?e=1CmdKI | AA3: 2.7 | AB3: Nohelí Cabrera | AC3: AM | AD3: 46247 | AO3: Incompleto | AP3: 20/08 LD Indica que se requiere mayor detalle para completar la estimación
A4: 375 | B4: 46258.983 | C4: 46259.002 | D4: javier.santiago@laureate.pe | E4: Javier Santiago Modesto | F4: Api CRM para registro de información de Trámites Carpeta Bachiller | G4: Necesitamos asegurar el registro de información relevante de Trámites Carpeta Bachiller, para garantizar la integridad de la información con CRM, logrando que el 100% de los trámites carpeta bachiller estén identificados correctamente en CRM. | H4: UPN | I4: Mónica García - VP Operaciones Digitales y Online | J4: Jose M. Horna Aguirre | K4: https://educorpperu-my.sharepoint.com/personal/diana_zapata_laureate_pe1/Documents/Aplicaciones/Microsoft%20Forms/REGISTRO%20DE%20INICIATIVAS%20-%20GESTI%C3%93N%20DE%20LA%20DEMANDA%20(2%201/Pregunta/APROBACI%C3%93N%20DE%20AREA%20SOLICITANTE_Javier%20Santiago%20Mode.pdf | L4: Carla Arias-Schreiber | M4: 46280 | N4: No | O4: 0 | P4: 0 | Q4: Otro | R4: La implementación de Trámites Carpeta Bachiller en el portal del estudiante UPN requiere de la integración de una API CRM para el registro de información relevante del alumno y los estados de trámites bachiller. Mientras no se cuente con la api CRM, la información se gestionara por medio de reportes de analítica web (taggeo). | S4: API CRM permitirá registrar información relevante de trámites carpeta bachiller, para fines de reporteria de CRM. | T4: CRM, Grados y Títulos, Experiencia del estudiante | U4: Alumnos | V4: Excelencia operativa | W4: No | X4: No cuantificado o S/0 | Y4: Reportería y gestión de Trámites Bachiller por estados (solicitados, anulados, pagados, observados) | Z4: https://educorpperu-my.sharepoint.com/personal/diana_zapata_laureate_pe1/_layouts/15/Doc.aspx?sourcedoc=%7B783048F0-0DE4-4F72-B0C9-7240C63CFF31%7D&file=Solicitud%20de%20requerimientos%20Idea%20nueva%20y%20mejo_Javier%20Santiago%20Mode%202.pptx&action=edit&mobileredirect=true | AA4: 1.2 | AB4: César Soplín | AC4: AM | AD4: 46260 | AO4: Incompleto | AP4: La información es recibida es solo un slide y requerimos mayor información para poder implementar (AS-IS, TO-BE, reglas de negocio, etc.) Hemos marcado el pedido como incompleto hasta puedan subsanar lo solicitado.
A5: 269 | B5: 46211.678 | C5: 46211.687 | D5: carla.arias@laureate.pe | E5: Carla Arias Schreiber Ulloa | F5: Equivalencias imperfectas | G5: Registrar en Banner las equivalencias "imperfectas" originadas por la malla Gutemberg, donde se presentan 3 escenarios que hoy el sistema no soporta, para asegurar la correcta trazabilidad, minimizar los impactos en registros/ procesos académicos y mitigar contingencias legales, logrando eliminar el trabajo manual de los equipos académicos, errores en asignación de cursos y alto nivel de tickets + reclamos de estudiantes. | H5: UPN | I5: Martín Santana - Rectorado UPN | J5: Giancarlo Flores | K5: https://educorpperu-my.sharepoint.com/personal/diana_zapata_laureate_pe1/Documents/Aplicaciones/Microsoft%20Forms/REGISTRO%20DE%20INICIATIVAS%20-%20GESTI%C3%93N%20DE%20LA%20DEMANDA%20(2%201/Pregunta/VB%20Rector%20UPN_Carla%20Arias%20Schreibe.png | L5: Carla Arias-Schreiber | M5: 46353 | N5: No | O5: 0 | P5: 0 | Q5: Otro | R5: Actualmente en el sistema Banner no se pueden registrar equivalencias académicas con la malla gutemberg, bajo los siguientes escenarios: 2 cursos equivalen a 1 o viceversa, o donde en equivalencias 1 a 1 el creditaje es mayor (impacto financiero a estudiantes con contigencia legal). | S5: Que el sistema soporta los tres escenarios descritos en la ppt adjunta. | T5: Matrícula Registro académicos Egreso y grados/ títulos Operaciones académicas | U5: Alumnos | V5: Excelencia académica | W5: No | X5: No cuantificado o S/0 | Y5: Asegurar el correcto avance académico de nuestros estudiantes y egreso. | Z5: https://educorpperu-my.sharepoint.com/personal/diana_zapata_laureate_pe1/_layouts/15/Doc.aspx?sourcedoc=%7B85F19B8A-D1D8-4393-94E6-0FE9A9BC1CB9%7D&file=Gesti%C3%B3n%20de%20Iniciativas%20-%20Equivalencias%2027-1_Carla%20Arias%20Schreibe.pptx&action=edit&mobileredirect=true | AA5: 1.4 | AB5: Ana Vega | AC5: AM | AD5: 46212 | AE5: Alta | AF5: 46268 | AG5: 46296 | AH5: 1 | AL5: Internos | AM5: Proyecto | AN5: SI | AO5: Registro Incompleto | AP5: 03/09: Se realizará un documento funcional junto con negocio a fin de aterrizar las reglas y con ello cotizar la PoC con Neoris. Asimismo, se solicitará al BP cambiar la descripción a PoC y se establecerá como fecha de inicio de la estimación de la PoC el lunes 07/09. 27/08: Coordinar con el BP la priorización de la prueba de concepto, dado que involucra desarrollos del equipo cuya ocupabilidad estará fuera de lo planificado para la estimación (30%), afectando la ejecución de otros proyectos y requerimientos. 20/08: El requerimiento está a muy alto nivel. Con esa información hemos investigado involucrando a nuestro equipo especialista y al proveedor Neoris. De manera nativa, Banner no soporta este tipo de equivalencias, sin embargo, hemos identificado dos posibilidades. Para asegurar que alguna de ellas funcione, se tiene que hacer una prueba de concepto. El estimado, es solo para hacer la prueba. Esta prueba cruza varios dominios, por lo cual se tendría que priorizar. 30/07: Se compartirá sustento de limitación de Banner para lograr el requerimiento 09/07: Asignado a Anthony Marin 08/09 Por cambio en el alcance se clasifica como Registro Incompleto
A6: 349 | B6: 46245.667 | C6: 46245.693 | D6: carla.arias@laureate.pe | E6: Carla Arias Schreiber Ulloa | F6: Visualización y matrícula de cursos virtuales | G6: Habilitar la visualización y matrícula de cursos virtuales con métodos educativos A1, A2 y S1, permitiendo que los estudiantes accedan a la oferta de cualquier sede de Cibertec: Modificar MDUU PRE_ASIGNAR_CAMPUS_PROY, con detalle descrito en la solicitud adjunta. | H6: CIB | I6: Danilo Tauil - GM TecVoc | J6: Spencer Camacho | K6: https://educorpperu-my.sharepoint.com/personal/diana_zapata_laureate_pe1/Documents/Aplicaciones/Microsoft%20Forms/REGISTRO%20DE%20INICIATIVAS%20-%20GESTI%C3%93N%20DE%20LA%20DEMANDA%20(2%201/Pregunta/Captura%20de%20pantalla%202026-08-11%20162410_Carla%20Arias%20Schreibe.png | L6: Carla Arias-Schreiber | M6: 46318 | N6: No | O6: 0 | P6: 0 | Q6: Otro | R6: 20% al 40% en los tickets y consultas asociados a disponibilidad de vacantes y matrícula, y actividades manuales de habilitación de clases. | S6: Que se cumplan con lo detallado en la solicitud adjunta. | T6: Matrícula (pre y rematrícula) | U6: Alumnos | V6: Experiencia | W6: No | X6: Menor a S/100,000.00 | Y6: - Entre el 30 % y el 37 % de los estudiantes de sedes presenciales ampliarían sus opciones de matrícula al acceder a la oferta de cursos virtuales disponible en todas las sedes. - Reducción estimada del 20 % al 40 % en los tickets y consultas asociados a disponibilidad de vacantes y matrícula, al brindar mayor oferta de cursos virtuales desde el inicio del proceso. - Mayor aprovechamiento de la oferta virtual institucional. - Reducción de procesos operativos manuales (tickets, prog. hor., proyección, matricula). - Mejor experiencia de matricula del estudiante. | Z6: https://educorpperu-my.sharepoint.com/personal/diana_zapata_laureate_pe1/_layouts/15/Doc.aspx?sourcedoc=%7B2D6D5900-204F-4E5C-8198-C68E24BD6614%7D&file=Gesti%C3%B3n%20de%20iniciativas%20-%20Visualizaci%C3%B3n%20y%20matr_Carla%20Arias%20Schreibe.pptx&action=edit&mobileredirect=true | AA6: 1.45 | AB6: Ana Vega | AC6: AM | AD6: 46246 | AE6: Media | AF6: 46280 | AG6: 46294 | AO6: Registro Incompleto | AP6: 13/08: Asignado a Sebastián Trujillo 08/09 Por cambio en el alcance se clasifica como Registro Incompleto
A7: 357 | B7: 46248.486 | C7: 46248.506 | D7: carla.arias@laureate.pe | E7: Carla Arias Schreiber Ulloa | F7: Unificación de Códigos de Curso | G7: Estandarización, homologación e integración de la programación académica para cursos que comparten la misma estructura curricular, creditaje y material académico, pero que actualmente se gestionan bajo distintos códigos por pertenecer a diferentes carreras o modalidades. | H7: CIB | I7: Danilo Tauil - GM TecVoc | J7: Spencer Camacho | K7: https://educorpperu-my.sharepoint.com/personal/diana_zapata_laureate_pe1/Documents/Aplicaciones/Microsoft%20Forms/REGISTRO%20DE%20INICIATIVAS%20-%20GESTI%C3%93N%20DE%20LA%20DEMANDA%20(2%201/Pregunta/Captura%20de%20pantalla%202026-08-11%20162410_Carla%20Arias%20Schreibe%201.png | L7: Carla Arias-Schreiber | M7: 46318 | N7: No | O7: 0 | P7: 0 | Q7: Otro | R7: 20% al 30% en los tickets dirigidos a Programación Horaria durante el periodo de matrícula, al eliminar las solicitudes de apertura de grupos secundarios manuales. Hoy no ven disponibles clases del curso, apesar de que sí hay clases disponibles del curso con un código distinto. La razón por la cual existen códigos distintos para el mismo curso (iguales en contenido, horas y créditos) es por actualización de mallas y diferencias entre carreras. | S7: Según detalle de la presentación. Estudiante pueda matricularse sin fricción (ingreso de ticket). | T7: Matrícula Programación de horarios Academia | U7: Alumnos | V7: Experiencia | W7: No | X7: Menor a S/100,000.00 | Y7: - Reducción del Volumen de Tickets en Zendesk: Disminución estimada del 20% al 30% en los tickets dirigidos a Programación Horaria durante el periodo de matrícula, al eliminar las solicitudes de apertura de grupos secundarios manuales. - Aumento en la Tasa de Matrícula Efectiva y Carga Completa: Reducción del abandono o postergación de matrícula por falta percibida de vacantes/horarios, incrementando en un 20% el volumen de alumnos matriculados a tiempo. - Empoderamiento del Alumno (Autogestión / Self-Service): Proceso de matrícula fluido, inmediato y transparente, donde el alumno encuentra vacantes disponibles desde su primer intento. - Precisión e Inteligencia en la Programación Horaria: Capacidad de planificar la oferta académica basándose en la demanda real acumulada y no en proyecciones fragmentadas por código. - Fortalecimiento de la Percepción de Marca y Satisfacción (NPS): Una experiencia de matrícula sin contratiempos impacta positivamente en la retención y en los índices de satisfacción institucional. | Z7: https://educorpperu-my.sharepoint.com/personal/diana_zapata_laureate_pe1/_layouts/15/Doc.aspx?sourcedoc=%7B2ECC5780-851C-47A4-A5C4-033C9918B3C6%7D&file=Gesti%C3%B3n%20de%20iniciativas%20-%20Unificaci%C3%B3n%20C%C3%B3digos_Carla%20Arias%20Schreibe.pptx&action=edit&mobileredirect=true | AA7: 1.45 | AB7: Ana Vega | AC7: AM | AD7: 46251 | AE7: Media | AF7: 46266 | AG7: 46280 | AO7: Registro Incompleto | AP7: 20/08: Asignado a Sebastián Trujillo 08/09 Por cambio en el alcance se clasifica como Registro Incompleto
A8: 432 | B8: 46366.774 | C8: 46366.774 | D8: bruno.chiappe@laureate.pe | E8: Bruno Chiappe Vegas | F8: Implementación del Canal WhatsApp Omnicanal con Asistente Virtual Comercial SofIA | G8: Necesitamos implementar y estandarizar un canal institucional de WhatsApp omnicanal, incorporando al asistente virtual SofIA como asesor educativo comercial y habilitando la atención integrada con los asesores de ventas, para eliminar la fragmentación de las conversaciones, la pérdida de información entre canales y responsables, las limitaciones de atención fuera del horario comercial y la falta de trazabilidad del proceso de captación y seguimiento, logrando una experiencia comercial continua y personalizada, mayor eficiencia operativa, mejor gestión de oportunidades comerciales, incremento de la conversión de prospectos a inscritos y medición integral de los resultados comerciales para UPN, UPC y Cibertec. | H8: LAU | I8: Ivan Olivares - VP Marketing y Comercial | J8: Jaime Medina Salcedo | K8: https://educorpperu.sharepoint.com/sites/ITCS/Documentos%20compartidos/Aplicaciones/Microsoft%20Forms/REGISTRO%20DE%20INICIATIVAS%20-%20GESTI%C3%93N%20DE%20LA%20DEMANDA%20V3/Aprobaci%C3%B3n%20de%20la%20iniciativa%20por%20el%20VP%20del%20%C3%A1rea%20sol/Whatsapp%20Channel%20SofIA%20-%20aprob_Bruno%20Chiappe%20Vegas.pdf | L8: Bruno Chiappe | M8: 46356 | N8: No | O8: 0 | P8: 0 | Q8: Otro | R8: Actualmente, la gestión comercial por WhatsApp presenta fragmentación en la atención, pérdida de contexto entre responsables, limitaciones de atención fuera de horario y falta de coordinación en campañas y seguimientos. Asimismo, existe una limitada trazabilidad de las interacciones y su impacto en las conversiones, dificultando la continuidad comercial, la eficiencia operativa y el aprovechamiento de oportunidades de inscripción. | S8: Contar con un canal institucional de WhatsApp omnicanal para UPN, UPC y Cibertec, que centralice la atención comercial e incorpore a SofIA como asesora virtual para orientar, perfilar, realizar venta consultiva y acompañar al prospecto hacia la inscripción. La solución deberá garantizar continuidad con los asesores de ventas, atención fuera de horario, campañas segmentadas, seguimiento de oportunidades y trazabilidad integral de las gestiones y resultados comerciales. | T8: Procesos: Captación de prospectos, atención comercial, admisión Áreas: Ventas, Marketing Digital, Command Center, Admisión | U8: Alumnos | V8: Experiencia | W8: No | X8: No cuantificado o S/0 | Y8: Mejora de la experiencia del prospecto mediante una atención personalizada, continua y disponible fuera de horario. Mayor eficiencia comercial gracias a la automatización con SofIA, la coordinación con asesores de ventas y el seguimiento oportuno de oportunidades. Asimismo, permite estandarizar la atención entre instituciones, optimizar campañas y fortalecer la trazabilidad, supervisión y toma de decisiones comerciales. | Z8: https://educorpperu.sharepoint.com/sites/ITCS/_layouts/15/Doc.aspx?sourcedoc=%7BC499C532-F918-4659-850F-F2012613C5FD%7D&file=AR_02_Canal_WhatsApp_Channel_y_Asistente_Virt_Bruno%20Chiappe%20Vegas.docx&action=default&mobileredirect=true | AA8: =IFERROR(VLOOKUP(N8,'Criterios de priorización'!$E$3:$F$4,2,FALSE)*'Criterios de priorización'!$D$3,0)+IFERROR(VLOOKUP(Q8,'Criterios de priorización'!$E$5:$F$8,2,FALSE)*'Criterios de priorización'!$D$5,0)+IFERROR(VLOOKUP(X8,'Criterios de priorización'!$E$9:$F$12,2,FALSE)*'Criterios de priorización'!$D$9,0)+IFERROR(VLOOKUP(V8,'Criterios de priorización'!$E$13:$F$18,2,FALSE)*'Criterios de priorización'!$D$13,0)+IFERROR(VLOOKUP(U8,'Criterios de priorización'!$E$19:$F$22,2,FALSE)*'Criterios de priorización'!$D$19,0) -> 1.3 | AB8: Christian Avila | AC8: BC | AD8: 46307 | AG8: =IF(AD8="","Pendiente fecha de asignación de LD",IF(AF8="","",WORKDAY(AF8,IF(AE8="Alta",20,IF(AE8="Media",10,5))))) | AO8: Pendiente | AP8: 13/10 Tras la revisión del documento AR se observa que la información está incompleta.

Sheet Por estimar
A1: Id | B1: Hora de inicio | C1: Hora de finalización | D1: Correo electrónico | E1: Nombre | F1: Título de la INICIATIVA | G1: Objetivo | H1: Institución | I1: VP del área solicitante | J1: Usuario solicitante del negocio | K1: Evidencia de la aprobación del VP o Director | L1: IT BP | M1: Fecha de entrega requerida | N1: Proyecto SPO | O1: Workstream del proyecto SPO | P1: ID SPO | Q1: Tipo de iniciativa | R1: Descripción del problema o desafío | S1: Situación deseada | T1: Procesos y áreas impactadas | U1: Usuarios beneficiados | V1: Pilar estratégico | W1: Estabilización de procesos SIS | X1: Beneficio cuantitativo (anual) | Y1: Beneficios cualitativos | Z1: Adjuntos | AA1: Puntaje Sugerido | AB1: Líder de Dominio | AC1: Asignado por | AD1: Fecha de asignación del LD | AE1: Complejidad | AF1: Fecha inicio (estimación) | AG1: Fecha fin (estimación) | AH1: Tiempo estimado (meses) | AI1: Costo total dolares | AJ1: Costo total Soles | AK1: Supuestos | AL1: Recursos internos o externos | AM1: Indicar si es Proyecto o Requerimiento no catalogado | AN1: Funcionalidad nueva (SI/NO) | AO1: Estatus Estimación | AP1: Comentarios
A2: 135 | B2: 46148.721 | C2: 46148.761 | D2: franco.vera@laureate.pe | E2: Franco Manuel Vera Sanchez | F2: Depuración de RPA ineficientes | G2: Necesitamos asegurar el retiro de 10 RPA deficientes, para ejecutar un plan de acción definido (rediseño de procesos, desarrollo, integración), logrando quedarnos sólo con los RPA justificados, según Plan de Trabajo realizado. | H2: LAU | I2: Humberto Marotta - Tecnologías y transformación digital | J2: Christian Quiroz | K2: https://educorpperu-my.sharepoint.com/personal/diana_zapata_laureate_pe1/Documents/Aplicaciones/Microsoft%20Forms/REGISTRO%20DE%20INICIATIVAS%20-%20GESTI%C3%93N%20DE%20LA%20DEMANDA%20(2%201/Pregunta/VB%20Humberto_RPA_Franco%20Manuel%20Vera%20S.png | L2: Gerson Vereau | M2: 46203 | N2: No | O2: 0 | Q2: Otro | R2: Los RPA identificados presentan bajos indicadores de efectividad o no son la solución más adecuada, lo que podría comprometer la continuidad y estabilidad de la operación. Aspectos identificados: Valor del proceso Calidad y arquitectura técnica Operación, riesgos y gobierno | S2: Se aplicará Plan de Acción para los 10 procesos (RPA ineficientes) que abarca: - Rediseño de Procesos - Desarrollo - Integración | T2: Académicos y de operaciones | U2: Ninguno | V2: Excelencia operativa | W2: NO | X2: No cuantificado o S/0 | Y2: Elevar el grado de alineamiento de los RPA y la optimización del modelo de automatización en UPN y UPC. | Z2: https://educorpperu-my.sharepoint.com/personal/diana_zapata_laureate_pe1/_layouts/15/Doc.aspx?sourcedoc=%7B24A1BDF7-9308-49FC-8068-7E45AEA5D050%7D&file=Status%20RPA%202026-04-01_Franco%20Manuel%20Vera%20S.pptx&action=edit&mobileredirect=true | AA2: 0.45 | AB2: Nicolas Morales | AC2: AM | AD2: 46149 | AE2: Alta | AF2: 46163 | AG2: 46308 | AO2: En proceso | AP2: 28/09: Se tiene sesión con los usuarios en la tardede hoy. Aún faltaría una sesión más para cerrar el alcance y poder estimar. Se solicitará una semana más de plazo. 30/07: Se ha solicitado a Alex Rivera el cambio de la fecha fin de estimación para el 20/08 debido a que se está priorizando actividades para la matrícula de Agosto. 25/06 Nicolas solicita cambio de fecha fin de estimación Motivo: Se está priorizando la reestimación de 9 iniciativas de la SPO, debido a que se solicita desviación del 10%
A3: 142 | B3: 46153.366 | C3: 46153.405 | D3: angela.lucano@laureate.pe | E3: Angela Lucano Carranza | F3: Implementación de WEB SICA 2.0: Plataforma Centralizada de Gestión y Consulta de Documentación Oficial UPC | G3: Necesitamos implementar una nueva plataforma WEB SICA 2.0 para centralizar, gestionar y publicar la documentación oficial vigente de la UPC, permitiendo el acceso público y privado según el tipo de documento, búsquedas avanzadas y actualización eficiente de versiones y enlaces, para que alumnos, académicos, administrativos, auditores y demás stakeholders puedan acceder de manera rápida, segura y confiable a información oficial actualizada, logrando continuidad operativa en procesos críticos como matrícula, auditorías ISO y cumplimiento normativo, además de habilitar futuras mejoras tecnológicas e integraciones de seguridad como doble autenticación. | H3: UPC | I3: Milagros Morgan - Rectorado UPC | J3: Daniel Ticona | K3: https://educorpperu-my.sharepoint.com/personal/diana_zapata_laureate_pe1/Documents/Aplicaciones/Microsoft%20Forms/REGISTRO%20DE%20INICIATIVAS%20-%20GESTI%C3%93N%20DE%20LA%20DEMANDA%20(2%201/Pregunta/RE_%20Requerimiento%20-%20Web%20SICA%202.0_Angela%20Lucano%20Carran.pdf | L3: Gerson Vereau | M3: 46249 | N3: No | O3: 0 | Q3: Seguridad de la información | R3: La UPC actualmente cuenta con un sistema WEB SICA que presenta limitaciones técnicas y funcionales debido a la falta de soporte y capacidad de evolución tecnológica . Esto dificulta la gestión eficiente de documentación oficial vigente, la implementación de mejoras de seguridad como doble autenticación (MFA) y la automatización de procesos relacionados con la publicación y actualización documental. Además, la experiencia de búsqueda y acceso a documentos no responde adecuadamente a las necesidades actuales de los diferentes stakeholders de la universidad. | S3: Se requiere implementar WEB SICA 2.0 como una plataforma moderna, centralizada y de fácil administración que permita publicar documentación oficial vigente de manera segura y eficiente. El sistema debe ofrecer búsquedas avanzadas por palabras clave, procesos, tipos y categorías de documentos, mantener URLs estables para evitar enlaces rotos, permitir controlar la visibilidad pública o privada desde ISOTOOLS y garantizar que los documentos públicos puedan ser consultados sin necesidad de autenticación. Además, debe brindar una experiencia visual intuitiva y preparada para futuras integraciones tecnológicas y de seguridad. | T3: Mapa de procesos de la UPC (SICA) | U3: Administrativos | V3: Excelencia operativa | W3: NO | X3: No cuantificado o S/0 | Y3: - Mejora en la experiencia de usuario mediante una plataforma más visual, intuitiva y moderna. - Mayor confiabilidad y transparencia de la documentación institucional publicada. - Fortalecimiento del cumplimiento normativo y de estándares de calidad institucional. - Mayor seguridad y control de acceso mediante manejo de documentos públicos y privados. - Mejora de la imagen institucional frente a estudiantes, auditores y entidades reguladoras. - Facilidad para futuras integraciones tecnológicas y automatizaciones. - Mayor gobernanza documental y trazabilidad de información oficial. - Continuidad operativa en procesos críticos como matrícula y auditorías institucionales. | Z3: https://educorpperu-my.sharepoint.com/personal/diana_zapata_laureate_pe1/_layouts/15/Doc.aspx?sourcedoc=%7BEBF8DE0E-5856-4C7A-A79E-3735E4A457A7%7D&file=Solicitud%20de%20requerimientos%20Idea%20nueva%20y%20mejo_Angela%20Lucano%20Carran%204.pptx&action=edit&mobileredirect=true; https://educorpperu-my.sharepoint.com/personal/diana_zapata_laureate_pe1/_layouts/15/Doc.aspx?sourcedoc=%7B05A05F7B-A6B9-4C46-9DCF-B8DB6F244B99%7D&file=WEB%20SICA%20DEFINICION_Angela%20Lucano%20Carran.pptx&action=edit&mobileredirect=true | AA3: 1.35 | AB3: Hugo Vega | AC3: AM | AD3: 46156 | AE3: Alta | AF3: 46296 | AG3: =IF(AD3="","Pendiente fecha de asignación de LD",IF(AF3="","",WORKDAY(AF3,IF(AE3="Alta",20,IF(AE3="Media",10,5))))) -> 46324 | AH3: 4 | AJ3: 200000 | AL3: Externos | AM3: Es un proyecto nuevo | AN3: Si | AO3: Pendiente | AP3: Esta aplicación se tiene que re-hacer e incluir las nuevas funcionalidades solicitadas por el usuario
A4: 174 | B4: 46167.833 | C4: 46167.866 | D4: angela.lucano@laureate.pe | E4: Angela Lucano Carranza | F4: UPN - Unificar la respuesta del caso y la encuesta de satisfacción por la atención | G4: Necesitamos integrar automáticamente el link de la encuesta de satisfacción dentro del mismo correo de respuesta enviado desde el CRM después de la atención al alumno, para centralizar la comunicación con el estudiante y simplificar su interacción, logrando incrementar la tasa de respuesta de encuestas, mejorar la representatividad y confiabilidad del NPS/CSAT, y optimizar la toma de decisiones basada en feedback real. | H4: UPN | I4: Mónica García - VP Operaciones Digitales y Online | J4: Lizbeth Bautista | K4: https://educorpperu-my.sharepoint.com/personal/diana_zapata_laureate_pe1/Documents/Aplicaciones/Microsoft%20Forms/REGISTRO%20DE%20INICIATIVAS%20-%20GESTI%C3%93N%20DE%20LA%20DEMANDA%20(2%201/Pregunta/Luis%20Roncal%20-%20VB%20Requerimientos%20priorizados%20L_Angela%20Lucano%20Carran%203.pdf | L4: Ángela Lucano | M4: 46203 | N4: No | O4: 0 | P4: 0 | Q4: Otro | R4: Actualmente, el estudiante recibe dos correos separados: uno con la respuesta a su caso y otro independiente con la encuesta de satisfacción. Esta dispersión genera pérdida de interacción y una baja tasa de respuesta (4%), afectando la representatividad de los indicadores de experiencia del estudiante y limitando la calidad de la información utilizada para la toma de decisiones. | S4: Que el CRM incorpore automáticamente el link único de encuesta dentro del mismo correo de respuesta del asesor, eliminando el envío de correos separados y permitiendo que la encuesta pueda responderse una sola vez. Además, se busca estandarizar el formato de comunicación para brindar una experiencia más simple, integrada y eficiente para el estudiante. | T4: Proceso de atención y respuesta de consultas en CRM (cierre de tickets y medición de satisfacción) Estudiantes que utilizan la ticketera de Contacto UPN, asesores de atención, equipo de Experiencia del Estudiante y áreas de Calidad Todas las áreas que interactúan en Contacto UPN (13 áreas). | U4: Alumnos | V4: Experiencia | W4: No | X4: No cuantificado o S/0 | Y4: Centralización de la comunicación en un solo correo. Mejora de la experiencia del estudiante al reducir pasos e interacción innecesaria. Incremento en la participación de encuestas gracias a una interacción más directa y contextual. Mayor confiabilidad y representatividad de indicadores NPS/CSAT. Optimización operativa y reducción de carga en el envío de correos. Mejora en la calidad de la información para análisis y toma de decisiones. Estandarización de la comunicación enviada desde el CRM. | Z4: https://educorpperu-my.sharepoint.com/personal/diana_zapata_laureate_pe1/_layouts/15/Doc.aspx?sourcedoc=%7BE433D766-B8B3-4448-8F99-56194F5A6868%7D&file=Requerimiento_Integraci%C3%B3n%20Encuestas%20en%20Respue_Angela%20Lucano%20Carran.pptx&action=edit&mobileredirect=true | AA4: 1.3 | AB4: César Soplín | AC4: AM | AD4: 46169 | AE4: Media | AF4: 46195 | AG4: =IF(AD4="","Pendiente fecha de asignación de LD",IF(AF4="","",WORKDAY(AF4,IF(AE4="Alta",20,IF(AE4="Media",10,5))))) -> 46209 | AL4: Internos / Externos | AM4: NO BAU | AN4: Si | AO4: En proceso | AP4: Debe definirse el almacenamiento. No debe almacenarse data en FTPs o similares. Debe usarse Datalake.
A5: 185 | B5: 46169.53 | C5: 46169.532 | D5: carlos.sanchez@laureate.pe | E5: Carlos Sanchez Rubio | F5: Microsegmentación / Nanosegmentación de Aplicaciones Críticas | G5: Implementar microsegmentación / nanosegmentación en aplicaciones críticas, para limitar comunicaciones no autorizadas y contener movimientos laterales dentro de la red, logrando reducir la superficie de ataque y mejorar la resiliencia frente a incidentes de ciberseguridad. | H5: CORP | I5: Humberto Marotta - Tecnologías y transformación digital | J5: Carlos Sanchez | K5: https://educorpperu-my.sharepoint.com/personal/diana_zapata_laureate_pe1/Documents/Aplicaciones/Microsoft%20Forms/REGISTRO%20DE%20INICIATIVAS%20-%20GESTI%C3%93N%20DE%20LA%20DEMANDA%20(2%201/Pregunta/Implementaci%C3%B3n%20Microsegmentaci%C3%B3n%20Illumio_Carlos%20Sanchez%20Rubio%204.pdf | L5: Gerson Vereau | M5: 46356 | N5: No | O5: 0 | P5: 0 | Q5: Seguridad de la informaciónSeguridad de la información | R5: Actualmente, las comunicaciones entre componentes o ambientes pueden ser más amplias de lo necesario. Esto facilita propagación de amenazas, movimientos laterales y mayores impactos ante el compromiso de un activo. Los controles de red existentes protegen a nivel perimetral o por segmentos amplios, pero no necesariamente restringen de forma granular las comunicaciones entre cargas, aplicaciones o servidores críticos. | S5: Las aplicaciones críticas deben operar con reglas de comunicación mínimas necesarias, controladas a nivel granular, permitiendo únicamente el tráfico explícitamente autorizado entre componentes. | T5: Infraestructura Aplicaciones en alcance: - Active Directories | U5: Todos | V5: Excelencia operativa | W5: No | X5: Mayor a S/500,000.00 | Y5: Fortalece la arquitectura de seguridad, mejora la contención de amenazas y reduce la superficie de ataque en entornos críticos. Incrementa la resiliencia tecnológica y mejora la capacidad de protección de servicios sensibles del negocio. | Z5: https://educorpperu-my.sharepoint.com/personal/diana_zapata_laureate_pe1/Documents/Aplicaciones/Microsoft%20Forms/REGISTRO%20DE%20INICIATIVAS%20-%20GESTI%C3%93N%20DE%20LA%20DEMANDA%20(2%201/Adjuntar%20sustentos%20que%20ayuden%20al%20entendimiento%20de/ADP-%20Laureate%20Education_Carlos%20Sanchez%20Rubio%204.pdf | AA5: 1.8 | AB5: Johnnel Ayala | AC5: AM | AD5: 46169 | AE5: Media | AF5: 46230 | AG5: =IF(AD5="","Pendiente fecha de asignación de LD",IF(AF5="","",WORKDAY(AF5,IF(AE5="Alta",20,IF(AE5="Media",10,5))))) -> 46244 | AO5: Pendiente
A6: 234 | B6: 46190.419 | C6: 46190.426 | D6: marco.pezo@laureate.pe | E6: Marco Pezo Huillca | F6: PRB0043036 Revisión de caídas de alto relacionadas a pase a producción por desarrollo | G6: Necesitamos implementar un plan macro que estandarice pruebas, documentación y homologación de ambientes en los pases a producción, para que se elimine la recurrencia de incidentes de alto impacto ocasionados por cambios mal planteados, pruebas insuficientes o diferencias entre ambientes, logrando mayor estabilidad en los sistemas críticos, reducción de riesgos operativos y confianza del negocio en la continuidad de sus procesos. | H6: LAU | I6: Humberto Marotta - Tecnologías y transformación digital | J6: Ernesto Barrón | K6: https://educorpperu-my.sharepoint.com/personal/diana_zapata_laureate_pe1/Documents/Aplicaciones/Microsoft%20Forms/REGISTRO%20DE%20INICIATIVAS%20-%20GESTI%C3%93N%20DE%20LA%20DEMANDA%20(2%201/Pregunta/PRB0043036%20Acuerdos%20RE_%20Revisi%C3%B3n%20de%20ca%C3%ADdas%20de_Marco%20Pezo%20Huillca.pdf | L6: Gerson Vereau | M6: 46219 | N6: No | O6: 0 | P6: 0 | Q6: ITSM (Servicios TI) | R6: Hoy en día, los pases a producción están generando caídas de alto impacto en sistemas críticos, con 9 incidentes registrados en lo que va del 2026. Las causas principales son diferencias entre ambientes de desarrollo y producción, pruebas insuficientes, documentación incompleta y requerimientos poco detallados del negocio. Esto impacta directamente al negocio porque provoca interrupciones en servicios como Banner y procesos académicos, obliga a realizar correcciones urgentes en horarios nocturnos, incrementa el riesgo operativo y disminuye la confianza del usuario en la estabilidad de las aplicaciones. | S6: Situación deseada Necesitamos establecer un plan macro de control en los pases a producción, con ambientes homologados y pruebas estandarizadas, para que se reduzca la recurrencia de caídas de alto impacto y se eliminen errores derivados de diferencias entre entornos o documentación incompleta, logrando mayor estabilidad en sistemas críticos como Banner, continuidad operativa sin interrupciones y confianza del negocio en la calidad de los cambios implementados. | T6: Todas las áreas que soliciten un cambio, que implique que el equipo de Soluciones y aplicaciones desarrolle y necesite un pase a producción que pueda impactar en una aplicación critica | U6: Todos | V6: Excelencia operativa | W6: No | X6: No cuantificado o S/0 | Y6: Mayor estabilidad operativa en sistemas críticos como Banner y procesos académicos. Incremento en la confianza del negocio al reducir la recurrencia de caídas por pases a producción. Mejor experiencia de usuario al evitar interrupciones y correcciones urgentes fuera de horario. Fortalecimiento de la gobernanza de cambios mediante pruebas estandarizadas y documentación completa. Reducción de la incertidumbre operativa al contar con ambientes homologados y controlados. | Z6: https://educorpperu-my.sharepoint.com/personal/diana_zapata_laureate_pe1/_layouts/15/Doc.aspx?sourcedoc=%7BB4E5B08F-C313-443B-A674-EAEFB2CF90A2%7D&file=PRB0043036%20Ca%C3%ADdas%20de%20servicio%20luego%20de%20cambio_Marco%20Pezo%20Huillca.xlsx&action=default&mobileredirect=true | AA6: 2.1 | AB6: Johnny Rodriguez | AC6: AM | AD6: 46197 | AG6: =IF(AD6="","Pendiente fecha de asignación de LD",IF(AF6="","",WORKDAY(AF6,IF(AE6="Alta",20,IF(AE6="Media",10,5))))) | AO6: Pendiente
A7: 236 | B7: 46190.426 | C7: 46190.495 | D7: marco.pezo@laureate.pe | E7: Marco Pezo Huillca | F7: PRB0043077 Revisión del aplicaciones alojadas en el servidor PEAWSBDPW06 | G7: Necesitamos independizar las aplicaciones críticas y optimizar la ejecución de queries y ETLs en el servidor, para que se eliminen las caídas recurrentes que afectan múltiples servicios académicos y administrativos por consumo excesivo de recursos, logrando mayor estabilidad operativa, continuidad de los portales y confianza del negocio en la disponibilidad de sus aplicaciones críticas. | H7: UPN | I7: Humberto Marotta - Tecnologías y transformación digital | J7: Ernesto Barrón | K7: https://educorpperu-my.sharepoint.com/personal/diana_zapata_laureate_pe1/Documents/Aplicaciones/Microsoft%20Forms/REGISTRO%20DE%20INICIATIVAS%20-%20GESTI%C3%93N%20DE%20LA%20DEMANDA%20(2%201/Pregunta/Acuerdos%20PRB0043077%20IMPORTANTE%20Revisi%C3%B3n%20del%20a_Marco%20Pezo%20Huillca.pdf | L7: Gerson Vereau | M7: 46219 | N7: No | O7: 0 | P7: 0 | Q7: ITSM (Servicios TI) | R7: Hoy en día, el servidor 06 concentra múltiples aplicaciones críticas (intranet, portales académicos, pagos, CRM), lo que ha generado 14 caídas en los últimos 6 meses. Las caídas ocurren porque los recursos del servidor se saturan cuando se ejecutan ETLs en paralelo o queries pesados, provocando que todas las aplicaciones alojadas se caigan simultáneamente. Esto impacta directamente al negocio porque interrumpe servicios académicos y administrativos, obliga a aplicar soluciones paliativas urgentes en horarios nocturnos, incrementa el riesgo operativo y reduce la confianza de los usuarios en la estabilidad de los sistemas institucionales. | S7: Necesitamos separar las aplicaciones críticas y ordenar la ejecución de queries y ETLs en servidores dedicados, para que se eliminen las caídas recurrentes por saturación de recursos y se evite que un fallo afecte transversalmente a todos los servicios, logrando continuidad operativa en portales académicos y administrativos, mayor disponibilidad de aplicaciones críticas y confianza del negocio en la estabilidad de la infraestructura. | T7: todas las áreas que cuenten con aplicaciones alojadas en el servidor 06 | U7: Todos | V7: Excelencia operativa | W7: No | X7: No cuantificado o S/0 | Y7: La separación de aplicaciones críticas y la optimización de queries y ETLs permitirá reducir las caídas recurrentes, brindando mayor estabilidad operativa, continuidad en portales académicos y administrativos, mejor experiencia de usuario al evitar interrupciones, fortalecimiento de la gobernanza de infraestructura y confianza del negocio en la disponibilidad de sus sistemas. | Z7: https://educorpperu-my.sharepoint.com/personal/diana_zapata_laureate_pe1/Documents/Aplicaciones/Microsoft%20Forms/REGISTRO%20DE%20INICIATIVAS%20-%20GESTI%C3%93N%20DE%20LA%20DEMANDA%20(2%201/Adjuntar%20sustentos%20que%20ayuden%20al%20entendimiento%20de/RE%20PRB0043077%20IMPORTANTE%20Revisi%C3%B3n%20del%20aplicac_Marco%20Pezo%20Huillca.pdf | AA7: 2.1 | AB7: Nicolas Morales | AC7: JR | AD7: 46197 | AE7: Alta | AF7: 46238 | AG7: 46300 | AO7: Pendiente | AP7: 28/09: Estamos a la espera de la cotización del proveedor Stefanini. 18/09 Se realizó la presentación al proveedor para explicar la problemática con la finalidad de que ellos puedan gestionar la planificación de actividades. '- Se iniciará luego de la estimación de Horacius
A8: 231 | B8: 46188.751 | C8: 46189.521 | D8: nicolas.morales@laureate.pe | E8: Nicolas Morales Chumpitaz | F8: Lean + IA - Gestión de egreso GyT - Digitalización y automatización de la venta de egreso y bachiller, y la generación de la constancia de egreso | G8: Obtener su egreso y posteriormente su bachiller de manera simple, digital y sin fricciones, con visibilidad clara del estado de su trámite, sin reprocesos ni seguimiento manual, y con su diploma disponible oportunamente cuando cumple los requisitos | H8: UPC | I8: Milagros Morgan - Rectorado UPC | J8: Diego Vega | K8: https://educorpperu-my.sharepoint.com/personal/diana_zapata_laureate_pe1/Documents/Aplicaciones/Microsoft%20Forms/REGISTRO%20DE%20INICIATIVAS%20-%20GESTI%C3%93N%20DE%20LA%20DEMANDA%20(2%201/Pregunta/G%26T%20UPC%20-%20UPN_Nicolas%20Morales%20Chum.png | L8: Ángela Lucano | M8: 46387 | N8: Si | O8: G&A | P8: 76557 | Q8: Otro | R8: Defectos: Solicitudes devueltas por: documentos faltantes, errores de registro, datos inconsistentes. Correcciones manuales posteriores. Sobreprocesamiento: Validación manual repetida de: requisitos académicos, pagos, estados del estudiante. Revisión caso por caso cuando las reglas son estándar. Transporte: Uso de correos, Excel, carpetas compartidas y sistema académico. Copia/pega de información entre plataformas no integradas. Espera: Múltiples revisiones académicas y administrativas en cadena. Casos detenidos en bandejas sin SLA visible. Talento No Utilizado: Analistas dedicados a: validaciones básicas, carga de información, seguimiento manual. Poco tiempo para análisis, mejora o control. | S8: asdada | T8: Activación del interés del estudiante por egreso y bachiller: - Segmentación inteligente (próximos a egreso) - Identificación de estudiantes próximos de 8°, 9° y 10° (riesgo y progreso) - Comunicación proactiva personalizada - Habilitación y notificación de activación del trámite de Egreso/Bachiller Solicitud del trámite de egreso/bachiller - Generación del trámite E/B, realizar pago y adjuntar foto - Validación de fotografía + datos personales - Registro de condición de egreso (Ejecución de procesos masivos banner) - Generación y registro de libro, folio y tomo de egresado (información que se registra en la constancia de egreso) - Ajuste de CAPP (Ejecución de procesos masivos banner) Generación de la constancia de egreso - Notificación de obtención de la condición de Egreso al estudiante - Generación y pago del trámite - Generación y entrega digital de la constancias de Egreso - Notificación de estudiantes con egreso al equipo de Marketing/Eventos Institucionales Generación del diploma bachiller Comunicación de requisitos pendientes para Bachiller Migración de datos del trámite del edstudiante Generar resolución rectoral y solicitud de datos Registrar el N° de resolución, fecha de resolución rectoral y otros datos propios de la institución Solicitar firma de Resolución Rectoral Firma de la resolución rectoral | U8: Alumnos | V8: Excelencia operativa | W8: No | X8: Mayor a S/500,000.00 | Y8: Liberación de horas operativas Incremento del NPS del estudiante Reducción de SLA | Z8: https://educorpperu-my.sharepoint.com/personal/diana_zapata_laureate_pe1/Documents/Aplicaciones/Microsoft%20Forms/REGISTRO%20DE%20INICIATIVAS%20-%20GESTI%C3%93N%20DE%20LA%20DEMANDA%20(2%201/Adjuntar%20sustentos%20que%20ayuden%20al%20entendimiento%20de/Resultados%20Taller%20Cocreaci%C3%B3n_Gesti%C3%B3n%20de%20Egres_Nicolas%20Morales%20Chum.pdf | AA8: 3.3 | AB8: Hugo Vega | AC8: AM | AD8: 46296 | AE8: Alta | AF8: 46218 | AG8: =IF(AD8="","Pendiente fecha de asignación de LD",IF(AF8="","",WORKDAY(AF8,IF(AE8="Alta",20,IF(AE8="Media",10,5))))) -> 46246 | AL8: Externos | AM8: Proyecto | AN8: SI | AO8: En proceso | AP8: 01/10 NM, solitcita cambio de LD , se asigna a Hugo Vega 30/07: On hold hasta que se resuelva la dependencia con Digital Tech. Sebastián L. convocará a reunión para priorización de las estimaciones. 16/07: On hold, por dependencia de Digital Tech 02/07: La estimación iniciará el 15/07 ya que se está priorizando la reestimación de 10 requerimientos anteriores. La fecha fin de la estimación aún no puede brindarse debido a que la complejidad supera a los criteros definidos a "Alta". Por otro lado se valida participación de Aceleradora, por motivo de que está abordando trámites para el alumno en UPC, además, se empezó la validación de priorización con el equipo de Aceleradora para la estimación.
A9: 237 | B9: 46190.525 | C9: 46190.539 | D9: nicolas.morales@laureate.pe | E9: Nicolas Morales Chumpitaz | F9: Lean + IA - Gestión de egreso GyT - Trámite de titulación UPC | G9: Necesitamos que el estudiante pueda obtener su Título Profesional de manera simple y sin fricciones, con claridad sobre si debe seguir el trámite directo o un programa de titulación, con visibilidad del estado de su proceso, sin reprocesos ni seguimientos manuales, y con su diploma disponible oportunamente cuando cumple los requisitos. | H9: UPC | I9: Milagros Morgan - Rectorado UPC | J9: Diego Vega | K9: https://educorpperu-my.sharepoint.com/personal/diana_zapata_laureate_pe1/Documents/Aplicaciones/Microsoft%20Forms/REGISTRO%20DE%20INICIATIVAS%20-%20GESTI%C3%93N%20DE%20LA%20DEMANDA%20(2%201/Pregunta/G%26T%20UPC%20-%20UPN_Nicolas%20Morales%20Chum%201.png | L9: Ángela Lucano | M9: 46387 | N9: Si | O9: G&A | P9: 76557 | Q9: Otro | R9: Defectos Solicitudes devueltas por: documentos faltantes, errores de registro, datos inconsistentes. Correcciones manuales posteriores. Sobreprocesamiento Validación manual repetida de: requisitos académicos, pagos, estados del estudiante. Revisión caso por caso cuando las reglas son estándar. Transporte Uso de correos, Excel, carpetas compartidas y sistema académico. Copia/pega de información entre plataformas no integradas. Espera Validación de requisitos Revisión de tesis / trabajo Talento No Utilizado Analistas dedicados a: validaciones básicas, carga de información, seguimiento manual. Poco tiempo para análisis, mejora o control. | S9: Generar solicitud de aprobación de tema de tesis o de suficiencia profesional// Validación de formato, titulo, otros// Envío de solicitudes a responsables académicos// Revisar, evaluar tema de tesis y brindar respuesta (informe)// Asignación de asesor académico// Brindar respuesta de la solicitud// Solicitud de asesorías // Realizar pago// Recibir solicitud y asignar asesor // Elaboración de la tesis o suficiencia profesional// Solicitud de ampliación// Revisión final del trabajo + VB// Solicitud de sustentación + carga de documentos + pago// Revisión de documentos// VB final por parte del asesor// Revisión de la versión final de la tesis o trabajo (bucle)// Asignación de jurados, fecha y hora de sustentación// Sustentación// Registro de resultados – Acta de sustentación// Publicación de trabajo en repositorio y emisión de handle// PROCESO: Expedición de titulo profesional// Trazabilidad integral | T9: Grados y Títulos | U9: Alumnos | V9: Excelencia operativa | W9: No | X9: Mayor a S/500,000.00 | Y9: Liberación de horas operativas Mayor eficiencia en horas y opex Incremento del NPS del estudiante Reducción de SLA | Z9: https://educorpperu-my.sharepoint.com/personal/diana_zapata_laureate_pe1/_layouts/15/Doc.aspx?sourcedoc=%7B59108DC4-BCFB-45D2-921E-F5F5AABCFCF6%7D&file=Resultados%20Taller%20Cocreaci%C3%B3n_Gesti%C3%B3n%20de%20Egres_Nicolas%20Morales%20Chum.pptx&action=edit&mobileredirect=true | AA9: 3.3 | AB9: Hugo Vega | AC9: AM | AD9: 46296 | AE9: Alta | AF9: 46218 | AG9: =IF(AD9="","Pendiente fecha de asignación de LD",IF(AF9="","",WORKDAY(AF9,IF(AE9="Alta",20,IF(AE9="Media",10,5))))) -> 46246 | AL9: Externos | AM9: Proyecto | AN9: SI | AO9: En proceso | AP9: 01/10 NM, solitcita cambio de LD , se asigna a Hugo Vega 30/07: On hold hasta que se resuelva la dependencia con Digital Tech. Sebastián L. convocará a reunión para priorización de las estimaciones. 16/07: On hold, por dependencia de Digital Tech 02/07: Se estimará en paquete junto al Id 231
A10: 238 | B10: 46190.539 | C10: 46190.546 | D10: nicolas.morales@laureate.pe | E10: Nicolas Morales Chumpitaz | F10: Lean + IA - Gestión de egreso GyT - Venta y programa de titulación UPC | G10: Que el alumno obtenga su Título Profesional de manera simple y sin fricciones, con claridad sobre si debe seguir el trámite directo o un programa de titulación, con visibilidad del estado de su proceso, sin reprocesos ni seguimientos manuales, y con su diploma disponible oportunamente cuando cumple los requisitos. | H10: UPC | I10: Milagros Morgan - Rectorado UPC | J10: Diego Vega | K10: https://educorpperu-my.sharepoint.com/personal/diana_zapata_laureate_pe1/Documents/Aplicaciones/Microsoft%20Forms/REGISTRO%20DE%20INICIATIVAS%20-%20GESTI%C3%93N%20DE%20LA%20DEMANDA%20(2%201/Pregunta/RE%20SPO%20Iniciativa%20Productividad%20WeTalk%20cLEAN_Nicolas%20Morales%20Chum%204.png | L10: Ángela Lucano | M10: 46387 | N10: Si | O10: G&A | P10: 76557 | Q10: Otro | R10: Defectos Solicitudes devueltas por: documentos faltantes, errores de registro, datos inconsistentes. Correcciones manuales posteriores. Sobreprocesamiento Validación manual repetida de: requisitos académicos, pagos, estados del estudiante. Revisión caso por caso cuando las reglas son estándar. Transporte Uso de correos, Excel, carpetas compartidas y sistema académico. Copia/pega de información entre plataformas no integradas. Espera Validación de requisitos Revisión de tesis / trabajo Talento No Utilizado Analistas dedicados a: validaciones básicas, carga de información, seguimiento manual. Poco tiempo para análisis, mejora o control. | S10: Identificación de los estudiantes para TSP// Envío de comunicaciones para promover la matrícula en el programa// Realizar pago// Auto matrícula en el programa// Envío de detalle para el inicio de clases (sección, aula virtual)// Ejecución de clases y asignación de asesores// Validación del trabajo versión final y generación de resultados// Revisión final del trabajo (acta de conformidad de trabajo)// Revisión de la versión final de la tesis o trabajo (bucle)// Asignación de jurados y la fecha y hora de sustentación// Sustentación// Registro de resultados – Acta de sustentación// Publicación de trabajo en repositorio y emisión de handle// PROCESO: Expedición de titulo profesional// Trazabilidad integral | T10: Grados y Títulos - Venta y programa de Titulación en UPC | U10: Alumnos | V10: Excelencia operativa | W10: No | X10: Mayor a S/500,000.00 | Y10: Liberación de horas operativas Mayor eficiencia en horas y opex Incremento del NPS del estudiante Reducción de SLA | Z10: https://educorpperu-my.sharepoint.com/personal/diana_zapata_laureate_pe1/_layouts/15/Doc.aspx?sourcedoc=%7B83B028A3-350B-4FFD-B8F6-5DB34F887832%7D&file=Resultados%20Taller%20Cocreaci%C3%B3n_Gesti%C3%B3n%20de%20Egres_Nicolas%20Morales%20Chum%201.pptx&action=edit&mobileredirect=true | AA10: 3.3 | AB10: Hugo Vega | AC10: AM | AD10: 46296 | AE10: Alta | AF10: 46218 | AG10: =IF(AD10="","Pendiente fecha de asignación de LD",IF(AF10="","",WORKDAY(AF10,IF(AE10="Alta",20,IF(AE10="Media",10,5))))) -> 46246 | AL10: Externos | AM10: Proyecto | AN10: SI | AO10: En proceso | AP10: 01/10 NM, solitcita cambio de LD , se asigna a Hugo Vega 30/07: On hold hasta que se resuelva la dependencia con Digital Tech. Sebastián L. convocará a reunión para priorización de las estimaciones. 16/07: On hold, por dependencia de Digital Tech 02/07: Se estimará en paquete junto al Id 231
